Workbook

Sheet reporting conso 4 batiments
F2: 2025 | G2: 2025 | H2: 2025 | I2: 2025 | J2: 2025 | K2: 2025 | L2: 2025 | M2: 2025 | N2: 2025 | O2: 2025 | P2: 2025 | Q2: 2025 | R2: 2025 | S2: 2026 | T2: 2026 | U2: 2026 | V2: 2026 | W2: 2026 | X2: 2026 | Y2: 2026 | Z2: 2026 | AA2: 2026 | AB2: 2026 | AC2: 2026 | AD2: 2026 | AE2: 2026 | AF2: 2027 | AG2: 2027 | AH2: 2027 | AI2: 2027 | AJ2: 2027 | AK2: 2027 | AL2: 2027 | AM2: 2027 | AN2: 2027 | AO2: 2027 | AP2: 2027 | AQ2: 2027 | AR2: 2027 | AS2: 2028 | AT2: 2028 | AU2: 2028 | AV2: 2028 | AW2: 2028 | AX2: 2028 | AY2: 2028 | AZ2: 2028 | BA2: 2028 | BB2: 2028 | BC2: 2028 | BD2: 2028 | BE2: 2028 | BF2: 2029 | BG2: 2029 | BH2: 2029 | BI2: 2029 | BJ2: 2029 | BK2: 2029 | BL2: 2029 | BM2: 2029 | BN2: 2029 | BO2: 2029 | BP2: 2029 | BQ2: 2029 | BR2: 2029 | BS2: 2030 | BT2: 2030 | BU2: 2030 | BV2: 2030 | BW2: 2030 | BX2: 2030 | BY2: 2030 | BZ2: 2030 | CA2: 2030 | CB2: 2030 | CC2: 2030 | CD2: 2030 | CE2: 2030 | CF2: 2031 | CG2: 2031 | CH2: 2031 | CI2: 2031 | CJ2: 2031 | CK2: 2031 | CL2: 2031 | CM2: 2031 | CN2: 2031 | CO2: 2031 | CP2: 2031 | CQ2: 2031 | CR2: 2031 | CS2: 2032 | CT2: 2032 | CU2: 2032 | CV2: 2032 | CW2: 2032 | CX2: 2032 | CY2: 2032 | CZ2: 2032 | DA2: 2032 | DB2: 2032 | DC2: 2032 | DD2: 2032 | DE2: 2032 | DF2: 2033 | DG2: 2033 | DH2: 2033 | DI2: 2033 | DJ2: 2033 | DK2: 2033 | DL2: 2033 | DM2: 2033 | DN2: 2033 | DO2: 2033 | DP2: 2033 | DQ2: 2033 | DR2: 2033
B3: Nombres de sites | C3: 9 | F3: 1 | G3: 2 | H3: 3 | I3: 4 | J3: 5 | K3: 6 | L3: 7 | M3: 8 | N3: 9 | O3: 10 | P3: 11 | Q3: 12 | R3: 2025 | S3: 1 | T3: 2 | U3: 3 | V3: 4 | W3: 5 | X3: 6 | Y3: 7 | Z3: 8 | AA3: 9 | AB3: 10 | AC3: 11 | AD3: 12 | AE3: 2026 | AF3: 1 | AG3: 2 | AH3: 3 | AI3: 4 | AJ3: 5 | AK3: 6 | AL3: 7 | AM3: 8 | AN3: 9 | AO3: 10 | AP3: 11 | AQ3: 12 | AR3: 2027 | AS3: 1 | AT3: 2 | AU3: 3 | AV3: 4 | AW3: 5 | AX3: 6 | AY3: 7 | AZ3: 8 | BA3: 9 | BB3: 10 | BC3: 11 | BD3: 12 | BE3: 2028 | BF3: 1 | BG3: 2 | BH3: 3 | BI3: 4 | BJ3: 5 | BK3: 6 | BL3: 7 | BM3: 8 | BN3: 9 | BO3: 10 | BP3: 11 | BQ3: 12 | BR3: 2029 | BS3: 1 | BT3: 2 | BU3: 3 | BV3: 4 | BW3: 5 | BX3: 6 | BY3: 7 | BZ3: 8 | CA3: 9 | CB3: 10 | CC3: 11 | CD3: 12 | CE3: 2030 | CF3: 1 | CG3: 2 | CH3: 3 | CI3: 4 | CJ3: 5 | CK3: 6 | CL3: 7 | CM3: 8 | CN3: 9 | CO3: 10 | CP3: 11 | CQ3: 12 | CR3: 2031 | CS3: 1 | CT3: 2 | CU3: 3 | CV3: 4 | CW3: 5 | CX3: 6 | CY3: 7 | CZ3: 8 | DA3: 9 | DB3: 10 | DC3: 11 | DD3: 12 | DE3: 2032 | DF3: 1 | DG3: 2 | DH3: 3 | DI3: 4 | DJ3: 5 | DK3: 6 | DL3: 7 | DM3: 8 | DN3: 9 | DO3: 10 | DP3: 11 | DQ3: 12 | DR3: 2033
F4: =EOMONTH(DATE(F2,F3,1),0) -> 45688 | G4: =EOMONTH(DATE(G2,G3,1),0) -> 45716 | H4: =EOMONTH(DATE(H2,H3,1),0) -> 45747 | I4: =EOMONTH(DATE(I2,I3,1),0) -> 45777 | J4: =EOMONTH(DATE(J2,J3,1),0) -> 45808 | K4: =EOMONTH(DATE(K2,K3,1),0) -> 45838 | L4: =EOMONTH(DATE(L2,L3,1),0) -> 45869 | M4: =EOMONTH(DATE(M2,M3,1),0) -> 45900 | ... Q4: =EOMONTH(DATE(Q2,Q3,1),0) -> 46022 | R4: =R3 -> 2025 | S4: =EOMONTH(DATE(S2,S3,1),0) -> 46053 | T4: =EOMONTH(DATE(T2,T3,1),0) -> 46081 | U4: =EOMONTH(DATE(U2,U3,1),0) -> 46112 | V4: =EOMONTH(DATE(V2,V3,1),0) -> 46142 | W4: =EOMONTH(DATE(W2,W3,1),0) -> 46173 | X4: =EOMONTH(DATE(X2,X3,1),0) -> 46203 | Y4: =EOMONTH(DATE(Y2,Y3,1),0) -> 46234 | Z4: =EOMONTH(DATE(Z2,Z3,1),0) -> 46265 | ... AD4: =EOMONTH(DATE(AD2,AD3,1),0) -> 46387 | AE4: =AE3 -> 2026 | AF4: =EOMONTH(DATE(AF2,AF3,1),0) -> 46418 | AG4: =EOMONTH(DATE(AG2,AG3,1),0) -> 46446 | AH4: =EOMONTH(DATE(AH2,AH3,1),0) -> 46477 | AI4: =EOMONTH(DATE(AI2,AI3,1),0) -> 46507 | AJ4: =EOMONTH(DATE(AJ2,AJ3,1),0) -> 46538 | AK4: =EOMONTH(DATE(AK2,AK3,1),0) -> 46568 | AL4: =EOMONTH(DATE(AL2,AL3,1),0) -> 46599 | AM4: =EOMONTH(DATE(AM2,AM3,1),0) -> 46630 | ... AQ4: =EOMONTH(DATE(AQ2,AQ3,1),0) -> 46752 | AR4: =AR3 -> 2027 | AS4: =EOMONTH(DATE(AS2,AS3,1),0) -> 46783 | AT4: =EOMONTH(DATE(AT2,AT3,1),0) -> 46812 | AU4: =EOMONTH(DATE(AU2,AU3,1),0) -> 46843 | AV4: =EOMONTH(DATE(AV2,AV3,1),0) -> 46873 | AW4: =EOMONTH(DATE(AW2,AW3,1),0) -> 46904 | AX4: =EOMONTH(DATE(AX2,AX3,1),0) -> 46934 | AY4: =EOMONTH(DATE(AY2,AY3,1),0) -> 46965 | AZ4: =EOMONTH(DATE(AZ2,AZ3,1),0) -> 46996 | ... BD4: =EOMONTH(DATE(BD2,BD3,1),0) -> 47118 | BE4: =BE3 -> 2028 | BF4: =EOMONTH(DATE(BF2,BF3,1),0) -> 47149 | BG4: =EOMONTH(DATE(BG2,BG3,1),0) -> 47177 | BH4: =EOMONTH(DATE(BH2,BH3,1),0) -> 47208 | BI4: =EOMONTH(DATE(BI2,BI3,1),0) -> 47238 | BJ4: =EOMONTH(DATE(BJ2,BJ3,1),0) -> 47269 | BK4: =EOMONTH(DATE(BK2,BK3,1),0) -> 47299 | BL4: =EOMONTH(DATE(BL2,BL3,1),0) -> 47330 | BM4: =EOMONTH(DATE(BM2,BM3,1),0) -> 47361 | ... BQ4: =EOMONTH(DATE(BQ2,BQ3,1),0) -> 47483 | BR4: =BR3 -> 2029 | BS4: =EOMONTH(DATE(BS2,BS3,1),0) -> 47514 | BT4: =EOMONTH(DATE(BT2,BT3,1),0) -> 47542 | BU4: =EOMONTH(DATE(BU2,BU3,1),0) -> 47573 | BV4: =EOMONTH(DATE(BV2,BV3,1),0) -> 47603 | BW4: =EOMONTH(DATE(BW2,BW3,1),0) -> 47634 | BX4: =EOMONTH(DATE(BX2,BX3,1),0) -> 47664 | BY4: =EOMONTH(DATE(BY2,BY3,1),0) -> 47695 | BZ4: =EOMONTH(DATE(BZ2,BZ3,1),0) -> 47726 | ... CD4: =EOMONTH(DATE(CD2,CD3,1),0) -> 47848 | CE4: =CE3 -> 2030 | CF4: =EOMONTH(DATE(CF2,CF3,1),0) -> 47879 | CG4: =EOMONTH(DATE(CG2,CG3,1),0) -> 47907 | CH4: =EOMONTH(DATE(CH2,CH3,1),0) -> 47938 | CI4: =EOMONTH(DATE(CI2,CI3,1),0) -> 47968 | CJ4: =EOMONTH(DATE(CJ2,CJ3,1),0) -> 47999 | CK4: =EOMONTH(DATE(CK2,CK3,1),0) -> 48029 | CL4: =EOMONTH(DATE(CL2,CL3,1),0) -> 48060 | CM4: =EOMONTH(DATE(CM2,CM3,1),0) -> 48091 | ... CQ4: =EOMONTH(DATE(CQ2,CQ3,1),0) -> 48213 | CR4: =CR3 -> 2031 | CS4: =EOMONTH(DATE(CS2,CS3,1),0) -> 48244 | CT4: =EOMONTH(DATE(CT2,CT3,1),0) -> 48273 | CU4: =EOMONTH(DATE(CU2,CU3,1),0) -> 48304 | CV4: =EOMONTH(DATE(CV2,CV3,1),0) -> 48334 | CW4: =EOMONTH(DATE(CW2,CW3,1),0) -> 48365 | CX4: =EOMONTH(DATE(CX2,CX3,1),0) -> 48395 | CY4: =EOMONTH(DATE(CY2,CY3,1),0) -> 48426 | CZ4: =EOMONTH(DATE(CZ2,CZ3,1),0) -> 48457 | ... DD4: =EOMONTH(DATE(DD2,DD3,1),0) -> 48579 | DE4: =DE3 -> 2032 | DF4: =EOMONTH(DATE(DF2,DF3,1),0) -> 48610 | DG4: =EOMONTH(DATE(DG2,DG3,1),0) -> 48638 | DH4: =EOMONTH(DATE(DH2,DH3,1),0) -> 48669 | DI4: =EOMONTH(DATE(DI2,DI3,1),0) -> 48699 | DJ4: =EOMONTH(DATE(DJ2,DJ3,1),0) -> 48730 | DK4: =EOMONTH(DATE(DK2,DK3,1),0) -> 48760 | DL4: =EOMONTH(DATE(DL2,DL3,1),0) -> 48791 | DM4: =EOMONTH(DATE(DM2,DM3,1),0) -> 48822 | ... DQ4: =EOMONTH(DATE(DQ2,DQ3,1),0) -> 48944 | DR4: =DR3 -> 2033
B6: Surface globale | C6: ='reporting montigny'!B6+'reporting boissy'!B6+'reporting moussy'!B6+'reporting trappes'!B6+'SPACELOG 5 BP'!B6+'SPACELOG 6 BP'!B6+'SPACELOG 7 BP'!B6+'SPACELOG 8 BP'!B6+'SPACELOG 9 BP'!B6 -> 0 | D6: PRODUITS | E6: CA mensuel | F6: =SUMIF('reporting montigny'!$F$2:$EE$2,F$4,'reporting montigny'!$F$6:$EE$6)+SUMIF('reporting boissy'!$F$2:$EE$2,F$4,'reporting boissy'!$F$6:$EE$6)+SUMIF('reporting moussy'!$F$2:$EE$2,F$4,'reporting moussy'!$F$6:$EE$6)+SUMIF('reporting trappes'!$F$2:$EE$2,F$4,'reporting trappes'!$F$6:$EE$6)+SUMIF('SPACELOG 5 BP'!$F$2:$EE$2,F$4,'SPACELOG 5 BP'!$F$6:$EE$6)+SUMIF('SPACELOG 6 BP'!$F$2:$EE$2,F$4,'SPACELOG 6 BP'!$F$6:$EE$6)+SUMIF('SPACELOG 7 BP'!$F$2:$EE$2,F$4,'SPACELOG 7 BP'!$F$6:$EE$6)+SUMIF('SPACELOG 8 BP'!$F$2:$EE$2,F$4,'SPACELOG 8 BP'!$F$6:$EE$6)+SUMIF('SPACELOG 9 BP'!$F$2:$EE$2,F$4,'SPACELOG 9 BP'!$F$6:$EE$6)+SUMIF('SPACELOG 10 BP'!$F$2:$EE$2,F$4,'SPACELOG 10 BP'!$F$6:$EE$6)+SUMIF('SPACELOG 11 BP'!$F$2:$EE$2,F$4,'SPACELOG 11 BP'!$F$6:$EE$6)+SUMIF('SPACELOG 12 BP'!$F$2:$EE$2,F$4,'SPACELOG 12 BP'!$F$6:$EE$6) -> 66142 | G6: =SUMIF('reporting montigny'!$F$2:$EE$2,G$4,'reporting montigny'!$F$6:$EE$6)+SUMIF('reporting boissy'!$F$2:$EE$2,G$4,'reporting boissy'!$F$6:$EE$6)+SUMIF('reporting moussy'!$F$2:$EE$2,G$4,'reporting moussy'!$F$6:$EE$6)+SUMIF('reporting trappes'!$F$2:$EE$2,G$4,'reporting trappes'!$F$6:$EE$6)+SUMIF('SPACELOG 5 BP'!$F$2:$EE$2,G$4,'SPACELOG 5 BP'!$F$6:$EE$6)+SUMIF('SPACELOG 6 BP'!$F$2:$EE$2,G$4,'SPACELOG 6 BP'!$F$6:$EE$6)+SUMIF('SPACELOG 7 BP'!$F$2:$EE$2,G$4,'SPACELOG 7 BP'!$F$6:$EE$6)+SUMIF('SPACELOG 8 BP'!$F$2:$EE$2,G$4,'SPACELOG 8 BP'!$F$6:$EE$6)+SUMIF('SPACELOG 9 BP'!$F$2:$EE$2,G$4,'SPACELOG 9 BP'!$F$6:$EE$6)+SUMIF('SPACELOG 10 BP'!$F$2:$EE$2,G$4,'SPACELOG 10 BP'!$F$6:$EE$6)+SUMIF('SPACELOG 11 BP'!$F$2:$EE$2,G$4,'SPACELOG 11 BP'!$F$6:$EE$6)+SUMIF('SPACELOG 12 BP'!$F$2:$EE$2,G$4,'SPACELOG 12 BP'!$F$6:$EE$6) -> 67910 | H6: =SUMIF('reporting montigny'!$F$2:$EE$2,H$4,'reporting montigny'!$F$6:$EE$6)+SUMIF('reporting boissy'!$F$2:$EE$2,H$4,'reporting boissy'!$F$6:$EE$6)+SUMIF('reporting moussy'!$F$2:$EE$2,H$4,'reporting moussy'!$F$6:$EE$6)+SUMIF('reporting trappes'!$F$2:$EE$2,H$4,'reporting trappes'!$F$6:$EE$6)+SUMIF('SPACELOG 5 BP'!$F$2:$EE$2,H$4,'SPACELOG 5 BP'!$F$6:$EE$6)+SUMIF('SPACELOG 6 BP'!$F$2:$EE$2,H$4,'SPACELOG 6 BP'!$F$6:$EE$6)+SUMIF('SPACELOG 7 BP'!$F$2:$EE$2,H$4,'SPACELOG 7 BP'!$F$6:$EE$6)+SUMIF('SPACELOG 8 BP'!$F$2:$EE$2,H$4,'SPACELOG 8 BP'!$F$6:$EE$6)+SUMIF('SPACELOG 9 BP'!$F$2:$EE$2,H$4,'SPACELOG 9 BP'!$F$6:$EE$6)+SUMIF('SPACELOG 10 BP'!$F$2:$EE$2,H$4,'SPACELOG 10 BP'!$F$6:$EE$6)+SUMIF('SPACELOG 11 BP'!$F$2:$EE$2,H$4,'SPACELOG 11 BP'!$F$6:$EE$6)+SUMIF('SPACELOG 12 BP'!$F$2:$EE$2,H$4,'SPACELOG 12 BP'!$F$6:$EE$6) -> 69810 | I6: =SUMIF('reporting montigny'!$F$2:$EE$2,I$4,'reporting montigny'!$F$6:$EE$6)+SUMIF('reporting boissy'!$F$2:$EE$2,I$4,'reporting boissy'!$F$6:$EE$6)+SUMIF('reporting moussy'!$F$2:$EE$2,I$4,'reporting moussy'!$F$6:$EE$6)+SUMIF('reporting trappes'!$F$2:$EE$2,I$4,'reporting trappes'!$F$6:$EE$6)+SUMIF('SPACELOG 5 BP'!$F$2:$EE$2,I$4,'SPACELOG 5 BP'!$F$6:$EE$6)+SUMIF('SPACELOG 6 BP'!$F$2:$EE$2,I$4,'SPACELOG 6 BP'!$F$6:$EE$6)+SUMIF('SPACELOG 7 BP'!$F$2:$EE$2,I$4,'SPACELOG 7 BP'!$F$6:$EE$6)+SUMIF('SPACELOG 8 BP'!$F$2:$EE$2,I$4,'SPACELOG 8 BP'!$F$6:$EE$6)+SUMIF('SPACELOG 9 BP'!$F$2:$EE$2,I$4,'SPACELOG 9 BP'!$F$6:$EE$6)+SUMIF('SPACELOG 10 BP'!$F$2:$EE$2,I$4,'SPACELOG 10 BP'!$F$6:$EE$6)+SUMIF('SPACELOG 11 BP'!$F$2:$EE$2,I$4,'SPACELOG 11 BP'!$F$6:$EE$6)+SUMIF('SPACELOG 12 BP'!$F$2:$EE$2,I$4,'SPACELOG 12 BP'!$F$6:$EE$6) -> 76242 | J6: =SUMIF('reporting montigny'!$F$2:$EE$2,J$4,'reporting montigny'!$F$6:$EE$6)+SUMIF('reporting boissy'!$F$2:$EE$2,J$4,'reporting boissy'!$F$6:$EE$6)+SUMIF('reporting moussy'!$F$2:$EE$2,J$4,'reporting moussy'!$F$6:$EE$6)+SUMIF('reporting trappes'!$F$2:$EE$2,J$4,'reporting trappes'!$F$6:$EE$6)+SUMIF('SPACELOG 5 BP'!$F$2:$EE$2,J$4,'SPACELOG 5 BP'!$F$6:$EE$6)+SUMIF('SPACELOG 6 BP'!$F$2:$EE$2,J$4,'SPACELOG 6 BP'!$F$6:$EE$6)+SUMIF('SPACELOG 7 BP'!$F$2:$EE$2,J$4,'SPACELOG 7 BP'!$F$6:$EE$6)+SUMIF('SPACELOG 8 BP'!$F$2:$EE$2,J$4,'SPACELOG 8 BP'!$F$6:$EE$6)+SUMIF('SPACELOG 9 BP'!$F$2:$EE$2,J$4,'SPACELOG 9 BP'!$F$6:$EE$6)+SUMIF('SPACELOG 10 BP'!$F$2:$EE$2,J$4,'SPACELOG 10 BP'!$F$6:$EE$6)+SUMIF('SPACELOG 11 BP'!$F$2:$EE$2,J$4,'SPACELOG 11 BP'!$F$6:$EE$6)+SUMIF('SPACELOG 12 BP'!$F$2:$EE$2,J$4,'SPACELOG 12 BP'!$F$6:$EE$6) -> 77910 | K6: =SUMIF('reporting montigny'!$F$2:$EE$2,K$4,'reporting montigny'!$F$6:$EE$6)+SUMIF('reporting boissy'!$F$2:$EE$2,K$4,'reporting boissy'!$F$6:$EE$6)+SUMIF('reporting moussy'!$F$2:$EE$2,K$4,'reporting moussy'!$F$6:$EE$6)+SUMIF('reporting trappes'!$F$2:$EE$2,K$4,'reporting trappes'!$F$6:$EE$6)+SUMIF('SPACELOG 5 BP'!$F$2:$EE$2,K$4,'SPACELOG 5 BP'!$F$6:$EE$6)+SUMIF('SPACELOG 6 BP'!$F$2:$EE$2,K$4,'SPACELOG 6 BP'!$F$6:$EE$6)+SUMIF('SPACELOG 7 BP'!$F$2:$EE$2,K$4,'SPACELOG 7 BP'!$F$6:$EE$6)+SUMIF('SPACELOG 8 BP'!$F$2:$EE$2,K$4,'SPACELOG 8 BP'!$F$6:$EE$6)+SUMIF('SPACELOG 9 BP'!$F$2:$EE$2,K$4,'SPACELOG 9 BP'!$F$6:$EE$6)+SUMIF('SPACELOG 10 BP'!$F$2:$EE$2,K$4,'SPACELOG 10 BP'!$F$6:$EE$6)+SUMIF('SPACELOG 11 BP'!$F$2:$EE$2,K$4,'SPACELOG 11 BP'!$F$6:$EE$6)+SUMIF('SPACELOG 12 BP'!$F$2:$EE$2,K$4,'SPACELOG 12 BP'!$F$6:$EE$6) -> 78310 | L6: =SUMIF('reporting montigny'!$F$2:$EE$2,L$4,'reporting montigny'!$F$6:$EE$6)+SUMIF('reporting boissy'!$F$2:$EE$2,L$4,'reporting boissy'!$F$6:$EE$6)+SUMIF('reporting moussy'!$F$2:$EE$2,L$4,'reporting moussy'!$F$6:$EE$6)+SUMIF('reporting trappes'!$F$2:$EE$2,L$4,'reporting trappes'!$F$6:$EE$6)+SUMIF('SPACELOG 5 BP'!$F$2:$EE$2,L$4,'SPACELOG 5 BP'!$F$6:$EE$6)+SUMIF('SPACELOG 6 BP'!$F$2:$EE$2,L$4,'SPACELOG 6 BP'!$F$6:$EE$6)+SUMIF('SPACELOG 7 BP'!$F$2:$EE$2,L$4,'SPACELOG 7 BP'!$F$6:$EE$6)+SUMIF('SPACELOG 8 BP'!$F$2:$EE$2,L$4,'SPACELOG 8 BP'!$F$6:$EE$6)+SUMIF('SPACELOG 9 BP'!$F$2:$EE$2,L$4,'SPACELOG 9 BP'!$F$6:$EE$6)+SUMIF('SPACELOG 10 BP'!$F$2:$EE$2,L$4,'SPACELOG 10 BP'!$F$6:$EE$6)+SUMIF('SPACELOG 11 BP'!$F$2:$EE$2,L$4,'SPACELOG 11 BP'!$F$6:$EE$6)+SUMIF('SPACELOG 12 BP'!$F$2:$EE$2,L$4,'SPACELOG 12 BP'!$F$6:$EE$6) -> 76610 | M6: =SUMIF('reporting montigny'!$F$2:$EE$2,M$4,'reporting montigny'!$F$6:$EE$6)+SUMIF('reporting boissy'!$F$2:$EE$2,M$4,'reporting boissy'!$F$6:$EE$6)+SUMIF('reporting moussy'!$F$2:$EE$2,M$4,'reporting moussy'!$F$6:$EE$6)+SUMIF('reporting trappes'!$F$2:$EE$2,M$4,'reporting trappes'!$F$6:$EE$6)+SUMIF('SPACELOG 5 BP'!$F$2:$EE$2,M$4,'SPACELOG 5 BP'!$F$6:$EE$6)+SUMIF('SPACELOG 6 BP'!$F$2:$EE$2,M$4,'SPACELOG 6 BP'!$F$6:$EE$6)+SUMIF('SPACELOG 7 BP'!$F$2:$EE$2,M$4,'SPACELOG 7 BP'!$F$6:$EE$6)+SUMIF('SPACELOG 8 BP'!$F$2:$EE$2,M$4,'SPACELOG 8 BP'!$F$6:$EE$6)+SUMIF('SPACELOG 9 BP'!$F$2:$EE$2,M$4,'SPACELOG 9 BP'!$F$6:$EE$6)+SUMIF('SPACELOG 10 BP'!$F$2:$EE$2,M$4,'SPACELOG 10 BP'!$F$6:$EE$6)+SUMIF('SPACELOG 11 BP'!$F$2:$EE$2,M$4,'SPACELOG 11 BP'!$F$6:$EE$6)+SUMIF('SPACELOG 12 BP'!$F$2:$EE$2,M$4,'SPACELOG 12 BP'!$F$6:$EE$6) -> 76610 | ... Q6: =SUMIF('reporting montigny'!$F$2:$EE$2,Q$4,'reporting montigny'!$F$6:$EE$6)+SUMIF('reporting boissy'!$F$2:$EE$2,Q$4,'reporting boissy'!$F$6:$EE$6)+SUMIF('reporting moussy'!$F$2:$EE$2,Q$4,'reporting moussy'!$F$6:$EE$6)+SUMIF('reporting trappes'!$F$2:$EE$2,Q$4,'reporting trappes'!$F$6:$EE$6)+SUMIF('SPACELOG 5 BP'!$F$2:$EE$2,Q$4,'SPACELOG 5 BP'!$F$6:$EE$6)+SUMIF('SPACELOG 6 BP'!$F$2:$EE$2,Q$4,'SPACELOG 6 BP'!$F$6:$EE$6)+SUMIF('SPACELOG 7 BP'!$F$2:$EE$2,Q$4,'SPACELOG 7 BP'!$F$6:$EE$6)+SUMIF('SPACELOG 8 BP'!$F$2:$EE$2,Q$4,'SPACELOG 8 BP'!$F$6:$EE$6)+SUMIF('SPACELOG 9 BP'!$F$2:$EE$2,Q$4,'SPACELOG 9 BP'!$F$6:$EE$6)+SUMIF('SPACELOG 10 BP'!$F$2:$EE$2,Q$4,'SPACELOG 10 BP'!$F$6:$EE$6)+SUMIF('SPACELOG 11 BP'!$F$2:$EE$2,Q$4,'SPACELOG 11 BP'!$F$6:$EE$6)+SUMIF('SPACELOG 12 BP'!$F$2:$EE$2,Q$4,'SPACELOG 12 BP'!$F$6:$EE$6) -> 88960 | R6: =SUM(F6:Q6) -> 918184 | S6: =SUMIF('reporting montigny'!$F$2:$EE$2,S$4,'reporting montigny'!$F$6:$EE$6)+SUMIF('reporting boissy'!$F$2:$EE$2,S$4,'reporting boissy'!$F$6:$EE$6)+SUMIF('reporting moussy'!$F$2:$EE$2,S$4,'reporting moussy'!$F$6:$EE$6)+SUMIF('reporting trappes'!$F$2:$EE$2,S$4,'reporting trappes'!$F$6:$EE$6)+SUMIF('SPACELOG 5 BP'!$F$2:$EE$2,S$4,'SPACELOG 5 BP'!$F$6:$EE$6)+SUMIF('SPACELOG 6 BP'!$F$2:$EE$2,S$4,'SPACELOG 6 BP'!$F$6:$EE$6)+SUMIF('SPACELOG 7 BP'!$F$2:$EE$2,S$4,'SPACELOG 7 BP'!$F$6:$EE$6)+SUMIF('SPACELOG 8 BP'!$F$2:$EE$2,S$4,'SPACELOG 8 BP'!$F$6:$EE$6)+SUMIF('SPACELOG 9 BP'!$F$2:$EE$2,S$4,'SPACELOG 9 BP'!$F$6:$EE$6)+SUMIF('SPACELOG 10 BP'!$F$2:$EE$2,S$4,'SPACELOG 10 BP'!$F$6:$EE$6)+SUMIF('SPACELOG 11 BP'!$F$2:$EE$2,S$4,'SPACELOG 11 BP'!$F$6:$EE$6)+SUMIF('SPACELOG 12 BP'!$F$2:$EE$2,S$4,'SPACELOG 12 BP'!$F$6:$EE$6) -> 84560 | T6: =SUMIF('reporting montigny'!$F$2:$EE$2,T$4,'reporting montigny'!$F$6:$EE$6)+SUMIF('reporting boissy'!$F$2:$EE$2,T$4,'reporting boissy'!$F$6:$EE$6)+SUMIF('reporting moussy'!$F$2:$EE$2,T$4,'reporting moussy'!$F$6:$EE$6)+SUMIF('reporting trappes'!$F$2:$EE$2,T$4,'reporting trappes'!$F$6:$EE$6)+SUMIF('SPACELOG 5 BP'!$F$2:$EE$2,T$4,'SPACELOG 5 BP'!$F$6:$EE$6)+SUMIF('SPACELOG 6 BP'!$F$2:$EE$2,T$4,'SPACELOG 6 BP'!$F$6:$EE$6)+SUMIF('SPACELOG 7 BP'!$F$2:$EE$2,T$4,'SPACELOG 7 BP'!$F$6:$EE$6)+SUMIF('SPACELOG 8 BP'!$F$2:$EE$2,T$4,'SPACELOG 8 BP'!$F$6:$EE$6)+SUMIF('SPACELOG 9 BP'!$F$2:$EE$2,T$4,'SPACELOG 9 BP'!$F$6:$EE$6)+SUMIF('SPACELOG 10 BP'!$F$2:$EE$2,T$4,'SPACELOG 10 BP'!$F$6:$EE$6)+SUMIF('SPACELOG 11 BP'!$F$2:$EE$2,T$4,'SPACELOG 11 BP'!$F$6:$EE$6)+SUMIF('SPACELOG 12 BP'!$F$2:$EE$2,T$4,'SPACELOG 12 BP'!$F$6:$EE$6) -> 86185 | U6: =SUMIF('reporting montigny'!$F$2:$EE$2,U$4,'reporting montigny'!$F$6:$EE$6)+SUMIF('reporting boissy'!$F$2:$EE$2,U$4,'reporting boissy'!$F$6:$EE$6)+SUMIF('reporting moussy'!$F$2:$EE$2,U$4,'reporting moussy'!$F$6:$EE$6)+SUMIF('reporting trappes'!$F$2:$EE$2,U$4,'reporting trappes'!$F$6:$EE$6)+SUMIF('SPACELOG 5 BP'!$F$2:$EE$2,U$4,'SPACELOG 5 BP'!$F$6:$EE$6)+SUMIF('SPACELOG 6 BP'!$F$2:$EE$2,U$4,'SPACELOG 6 BP'!$F$6:$EE$6)+SUMIF('SPACELOG 7 BP'!$F$2:$EE$2,U$4,'SPACELOG 7 BP'!$F$6:$EE$6)+SUMIF('SPACELOG 8 BP'!$F$2:$EE$2,U$4,'SPACELOG 8 BP'!$F$6:$EE$6)+SUMIF('SPACELOG 9 BP'!$F$2:$EE$2,U$4,'SPACELOG 9 BP'!$F$6:$EE$6)+SUMIF('SPACELOG 10 BP'!$F$2:$EE$2,U$4,'SPACELOG 10 BP'!$F$6:$EE$6)+SUMIF('SPACELOG 11 BP'!$F$2:$EE$2,U$4,'SPACELOG 11 BP'!$F$6:$EE$6)+SUMIF('SPACELOG 12 BP'!$F$2:$EE$2,U$4,'SPACELOG 12 BP'!$F$6:$EE$6) -> 89185 | V6: =SUMIF('reporting montigny'!$F$2:$EE$2,V$4,'reporting montigny'!$F$6:$EE$6)+SUMIF('reporting boissy'!$F$2:$EE$2,V$4,'reporting boissy'!$F$6:$EE$6)+SUMIF('reporting moussy'!$F$2:$EE$2,V$4,'reporting moussy'!$F$6:$EE$6)+SUMIF('reporting trappes'!$F$2:$EE$2,V$4,'reporting trappes'!$F$6:$EE$6)+SUMIF('SPACELOG 5 BP'!$F$2:$EE$2,V$4,'SPACELOG 5 BP'!$F$6:$EE$6)+SUMIF('SPACELOG 6 BP'!$F$2:$EE$2,V$4,'SPACELOG 6 BP'!$F$6:$EE$6)+SUMIF('SPACELOG 7 BP'!$F$2:$EE$2,V$4,'SPACELOG 7 BP'!$F$6:$EE$6)+SUMIF('SPACELOG 8 BP'!$F$2:$EE$2,V$4,'SPACELOG 8 BP'!$F$6:$EE$6)+SUMIF('SPACELOG 9 BP'!$F$2:$EE$2,V$4,'SPACELOG 9 BP'!$F$6:$EE$6)+SUMIF('SPACELOG 10 BP'!$F$2:$EE$2,V$4,'SPACELOG 10 BP'!$F$6:$EE$6)+SUMIF('SPACELOG 11 BP'!$F$2:$EE$2,V$4,'SPACELOG 11 BP'!$F$6:$EE$6)+SUMIF('SPACELOG 12 BP'!$F$2:$EE$2,V$4,'SPACELOG 12 BP'!$F$6:$EE$6) -> 83735 | W6: =SUMIF('reporting montigny'!$F$2:$EE$2,W$4,'reporting montigny'!$F$6:$EE$6)+SUMIF('reporting boissy'!$F$2:$EE$2,W$4,'reporting boissy'!$F$6:$EE$6)+SUMIF('reporting moussy'!$F$2:$EE$2,W$4,'reporting moussy'!$F$6:$EE$6)+SUMIF('reporting trappes'!$F$2:$EE$2,W$4,'reporting trappes'!$F$6:$EE$6)+SUMIF('SPACELOG 5 BP'!$F$2:$EE$2,W$4,'SPACELOG 5 BP'!$F$6:$EE$6)+SUMIF('SPACELOG 6 BP'!$F$2:$EE$2,W$4,'SPACELOG 6 BP'!$F$6:$EE$6)+SUMIF('SPACELOG 7 BP'!$F$2:$EE$2,W$4,'SPACELOG 7 BP'!$F$6:$EE$6)+SUMIF('SPACELOG 8 BP'!$F$2:$EE$2,W$4,'SPACELOG 8 BP'!$F$6:$EE$6)+SUMIF('SPACELOG 9 BP'!$F$2:$EE$2,W$4,'SPACELOG 9 BP'!$F$6:$EE$6)+SUMIF('SPACELOG 10 BP'!$F$2:$EE$2,W$4,'SPACELOG 10 BP'!$F$6:$EE$6)+SUMIF('SPACELOG 11 BP'!$F$2:$EE$2,W$4,'SPACELOG 11 BP'!$F$6:$EE$6)+SUMIF('SPACELOG 12 BP'!$F$2:$EE$2,W$4,'SPACELOG 12 BP'!$F$6:$EE$6) -> 94035 | X6: =SUMIF('reporting montigny'!$F$2:$EE$2,X$4,'reporting montigny'!$F$6:$EE$6)+SUMIF('reporting boissy'!$F$2:$EE$2,X$4,'reporting boissy'!$F$6:$EE$6)+SUMIF('reporting moussy'!$F$2:$EE$2,X$4,'reporting moussy'!$F$6:$EE$6)+SUMIF('reporting trappes'!$F$2:$EE$2,X$4,'reporting trappes'!$F$6:$EE$6)+SUMIF('SPACELOG 5 BP'!$F$2:$EE$2,X$4,'SPACELOG 5 BP'!$F$6:$EE$6)+SUMIF('SPACELOG 6 BP'!$F$2:$EE$2,X$4,'SPACELOG 6 BP'!$F$6:$EE$6)+SUMIF('SPACELOG 7 BP'!$F$2:$EE$2,X$4,'SPACELOG 7 BP'!$F$6:$EE$6)+SUMIF('SPACELOG 8 BP'!$F$2:$EE$2,X$4,'SPACELOG 8 BP'!$F$6:$EE$6)+SUMIF('SPACELOG 9 BP'!$F$2:$EE$2,X$4,'SPACELOG 9 BP'!$F$6:$EE$6)+SUMIF('SPACELOG 10 BP'!$F$2:$EE$2,X$4,'SPACELOG 10 BP'!$F$6:$EE$6)+SUMIF('SPACELOG 11 BP'!$F$2:$EE$2,X$4,'SPACELOG 11 BP'!$F$6:$EE$6)+SUMIF('SPACELOG 12 BP'!$F$2:$EE$2,X$4,'SPACELOG 12 BP'!$F$6:$EE$6) -> 93185 | Y6: =SUMIF('reporting montigny'!$F$2:$EE$2,Y$4,'reporting montigny'!$F$6:$EE$6)+SUMIF('reporting boissy'!$F$2:$EE$2,Y$4,'reporting boissy'!$F$6:$EE$6)+SUMIF('reporting moussy'!$F$2:$EE$2,Y$4,'reporting moussy'!$F$6:$EE$6)+SUMIF('reporting trappes'!$F$2:$EE$2,Y$4,'reporting trappes'!$F$6:$EE$6)+SUMIF('SPACELOG 5 BP'!$F$2:$EE$2,Y$4,'SPACELOG 5 BP'!$F$6:$EE$6)+SUMIF('SPACELOG 6 BP'!$F$2:$EE$2,Y$4,'SPACELOG 6 BP'!$F$6:$EE$6)+SUMIF('SPACELOG 7 BP'!$F$2:$EE$2,Y$4,'SPACELOG 7 BP'!$F$6:$EE$6)+SUMIF('SPACELOG 8 BP'!$F$2:$EE$2,Y$4,'SPACELOG 8 BP'!$F$6:$EE$6)+SUMIF('SPACELOG 9 BP'!$F$2:$EE$2,Y$4,'SPACELOG 9 BP'!$F$6:$EE$6)+SUMIF('SPACELOG 10 BP'!$F$2:$EE$2,Y$4,'SPACELOG 10 BP'!$F$6:$EE$6)+SUMIF('SPACELOG 11 BP'!$F$2:$EE$2,Y$4,'SPACELOG 11 BP'!$F$6:$EE$6)+SUMIF('SPACELOG 12 BP'!$F$2:$EE$2,Y$4,'SPACELOG 12 BP'!$F$6:$EE$6) -> 101635 | Z6: =SUMIF('reporting montigny'!$F$2:$EE$2,Z$4,'reporting montigny'!$F$6:$EE$6)+SUMIF('reporting boissy'!$F$2:$EE$2,Z$4,'reporting boissy'!$F$6:$EE$6)+SUMIF('reporting moussy'!$F$2:$EE$2,Z$4,'reporting moussy'!$F$6:$EE$6)+SUMIF('reporting trappes'!$F$2:$EE$2,Z$4,'reporting trappes'!$F$6:$EE$6)+SUMIF('SPACELOG 5 BP'!$F$2:$EE$2,Z$4,'SPACELOG 5 BP'!$F$6:$EE$6)+SUMIF('SPACELOG 6 BP'!$F$2:$EE$2,Z$4,'SPACELOG 6 BP'!$F$6:$EE$6)+SUMIF('SPACELOG 7 BP'!$F$2:$EE$2,Z$4,'SPACELOG 7 BP'!$F$6:$EE$6)+SUMIF('SPACELOG 8 BP'!$F$2:$EE$2,Z$4,'SPACELOG 8 BP'!$F$6:$EE$6)+SUMIF('SPACELOG 9 BP'!$F$2:$EE$2,Z$4,'SPACELOG 9 BP'!$F$6:$EE$6)+SUMIF('SPACELOG 10 BP'!$F$2:$EE$2,Z$4,'SPACELOG 10 BP'!$F$6:$EE$6)+SUMIF('SPACELOG 11 BP'!$F$2:$EE$2,Z$4,'SPACELOG 11 BP'!$F$6:$EE$6)+SUMIF('SPACELOG 12 BP'!$F$2:$EE$2,Z$4,'SPACELOG 12 BP'!$F$6:$EE$6) -> 104185 | ... AD6: =SUMIF('reporting montigny'!$F$2:$EE$2,AD$4,'reporting montigny'!$F$6:$EE$6)+SUMIF('reporting boissy'!$F$2:$EE$2,AD$4,'reporting boissy'!$F$6:$EE$6)+SUMIF('reporting moussy'!$F$2:$EE$2,AD$4,'reporting moussy'!$F$6:$EE$6)+SUMIF('reporting trappes'!$F$2:$EE$2,AD$4,'reporting trappes'!$F$6:$EE$6)+SUMIF('SPACELOG 5 BP'!$F$2:$EE$2,AD$4,'SPACELOG 5 BP'!$F$6:$EE$6)+SUMIF('SPACELOG 6 BP'!$F$2:$EE$2,AD$4,'SPACELOG 6 BP'!$F$6:$EE$6)+SUMIF('SPACELOG 7 BP'!$F$2:$EE$2,AD$4,'SPACELOG 7 BP'!$F$6:$EE$6)+SUMIF('SPACELOG 8 BP'!$F$2:$EE$2,AD$4,'SPACELOG 8 BP'!$F$6:$EE$6)+SUMIF('SPACELOG 9 BP'!$F$2:$EE$2,AD$4,'SPACELOG 9 BP'!$F$6:$EE$6)+SUMIF('SPACELOG 10 BP'!$F$2:$EE$2,AD$4,'SPACELOG 10 BP'!$F$6:$EE$6)+SUMIF('SPACELOG 11 BP'!$F$2:$EE$2,AD$4,'SPACELOG 11 BP'!$F$6:$EE$6)+SUMIF('SPACELOG 12 BP'!$F$2:$EE$2,AD$4,'SPACELOG 12 BP'!$F$6:$EE$6) -> 114385 | AE6: =SUM(S6:AD6) -> 1178945 | AF6: =SUMIF('reporting montigny'!$F$2:$EE$2,AF$4,'reporting montigny'!$F$6:$EE$6)+SUMIF('reporting boissy'!$F$2:$EE$2,AF$4,'reporting boissy'!$F$6:$EE$6)+SUMIF('reporting moussy'!$F$2:$EE$2,AF$4,'reporting moussy'!$F$6:$EE$6)+SUMIF('reporting trappes'!$F$2:$EE$2,AF$4,'reporting trappes'!$F$6:$EE$6)+SUMIF('SPACELOG 5 BP'!$F$2:$EE$2,AF$4,'SPACELOG 5 BP'!$F$6:$EE$6)+SUMIF('SPACELOG 6 BP'!$F$2:$EE$2,AF$4,'SPACELOG 6 BP'!$F$6:$EE$6)+SUMIF('SPACELOG 7 BP'!$F$2:$EE$2,AF$4,'SPACELOG 7 BP'!$F$6:$EE$6)+SUMIF('SPACELOG 8 BP'!$F$2:$EE$2,AF$4,'SPACELOG 8 BP'!$F$6:$EE$6)+SUMIF('SPACELOG 9 BP'!$F$2:$EE$2,AF$4,'SPACELOG 9 BP'!$F$6:$EE$6)+SUMIF('SPACELOG 10 BP'!$F$2:$EE$2,AF$4,'SPACELOG 10 BP'!$F$6:$EE$6)+SUMIF('SPACELOG 11 BP'!$F$2:$EE$2,AF$4,'SPACELOG 11 BP'!$F$6:$EE$6)+SUMIF('SPACELOG 12 BP'!$F$2:$EE$2,AF$4,'SPACELOG 12 BP'!$F$6:$EE$6) -> 116935 | AG6: =SUMIF('reporting montigny'!$F$2:$EE$2,AG$4,'reporting montigny'!$F$6:$EE$6)+SUMIF('reporting boissy'!$F$2:$EE$2,AG$4,'reporting boissy'!$F$6:$EE$6)+SUMIF('reporting moussy'!$F$2:$EE$2,AG$4,'reporting moussy'!$F$6:$EE$6)+SUMIF('reporting trappes'!$F$2:$EE$2,AG$4,'reporting trappes'!$F$6:$EE$6)+SUMIF('SPACELOG 5 BP'!$F$2:$EE$2,AG$4,'SPACELOG 5 BP'!$F$6:$EE$6)+SUMIF('SPACELOG 6 BP'!$F$2:$EE$2,AG$4,'SPACELOG 6 BP'!$F$6:$EE$6)+SUMIF('SPACELOG 7 BP'!$F$2:$EE$2,AG$4,'SPACELOG 7 BP'!$F$6:$EE$6)+SUMIF('SPACELOG 8 BP'!$F$2:$EE$2,AG$4,'SPACELOG 8 BP'!$F$6:$EE$6)+SUMIF('SPACELOG 9 BP'!$F$2:$EE$2,AG$4,'SPACELOG 9 BP'!$F$6:$EE$6)+SUMIF('SPACELOG 10 BP'!$F$2:$EE$2,AG$4,'SPACELOG 10 BP'!$F$6:$EE$6)+SUMIF('SPACELOG 11 BP'!$F$2:$EE$2,AG$4,'SPACELOG 11 BP'!$F$6:$EE$6)+SUMIF('SPACELOG 12 BP'!$F$2:$EE$2,AG$4,'SPACELOG 12 BP'!$F$6:$EE$6) -> 119485 | AH6: =SUMIF('reporting montigny'!$F$2:$EE$2,AH$4,'reporting montigny'!$F$6:$EE$6)+SUMIF('reporting boissy'!$F$2:$EE$2,AH$4,'reporting boissy'!$F$6:$EE$6)+SUMIF('reporting moussy'!$F$2:$EE$2,AH$4,'reporting moussy'!$F$6:$EE$6)+SUMIF('reporting trappes'!$F$2:$EE$2,AH$4,'reporting trappes'!$F$6:$EE$6)+SUMIF('SPACELOG 5 BP'!$F$2:$EE$2,AH$4,'SPACELOG 5 BP'!$F$6:$EE$6)+SUMIF('SPACELOG 6 BP'!$F$2:$EE$2,AH$4,'SPACELOG 6 BP'!$F$6:$EE$6)+SUMIF('SPACELOG 7 BP'!$F$2:$EE$2,AH$4,'SPACELOG 7 BP'!$F$6:$EE$6)+SUMIF('SPACELOG 8 BP'!$F$2:$EE$2,AH$4,'SPACELOG 8 BP'!$F$6:$EE$6)+SUMIF('SPACELOG 9 BP'!$F$2:$EE$2,AH$4,'SPACELOG 9 BP'!$F$6:$EE$6)+SUMIF('SPACELOG 10 BP'!$F$2:$EE$2,AH$4,'SPACELOG 10 BP'!$F$6:$EE$6)+SUMIF('SPACELOG 11 BP'!$F$2:$EE$2,AH$4,'SPACELOG 11 BP'!$F$6:$EE$6)+SUMIF('SPACELOG 12 BP'!$F$2:$EE$2,AH$4,'SPACELOG 12 BP'!$F$6:$EE$6) -> 122035 | AI6: =SUMIF('reporting montigny'!$F$2:$EE$2,AI$4,'reporting montigny'!$F$6:$EE$6)+SUMIF('reporting boissy'!$F$2:$EE$2,AI$4,'reporting boissy'!$F$6:$EE$6)+SUMIF('reporting moussy'!$F$2:$EE$2,AI$4,'reporting moussy'!$F$6:$EE$6)+SUMIF('reporting trappes'!$F$2:$EE$2,AI$4,'reporting trappes'!$F$6:$EE$6)+SUMIF('SPACELOG 5 BP'!$F$2:$EE$2,AI$4,'SPACELOG 5 BP'!$F$6:$EE$6)+SUMIF('SPACELOG 6 BP'!$F$2:$EE$2,AI$4,'SPACELOG 6 BP'!$F$6:$EE$6)+SUMIF('SPACELOG 7 BP'!$F$2:$EE$2,AI$4,'SPACELOG 7 BP'!$F$6:$EE$6)+SUMIF('SPACELOG 8 BP'!$F$2:$EE$2,AI$4,'SPACELOG 8 BP'!$F$6:$EE$6)+SUMIF('SPACELOG 9 BP'!$F$2:$EE$2,AI$4,'SPACELOG 9 BP'!$F$6:$EE$6)+SUMIF('SPACELOG 10 BP'!$F$2:$EE$2,AI$4,'SPACELOG 10 BP'!$F$6:$EE$6)+SUMIF('SPACELOG 11 BP'!$F$2:$EE$2,AI$4,'SPACELOG 11 BP'!$F$6:$EE$6)+SUMIF('SPACELOG 12 BP'!$F$2:$EE$2,AI$4,'SPACELOG 12 BP'!$F$6:$EE$6) -> 124585 | AJ6: =SUMIF('reporting montigny'!$F$2:$EE$2,AJ$4,'reporting montigny'!$F$6:$EE$6)+SUMIF('reporting boissy'!$F$2:$EE$2,AJ$4,'reporting boissy'!$F$6:$EE$6)+SUMIF('reporting moussy'!$F$2:$EE$2,AJ$4,'reporting moussy'!$F$6:$EE$6)+SUMIF('reporting trappes'!$F$2:$EE$2,AJ$4,'reporting trappes'!$F$6:$EE$6)+SUMIF('SPACELOG 5 BP'!$F$2:$EE$2,AJ$4,'SPACELOG 5 BP'!$F$6:$EE$6)+SUMIF('SPACELOG 6 BP'!$F$2:$EE$2,AJ$4,'SPACELOG 6 BP'!$F$6:$EE$6)+SUMIF('SPACELOG 7 BP'!$F$2:$EE$2,AJ$4,'SPACELOG 7 BP'!$F$6:$EE$6)+SUMIF('SPACELOG 8 BP'!$F$2:$EE$2,AJ$4,'SPACELOG 8 BP'!$F$6:$EE$6)+SUMIF('SPACELOG 9 BP'!$F$2:$EE$2,AJ$4,'SPACELOG 9 BP'!$F$6:$EE$6)+SUMIF('SPACELOG 10 BP'!$F$2:$EE$2,AJ$4,'SPACELOG 10 BP'!$F$6:$EE$6)+SUMIF('SPACELOG 11 BP'!$F$2:$EE$2,AJ$4,'SPACELOG 11 BP'!$F$6:$EE$6)+SUMIF('SPACELOG 12 BP'!$F$2:$EE$2,AJ$4,'SPACELOG 12 BP'!$F$6:$EE$6) -> 126385 | AK6: =SUMIF('reporting montigny'!$F$2:$EE$2,AK$4,'reporting montigny'!$F$6:$EE$6)+SUMIF('reporting boissy'!$F$2:$EE$2,AK$4,'reporting boissy'!$F$6:$EE$6)+SUMIF('reporting moussy'!$F$2:$EE$2,AK$4,'reporting moussy'!$F$6:$EE$6)+SUMIF('reporting trappes'!$F$2:$EE$2,AK$4,'reporting trappes'!$F$6:$EE$6)+SUMIF('SPACELOG 5 BP'!$F$2:$EE$2,AK$4,'SPACELOG 5 BP'!$F$6:$EE$6)+SUMIF('SPACELOG 6 BP'!$F$2:$EE$2,AK$4,'SPACELOG 6 BP'!$F$6:$EE$6)+SUMIF('SPACELOG 7 BP'!$F$2:$EE$2,AK$4,'SPACELOG 7 BP'!$F$6:$EE$6)+SUMIF('SPACELOG 8 BP'!$F$2:$EE$2,AK$4,'SPACELOG 8 BP'!$F$6:$EE$6)+SUMIF('SPACELOG 9 BP'!$F$2:$EE$2,AK$4,'SPACELOG 9 BP'!$F$6:$EE$6)+SUMIF('SPACELOG 10 BP'!$F$2:$EE$2,AK$4,'SPACELOG 10 BP'!$F$6:$EE$6)+SUMIF('SPACELOG 11 BP'!$F$2:$EE$2,AK$4,'SPACELOG 11 BP'!$F$6:$EE$6)+SUMIF('SPACELOG 12 BP'!$F$2:$EE$2,AK$4,'SPACELOG 12 BP'!$F$6:$EE$6) -> 128185 | AL6: =SUMIF('reporting montigny'!$F$2:$EE$2,AL$4,'reporting montigny'!$F$6:$EE$6)+SUMIF('reporting boissy'!$F$2:$EE$2,AL$4,'reporting boissy'!$F$6:$EE$6)+SUMIF('reporting moussy'!$F$2:$EE$2,AL$4,'reporting moussy'!$F$6:$EE$6)+SUMIF('reporting trappes'!$F$2:$EE$2,AL$4,'reporting trappes'!$F$6:$EE$6)+SUMIF('SPACELOG 5 BP'!$F$2:$EE$2,AL$4,'SPACELOG 5 BP'!$F$6:$EE$6)+SUMIF('SPACELOG 6 BP'!$F$2:$EE$2,AL$4,'SPACELOG 6 BP'!$F$6:$EE$6)+SUMIF('SPACELOG 7 BP'!$F$2:$EE$2,AL$4,'SPACELOG 7 BP'!$F$6:$EE$6)+SUMIF('SPACELOG 8 BP'!$F$2:$EE$2,AL$4,'SPACELOG 8 BP'!$F$6:$EE$6)+SUMIF('SPACELOG 9 BP'!$F$2:$EE$2,AL$4,'SPACELOG 9 BP'!$F$6:$EE$6)+SUMIF('SPACELOG 10 BP'!$F$2:$EE$2,AL$4,'SPACELOG 10 BP'!$F$6:$EE$6)+SUMIF('SPACELOG 11 BP'!$F$2:$EE$2,AL$4,'SPACELOG 11 BP'!$F$6:$EE$6)+SUMIF('SPACELOG 12 BP'!$F$2:$EE$2,AL$4,'SPACELOG 12 BP'!$F$6:$EE$6) -> 128185 | AM6: =SUMIF('reporting montigny'!$F$2:$EE$2,AM$4,'reporting montigny'!$F$6:$EE$6)+SUMIF('reporting boissy'!$F$2:$EE$2,AM$4,'reporting boissy'!$F$6:$EE$6)+SUMIF('reporting moussy'!$F$2:$EE$2,AM$4,'reporting moussy'!$F$6:$EE$6)+SUMIF('reporting trappes'!$F$2:$EE$2,AM$4,'reporting trappes'!$F$6:$EE$6)+SUMIF('SPACELOG 5 BP'!$F$2:$EE$2,AM$4,'SPACELOG 5 BP'!$F$6:$EE$6)+SUMIF('SPACELOG 6 BP'!$F$2:$EE$2,AM$4,'SPACELOG 6 BP'!$F$6:$EE$6)+SUMIF('SPACELOG 7 BP'!$F$2:$EE$2,AM$4,'SPACELOG 7 BP'!$F$6:$EE$6)+SUMIF('SPACELOG 8 BP'!$F$2:$EE$2,AM$4,'SPACELOG 8 BP'!$F$6:$EE$6)+SUMIF('SPACELOG 9 BP'!$F$2:$EE$2,AM$4,'SPACELOG 9 BP'!$F$6:$EE$6)+SUMIF('SPACELOG 10 BP'!$F$2:$EE$2,AM$4,'SPACELOG 10 BP'!$F$6:$EE$6)+SUMIF('SPACELOG 11 BP'!$F$2:$EE$2,AM$4,'SPACELOG 11 BP'!$F$6:$EE$6)+SUMIF('SPACELOG 12 BP'!$F$2:$EE$2,AM$4,'SPACELOG 12 BP'!$F$6:$EE$6) -> 128185 | ... AQ6: =SUMIF('reporting montigny'!$F$2:$EE$2,AQ$4,'reporting montigny'!$F$6:$EE$6)+SUMIF('reporting boissy'!$F$2:$EE$2,AQ$4,'reporting boissy'!$F$6:$EE$6)+SUMIF('reporting moussy'!$F$2:$EE$2,AQ$4,'reporting moussy'!$F$6:$EE$6)+SUMIF('reporting trappes'!$F$2:$EE$2,AQ$4,'reporting trappes'!$F$6:$EE$6)+SUMIF('SPACELOG 5 BP'!$F$2:$EE$2,AQ$4,'SPACELOG 5 BP'!$F$6:$EE$6)+SUMIF('SPACELOG 6 BP'!$F$2:$EE$2,AQ$4,'SPACELOG 6 BP'!$F$6:$EE$6)+SUMIF('SPACELOG 7 BP'!$F$2:$EE$2,AQ$4,'SPACELOG 7 BP'!$F$6:$EE$6)+SUMIF('SPACELOG 8 BP'!$F$2:$EE$2,AQ$4,'SPACELOG 8 BP'!$F$6:$EE$6)+SUMIF('SPACELOG 9 BP'!$F$2:$EE$2,AQ$4,'SPACELOG 9 BP'!$F$6:$EE$6)+SUMIF('SPACELOG 10 BP'!$F$2:$EE$2,AQ$4,'SPACELOG 10 BP'!$F$6:$EE$6)+SUMIF('SPACELOG 11 BP'!$F$2:$EE$2,AQ$4,'SPACELOG 11 BP'!$F$6:$EE$6)+SUMIF('SPACELOG 12 BP'!$F$2:$EE$2,AQ$4,'SPACELOG 12 BP'!$F$6:$EE$6) -> 128185 | AR6: =SUM(AF6:AQ6) -> 1506720 | AS6: =SUMIF('reporting montigny'!$F$2:$EE$2,AS$4,'reporting montigny'!$F$6:$EE$6)+SUMIF('reporting boissy'!$F$2:$EE$2,AS$4,'reporting boissy'!$F$6:$EE$6)+SUMIF('reporting moussy'!$F$2:$EE$2,AS$4,'reporting moussy'!$F$6:$EE$6)+SUMIF('reporting trappes'!$F$2:$EE$2,AS$4,'reporting trappes'!$F$6:$EE$6)+SUMIF('SPACELOG 5 BP'!$F$2:$EE$2,AS$4,'SPACELOG 5 BP'!$F$6:$EE$6)+SUMIF('SPACELOG 6 BP'!$F$2:$EE$2,AS$4,'SPACELOG 6 BP'!$F$6:$EE$6)+SUMIF('SPACELOG 7 BP'!$F$2:$EE$2,AS$4,'SPACELOG 7 BP'!$F$6:$EE$6)+SUMIF('SPACELOG 8 BP'!$F$2:$EE$2,AS$4,'SPACELOG 8 BP'!$F$6:$EE$6)+SUMIF('SPACELOG 9 BP'!$F$2:$EE$2,AS$4,'SPACELOG 9 BP'!$F$6:$EE$6)+SUMIF('SPACELOG 10 BP'!$F$2:$EE$2,AS$4,'SPACELOG 10 BP'!$F$6:$EE$6)+SUMIF('SPACELOG 11 BP'!$F$2:$EE$2,AS$4,'SPACELOG 11 BP'!$F$6:$EE$6)+SUMIF('SPACELOG 12 BP'!$F$2:$EE$2,AS$4,'SPACELOG 12 BP'!$F$6:$EE$6) -> 128185 | AT6: =SUMIF('reporting montigny'!$F$2:$EE$2,AT$4,'reporting montigny'!$F$6:$EE$6)+SUMIF('reporting boissy'!$F$2:$EE$2,AT$4,'reporting boissy'!$F$6:$EE$6)+SUMIF('reporting moussy'!$F$2:$EE$2,AT$4,'reporting moussy'!$F$6:$EE$6)+SUMIF('reporting trappes'!$F$2:$EE$2,AT$4,'reporting trappes'!$F$6:$EE$6)+SUMIF('SPACELOG 5 BP'!$F$2:$EE$2,AT$4,'SPACELOG 5 BP'!$F$6:$EE$6)+SUMIF('SPACELOG 6 BP'!$F$2:$EE$2,AT$4,'SPACELOG 6 BP'!$F$6:$EE$6)+SUMIF('SPACELOG 7 BP'!$F$2:$EE$2,AT$4,'SPACELOG 7 BP'!$F$6:$EE$6)+SUMIF('SPACELOG 8 BP'!$F$2:$EE$2,AT$4,'SPACELOG 8 BP'!$F$6:$EE$6)+SUMIF('SPACELOG 9 BP'!$F$2:$EE$2,AT$4,'SPACELOG 9 BP'!$F$6:$EE$6)+SUMIF('SPACELOG 10 BP'!$F$2:$EE$2,AT$4,'SPACELOG 10 BP'!$F$6:$EE$6)+SUMIF('SPACELOG 11 BP'!$F$2:$EE$2,AT$4,'SPACELOG 11 BP'!$F$6:$EE$6)+SUMIF('SPACELOG 12 BP'!$F$2:$EE$2,AT$4,'SPACELOG 12 BP'!$F$6:$EE$6) -> 128185 | AU6: =SUMIF('reporting montigny'!$F$2:$EE$2,AU$4,'reporting montigny'!$F$6:$EE$6)+SUMIF('reporting boissy'!$F$2:$EE$2,AU$4,'reporting boissy'!$F$6:$EE$6)+SUMIF('reporting moussy'!$F$2:$EE$2,AU$4,'reporting moussy'!$F$6:$EE$6)+SUMIF('reporting trappes'!$F$2:$EE$2,AU$4,'reporting trappes'!$F$6:$EE$6)+SUMIF('SPACELOG 5 BP'!$F$2:$EE$2,AU$4,'SPACELOG 5 BP'!$F$6:$EE$6)+SUMIF('SPACELOG 6 BP'!$F$2:$EE$2,AU$4,'SPACELOG 6 BP'!$F$6:$EE$6)+SUMIF('SPACELOG 7 BP'!$F$2:$EE$2,AU$4,'SPACELOG 7 BP'!$F$6:$EE$6)+SUMIF('SPACELOG 8 BP'!$F$2:$EE$2,AU$4,'SPACELOG 8 BP'!$F$6:$EE$6)+SUMIF('SPACELOG 9 BP'!$F$2:$EE$2,AU$4,'SPACELOG 9 BP'!$F$6:$EE$6)+SUMIF('SPACELOG 10 BP'!$F$2:$EE$2,AU$4,'SPACELOG 10 BP'!$F$6:$EE$6)+SUMIF('SPACELOG 11 BP'!$F$2:$EE$2,AU$4,'SPACELOG 11 BP'!$F$6:$EE$6)+SUMIF('SPACELOG 12 BP'!$F$2:$EE$2,AU$4,'SPACELOG 12 BP'!$F$6:$EE$6) -> 128185 | AV6: =SUMIF('reporting montigny'!$F$2:$EE$2,AV$4,'reporting montigny'!$F$6:$EE$6)+SUMIF('reporting boissy'!$F$2:$EE$2,AV$4,'reporting boissy'!$F$6:$EE$6)+SUMIF('reporting moussy'!$F$2:$EE$2,AV$4,'reporting moussy'!$F$6:$EE$6)+SUMIF('reporting trappes'!$F$2:$EE$2,AV$4,'reporting trappes'!$F$6:$EE$6)+SUMIF('SPACELOG 5 BP'!$F$2:$EE$2,AV$4,'SPACELOG 5 BP'!$F$6:$EE$6)+SUMIF('SPACELOG 6 BP'!$F$2:$EE$2,AV$4,'SPACELOG 6 BP'!$F$6:$EE$6)+SUMIF('SPACELOG 7 BP'!$F$2:$EE$2,AV$4,'SPACELOG 7 BP'!$F$6:$EE$6)+SUMIF('SPACELOG 8 BP'!$F$2:$EE$2,AV$4,'SPACELOG 8 BP'!$F$6:$EE$6)+SUMIF('SPACELOG 9 BP'!$F$2:$EE$2,AV$4,'SPACELOG 9 BP'!$F$6:$EE$6)+SUMIF('SPACELOG 10 BP'!$F$2:$EE$2,AV$4,'SPACELOG 10 BP'!$F$6:$EE$6)+SUMIF('SPACELOG 11 BP'!$F$2:$EE$2,AV$4,'SPACELOG 11 BP'!$F$6:$EE$6)+SUMIF('SPACELOG 12 BP'!$F$2:$EE$2,AV$4,'SPACELOG 12 BP'!$F$6:$EE$6) -> 128185 | AW6: =SUMIF('reporting montigny'!$F$2:$EE$2,AW$4,'reporting montigny'!$F$6:$EE$6)+SUMIF('reporting boissy'!$F$2:$EE$2,AW$4,'reporting boissy'!$F$6:$EE$6)+SUMIF('reporting moussy'!$F$2:$EE$2,AW$4,'reporting moussy'!$F$6:$EE$6)+SUMIF('reporting trappes'!$F$2:$EE$2,AW$4,'reporting trappes'!$F$6:$EE$6)+SUMIF('SPACELOG 5 BP'!$F$2:$EE$2,AW$4,'SPACELOG 5 BP'!$F$6:$EE$6)+SUMIF('SPACELOG 6 BP'!$F$2:$EE$2,AW$4,'SPACELOG 6 BP'!$F$6:$EE$6)+SUMIF('SPACELOG 7 BP'!$F$2:$EE$2,AW$4,'SPACELOG 7 BP'!$F$6:$EE$6)+SUMIF('SPACELOG 8 BP'!$F$2:$EE$2,AW$4,'SPACELOG 8 BP'!$F$6:$EE$6)+SUMIF('SPACELOG 9 BP'!$F$2:$EE$2,AW$4,'SPACELOG 9 BP'!$F$6:$EE$6)+SUMIF('SPACELOG 10 BP'!$F$2:$EE$2,AW$4,'SPACELOG 10 BP'!$F$6:$EE$6)+SUMIF('SPACELOG 11 BP'!$F$2:$EE$2,AW$4,'SPACELOG 11 BP'!$F$6:$EE$6)+SUMIF('SPACELOG 12 BP'!$F$2:$EE$2,AW$4,'SPACELOG 12 BP'!$F$6:$EE$6) -> 128185 | AX6: =SUMIF('reporting montigny'!$F$2:$EE$2,AX$4,'reporting montigny'!$F$6:$EE$6)+SUMIF('reporting boissy'!$F$2:$EE$2,AX$4,'reporting boissy'!$F$6:$EE$6)+SUMIF('reporting moussy'!$F$2:$EE$2,AX$4,'reporting moussy'!$F$6:$EE$6)+SUMIF('reporting trappes'!$F$2:$EE$2,AX$4,'reporting trappes'!$F$6:$EE$6)+SUMIF('SPACELOG 5 BP'!$F$2:$EE$2,AX$4,'SPACELOG 5 BP'!$F$6:$EE$6)+SUMIF('SPACELOG 6 BP'!$F$2:$EE$2,AX$4,'SPACELOG 6 BP'!$F$6:$EE$6)+SUMIF('SPACELOG 7 BP'!$F$2:$EE$2,AX$4,'SPACELOG 7 BP'!$F$6:$EE$6)+SUMIF('SPACELOG 8 BP'!$F$2:$EE$2,AX$4,'SPACELOG 8 BP'!$F$6:$EE$6)+SUMIF('SPACELOG 9 BP'!$F$2:$EE$2,AX$4,'SPACELOG 9 BP'!$F$6:$EE$6)+SUMIF('SPACELOG 10 BP'!$F$2:$EE$2,AX$4,'SPACELOG 10 BP'!$F$6:$EE$6)+SUMIF('SPACELOG 11 BP'!$F$2:$EE$2,AX$4,'SPACELOG 11 BP'!$F$6:$EE$6)+SUMIF('SPACELOG 12 BP'!$F$2:$EE$2,AX$4,'SPACELOG 12 BP'!$F$6:$EE$6) -> 128185 | AY6: =SUMIF('reporting montigny'!$F$2:$EE$2,AY$4,'reporting montigny'!$F$6:$EE$6)+SUMIF('reporting boissy'!$F$2:$EE$2,AY$4,'reporting boissy'!$F$6:$EE$6)+SUMIF('reporting moussy'!$F$2:$EE$2,AY$4,'reporting moussy'!$F$6:$EE$6)+SUMIF('reporting trappes'!$F$2:$EE$2,AY$4,'reporting trappes'!$F$6:$EE$6)+SUMIF('SPACELOG 5 BP'!$F$2:$EE$2,AY$4,'SPACELOG 5 BP'!$F$6:$EE$6)+SUMIF('SPACELOG 6 BP'!$F$2:$EE$2,AY$4,'SPACELOG 6 BP'!$F$6:$EE$6)+SUMIF('SPACELOG 7 BP'!$F$2:$EE$2,AY$4,'SPACELOG 7 BP'!$F$6:$EE$6)+SUMIF('SPACELOG 8 BP'!$F$2:$EE$2,AY$4,'SPACELOG 8 BP'!$F$6:$EE$6)+SUMIF('SPACELOG 9 BP'!$F$2:$EE$2,AY$4,'SPACELOG 9 BP'!$F$6:$EE$6)+SUMIF('SPACELOG 10 BP'!$F$2:$EE$2,AY$4,'SPACELOG 10 BP'!$F$6:$EE$6)+SUMIF('SPACELOG 11 BP'!$F$2:$EE$2,AY$4,'SPACELOG 11 BP'!$F$6:$EE$6)+SUMIF('SPACELOG 12 BP'!$F$2:$EE$2,AY$4,'SPACELOG 12 BP'!$F$6:$EE$6) -> 128185 | AZ6: =SUMIF('reporting montigny'!$F$2:$EE$2,AZ$4,'reporting montigny'!$F$6:$EE$6)+SUMIF('reporting boissy'!$F$2:$EE$2,AZ$4,'reporting boissy'!$F$6:$EE$6)+SUMIF('reporting moussy'!$F$2:$EE$2,AZ$4,'reporting moussy'!$F$6:$EE$6)+SUMIF('reporting trappes'!$F$2:$EE$2,AZ$4,'reporting trappes'!$F$6:$EE$6)+SUMIF('SPACELOG 5 BP'!$F$2:$EE$2,AZ$4,'SPACELOG 5 BP'!$F$6:$EE$6)+SUMIF('SPACELOG 6 BP'!$F$2:$EE$2,AZ$4,'SPACELOG 6 BP'!$F$6:$EE$6)+SUMIF('SPACELOG 7 BP'!$F$2:$EE$2,AZ$4,'SPACELOG 7 BP'!$F$6:$EE$6)+SUMIF('SPACELOG 8 BP'!$F$2:$EE$2,AZ$4,'SPACELOG 8 BP'!$F$6:$EE$6)+SUMIF('SPACELOG 9 BP'!$F$2:$EE$2,AZ$4,'SPACELOG 9 BP'!$F$6:$EE$6)+SUMIF('SPACELOG 10 BP'!$F$2:$EE$2,AZ$4,'SPACELOG 10 BP'!$F$6:$EE$6)+SUMIF('SPACELOG 11 BP'!$F$2:$EE$2,AZ$4,'SPACELOG 11 BP'!$F$6:$EE$6)+SUMIF('SPACELOG 12 BP'!$F$2:$EE$2,AZ$4,'SPACELOG 12 BP'!$F$6:$EE$6) -> 128185 | ... BD6: =SUMIF('reporting montigny'!$F$2:$EE$2,BD$4,'reporting montigny'!$F$6:$EE$6)+SUMIF('reporting boissy'!$F$2:$EE$2,BD$4,'reporting boissy'!$F$6:$EE$6)+SUMIF('reporting moussy'!$F$2:$EE$2,BD$4,'reporting moussy'!$F$6:$EE$6)+SUMIF('reporting trappes'!$F$2:$EE$2,BD$4,'reporting trappes'!$F$6:$EE$6)+SUMIF('SPACELOG 5 BP'!$F$2:$EE$2,BD$4,'SPACELOG 5 BP'!$F$6:$EE$6)+SUMIF('SPACELOG 6 BP'!$F$2:$EE$2,BD$4,'SPACELOG 6 BP'!$F$6:$EE$6)+SUMIF('SPACELOG 7 BP'!$F$2:$EE$2,BD$4,'SPACELOG 7 BP'!$F$6:$EE$6)+SUMIF('SPACELOG 8 BP'!$F$2:$EE$2,BD$4,'SPACELOG 8 BP'!$F$6:$EE$6)+SUMIF('SPACELOG 9 BP'!$F$2:$EE$2,BD$4,'SPACELOG 9 BP'!$F$6:$EE$6)+SUMIF('SPACELOG 10 BP'!$F$2:$EE$2,BD$4,'SPACELOG 10 BP'!$F$6:$EE$6)+SUMIF('SPACELOG 11 BP'!$F$2:$EE$2,BD$4,'SPACELOG 11 BP'!$F$6:$EE$6)+SUMIF('SPACELOG 12 BP'!$F$2:$EE$2,BD$4,'SPACELOG 12 BP'!$F$6:$EE$6) -> 128185 | BE6: =SUM(AS6:BD6) -> 1538220 | BF6: =SUMIF('reporting montigny'!$F$2:$EE$2,BF$4,'reporting montigny'!$F$6:$EE$6)+SUMIF('reporting boissy'!$F$2:$EE$2,BF$4,'reporting boissy'!$F$6:$EE$6)+SUMIF('reporting moussy'!$F$2:$EE$2,BF$4,'reporting moussy'!$F$6:$EE$6)+SUMIF('reporting trappes'!$F$2:$EE$2,BF$4,'reporting trappes'!$F$6:$EE$6)+SUMIF('SPACELOG 5 BP'!$F$2:$EE$2,BF$4,'SPACELOG 5 BP'!$F$6:$EE$6)+SUMIF('SPACELOG 6 BP'!$F$2:$EE$2,BF$4,'SPACELOG 6 BP'!$F$6:$EE$6)+SUMIF('SPACELOG 7 BP'!$F$2:$EE$2,BF$4,'SPACELOG 7 BP'!$F$6:$EE$6)+SUMIF('SPACELOG 8 BP'!$F$2:$EE$2,BF$4,'SPACELOG 8 BP'!$F$6:$EE$6)+SUMIF('SPACELOG 9 BP'!$F$2:$EE$2,BF$4,'SPACELOG 9 BP'!$F$6:$EE$6)+SUMIF('SPACELOG 10 BP'!$F$2:$EE$2,BF$4,'SPACELOG 10 BP'!$F$6:$EE$6)+SUMIF('SPACELOG 11 BP'!$F$2:$EE$2,BF$4,'SPACELOG 11 BP'!$F$6:$EE$6)+SUMIF('SPACELOG 12 BP'!$F$2:$EE$2,BF$4,'SPACELOG 12 BP'!$F$6:$EE$6) -> 128185 | BG6: =SUMIF('reporting montigny'!$F$2:$EE$2,BG$4,'reporting montigny'!$F$6:$EE$6)+SUMIF('reporting boissy'!$F$2:$EE$2,BG$4,'reporting boissy'!$F$6:$EE$6)+SUMIF('reporting moussy'!$F$2:$EE$2,BG$4,'reporting moussy'!$F$6:$EE$6)+SUMIF('reporting trappes'!$F$2:$EE$2,BG$4,'reporting trappes'!$F$6:$EE$6)+SUMIF('SPACELOG 5 BP'!$F$2:$EE$2,BG$4,'SPACELOG 5 BP'!$F$6:$EE$6)+SUMIF('SPACELOG 6 BP'!$F$2:$EE$2,BG$4,'SPACELOG 6 BP'!$F$6:$EE$6)+SUMIF('SPACELOG 7 BP'!$F$2:$EE$2,BG$4,'SPACELOG 7 BP'!$F$6:$EE$6)+SUMIF('SPACELOG 8 BP'!$F$2:$EE$2,BG$4,'SPACELOG 8 BP'!$F$6:$EE$6)+SUMIF('SPACELOG 9 BP'!$F$2:$EE$2,BG$4,'SPACELOG 9 BP'!$F$6:$EE$6)+SUMIF('SPACELOG 10 BP'!$F$2:$EE$2,BG$4,'SPACELOG 10 BP'!$F$6:$EE$6)+SUMIF('SPACELOG 11 BP'!$F$2:$EE$2,BG$4,'SPACELOG 11 BP'!$F$6:$EE$6)+SUMIF('SPACELOG 12 BP'!$F$2:$EE$2,BG$4,'SPACELOG 12 BP'!$F$6:$EE$6) -> 128185 | BH6: =SUMIF('reporting montigny'!$F$2:$EE$2,BH$4,'reporting montigny'!$F$6:$EE$6)+SUMIF('reporting boissy'!$F$2:$EE$2,BH$4,'reporting boissy'!$F$6:$EE$6)+SUMIF('reporting moussy'!$F$2:$EE$2,BH$4,'reporting moussy'!$F$6:$EE$6)+SUMIF('reporting trappes'!$F$2:$EE$2,BH$4,'reporting trappes'!$F$6:$EE$6)+SUMIF('SPACELOG 5 BP'!$F$2:$EE$2,BH$4,'SPACELOG 5 BP'!$F$6:$EE$6)+SUMIF('SPACELOG 6 BP'!$F$2:$EE$2,BH$4,'SPACELOG 6 BP'!$F$6:$EE$6)+SUMIF('SPACELOG 7 BP'!$F$2:$EE$2,BH$4,'SPACELOG 7 BP'!$F$6:$EE$6)+SUMIF('SPACELOG 8 BP'!$F$2:$EE$2,BH$4,'SPACELOG 8 BP'!$F$6:$EE$6)+SUMIF('SPACELOG 9 BP'!$F$2:$EE$2,BH$4,'SPACELOG 9 BP'!$F$6:$EE$6)+SUMIF('SPACELOG 10 BP'!$F$2:$EE$2,BH$4,'SPACELOG 10 BP'!$F$6:$EE$6)+SUMIF('SPACELOG 11 BP'!$F$2:$EE$2,BH$4,'SPACELOG 11 BP'!$F$6:$EE$6)+SUMIF('SPACELOG 12 BP'!$F$2:$EE$2,BH$4,'SPACELOG 12 BP'!$F$6:$EE$6) -> 128185 | BI6: =SUMIF('reporting montigny'!$F$2:$EE$2,BI$4,'reporting montigny'!$F$6:$EE$6)+SUMIF('reporting boissy'!$F$2:$EE$2,BI$4,'reporting boissy'!$F$6:$EE$6)+SUMIF('reporting moussy'!$F$2:$EE$2,BI$4,'reporting moussy'!$F$6:$EE$6)+SUMIF('reporting trappes'!$F$2:$EE$2,BI$4,'reporting trappes'!$F$6:$EE$6)+SUMIF('SPACELOG 5 BP'!$F$2:$EE$2,BI$4,'SPACELOG 5 BP'!$F$6:$EE$6)+SUMIF('SPACELOG 6 BP'!$F$2:$EE$2,BI$4,'SPACELOG 6 BP'!$F$6:$EE$6)+SUMIF('SPACELOG 7 BP'!$F$2:$EE$2,BI$4,'SPACELOG 7 BP'!$F$6:$EE$6)+SUMIF('SPACELOG 8 BP'!$F$2:$EE$2,BI$4,'SPACELOG 8 BP'!$F$6:$EE$6)+SUMIF('SPACELOG 9 BP'!$F$2:$EE$2,BI$4,'SPACELOG 9 BP'!$F$6:$EE$6)+SUMIF('SPACELOG 10 BP'!$F$2:$EE$2,BI$4,'SPACELOG 10 BP'!$F$6:$EE$6)+SUMIF('SPACELOG 11 BP'!$F$2:$EE$2,BI$4,'SPACELOG 11 BP'!$F$6:$EE$6)+SUMIF('SPACELOG 12 BP'!$F$2:$EE$2,BI$4,'SPACELOG 12 BP'!$F$6:$EE$6) -> 128185 | BJ6: =SUMIF('reporting montigny'!$F$2:$EE$2,BJ$4,'reporting montigny'!$F$6:$EE$6)+SUMIF('reporting boissy'!$F$2:$EE$2,BJ$4,'reporting boissy'!$F$6:$EE$6)+SUMIF('reporting moussy'!$F$2:$EE$2,BJ$4,'reporting moussy'!$F$6:$EE$6)+SUMIF('reporting trappes'!$F$2:$EE$2,BJ$4,'reporting trappes'!$F$6:$EE$6)+SUMIF('SPACELOG 5 BP'!$F$2:$EE$2,BJ$4,'SPACELOG 5 BP'!$F$6:$EE$6)+SUMIF('SPACELOG 6 BP'!$F$2:$EE$2,BJ$4,'SPACELOG 6 BP'!$F$6:$EE$6)+SUMIF('SPACELOG 7 BP'!$F$2:$EE$2,BJ$4,'SPACELOG 7 BP'!$F$6:$EE$6)+SUMIF('SPACELOG 8 BP'!$F$2:$EE$2,BJ$4,'SPACELOG 8 BP'!$F$6:$EE$6)+SUMIF('SPACELOG 9 BP'!$F$2:$EE$2,BJ$4,'SPACELOG 9 BP'!$F$6:$EE$6)+SUMIF('SPACELOG 10 BP'!$F$2:$EE$2,BJ$4,'SPACELOG 10 BP'!$F$6:$EE$6)+SUMIF('SPACELOG 11 BP'!$F$2:$EE$2,BJ$4,'SPACELOG 11 BP'!$F$6:$EE$6)+SUMIF('SPACELOG 12 BP'!$F$2:$EE$2,BJ$4,'SPACELOG 12 BP'!$F$6:$EE$6) -> 128185 | BK6: =SUMIF('reporting montigny'!$F$2:$EE$2,BK$4,'reporting montigny'!$F$6:$EE$6)+SUMIF('reporting boissy'!$F$2:$EE$2,BK$4,'reporting boissy'!$F$6:$EE$6)+SUMIF('reporting moussy'!$F$2:$EE$2,BK$4,'reporting moussy'!$F$6:$EE$6)+SUMIF('reporting trappes'!$F$2:$EE$2,BK$4,'reporting trappes'!$F$6:$EE$6)+SUMIF('SPACELOG 5 BP'!$F$2:$EE$2,BK$4,'SPACELOG 5 BP'!$F$6:$EE$6)+SUMIF('SPACELOG 6 BP'!$F$2:$EE$2,BK$4,'SPACELOG 6 BP'!$F$6:$EE$6)+SUMIF('SPACELOG 7 BP'!$F$2:$EE$2,BK$4,'SPACELOG 7 BP'!$F$6:$EE$6)+SUMIF('SPACELOG 8 BP'!$F$2:$EE$2,BK$4,'SPACELOG 8 BP'!$F$6:$EE$6)+SUMIF('SPACELOG 9 BP'!$F$2:$EE$2,BK$4,'SPACELOG 9 BP'!$F$6:$EE$6)+SUMIF('SPACELOG 10 BP'!$F$2:$EE$2,BK$4,'SPACELOG 10 BP'!$F$6:$EE$6)+SUMIF('SPACELOG 11 BP'!$F$2:$EE$2,BK$4,'SPACELOG 11 BP'!$F$6:$EE$6)+SUMIF('SPACELOG 12 BP'!$F$2:$EE$2,BK$4,'SPACELOG 12 BP'!$F$6:$EE$6) -> 128185 | BL6: =SUMIF('reporting montigny'!$F$2:$EE$2,BL$4,'reporting montigny'!$F$6:$EE$6)+SUMIF('reporting boissy'!$F$2:$EE$2,BL$4,'reporting boissy'!$F$6:$EE$6)+SUMIF('reporting moussy'!$F$2:$EE$2,BL$4,'reporting moussy'!$F$6:$EE$6)+SUMIF('reporting trappes'!$F$2:$EE$2,BL$4,'reporting trappes'!$F$6:$EE$6)+SUMIF('SPACELOG 5 BP'!$F$2:$EE$2,BL$4,'SPACELOG 5 BP'!$F$6:$EE$6)+SUMIF('SPACELOG 6 BP'!$F$2:$EE$2,BL$4,'SPACELOG 6 BP'!$F$6:$EE$6)+SUMIF('SPACELOG 7 BP'!$F$2:$EE$2,BL$4,'SPACELOG 7 BP'!$F$6:$EE$6)+SUMIF('SPACELOG 8 BP'!$F$2:$EE$2,BL$4,'SPACELOG 8 BP'!$F$6:$EE$6)+SUMIF('SPACELOG 9 BP'!$F$2:$EE$2,BL$4,'SPACELOG 9 BP'!$F$6:$EE$6)+SUMIF('SPACELOG 10 BP'!$F$2:$EE$2,BL$4,'SPACELOG 10 BP'!$F$6:$EE$6)+SUMIF('SPACELOG 11 BP'!$F$2:$EE$2,BL$4,'SPACELOG 11 BP'!$F$6:$EE$6)+SUMIF('SPACELOG 12 BP'!$F$2:$EE$2,BL$4,'SPACELOG 12 BP'!$F$6:$EE$6) -> 128185 | BM6: =SUMIF('reporting montigny'!$F$2:$EE$2,BM$4,'reporting montigny'!$F$6:$EE$6)+SUMIF('reporting boissy'!$F$2:$EE$2,BM$4,'reporting boissy'!$F$6:$EE$6)+SUMIF('reporting moussy'!$F$2:$EE$2,BM$4,'reporting moussy'!$F$6:$EE$6)+SUMIF('reporting trappes'!$F$2:$EE$2,BM$4,'reporting trappes'!$F$6:$EE$6)+SUMIF('SPACELOG 5 BP'!$F$2:$EE$2,BM$4,'SPACELOG 5 BP'!$F$6:$EE$6)+SUMIF('SPACELOG 6 BP'!$F$2:$EE$2,BM$4,'SPACELOG 6 BP'!$F$6:$EE$6)+SUMIF('SPACELOG 7 BP'!$F$2:$EE$2,BM$4,'SPACELOG 7 BP'!$F$6:$EE$6)+SUMIF('SPACELOG 8 BP'!$F$2:$EE$2,BM$4,'SPACELOG 8 BP'!$F$6:$EE$6)+SUMIF('SPACELOG 9 BP'!$F$2:$EE$2,BM$4,'SPACELOG 9 BP'!$F$6:$EE$6)+SUMIF('SPACELOG 10 BP'!$F$2:$EE$2,BM$4,'SPACELOG 10 BP'!$F$6:$EE$6)+SUMIF('SPACELOG 11 BP'!$F$2:$EE$2,BM$4,'SPACELOG 11 BP'!$F$6:$EE$6)+SUMIF('SPACELOG 12 BP'!$F$2:$EE$2,BM$4,'SPACELOG 12 BP'!$F$6:$EE$6) -> 128185 | ... BQ6: =SUMIF('reporting montigny'!$F$2:$EE$2,BQ$4,'reporting montigny'!$F$6:$EE$6)+SUMIF('reporting boissy'!$F$2:$EE$2,BQ$4,'reporting boissy'!$F$6:$EE$6)+SUMIF('reporting moussy'!$F$2:$EE$2,BQ$4,'reporting moussy'!$F$6:$EE$6)+SUMIF('reporting trappes'!$F$2:$EE$2,BQ$4,'reporting trappes'!$F$6:$EE$6)+SUMIF('SPACELOG 5 BP'!$F$2:$EE$2,BQ$4,'SPACELOG 5 BP'!$F$6:$EE$6)+SUMIF('SPACELOG 6 BP'!$F$2:$EE$2,BQ$4,'SPACELOG 6 BP'!$F$6:$EE$6)+SUMIF('SPACELOG 7 BP'!$F$2:$EE$2,BQ$4,'SPACELOG 7 BP'!$F$6:$EE$6)+SUMIF('SPACELOG 8 BP'!$F$2:$EE$2,BQ$4,'SPACELOG 8 BP'!$F$6:$EE$6)+SUMIF('SPACELOG 9 BP'!$F$2:$EE$2,BQ$4,'SPACELOG 9 BP'!$F$6:$EE$6)+SUMIF('SPACELOG 10 BP'!$F$2:$EE$2,BQ$4,'SPACELOG 10 BP'!$F$6:$EE$6)+SUMIF('SPACELOG 11 BP'!$F$2:$EE$2,BQ$4,'SPACELOG 11 BP'!$F$6:$EE$6)+SUMIF('SPACELOG 12 BP'!$F$2:$EE$2,BQ$4,'SPACELOG 12 BP'!$F$6:$EE$6) -> 128185 | BR6: =SUM(BF6:BQ6) -> 1538220 | BS6: =SUMIF('reporting montigny'!$F$2:$EE$2,BS$4,'reporting montigny'!$F$6:$EE$6)+SUMIF('reporting boissy'!$F$2:$EE$2,BS$4,'reporting boissy'!$F$6:$EE$6)+SUMIF('reporting moussy'!$F$2:$EE$2,BS$4,'reporting moussy'!$F$6:$EE$6)+SUMIF('reporting trappes'!$F$2:$EE$2,BS$4,'reporting trappes'!$F$6:$EE$6)+SUMIF('SPACELOG 5 BP'!$F$2:$EE$2,BS$4,'SPACELOG 5 BP'!$F$6:$EE$6)+SUMIF('SPACELOG 6 BP'!$F$2:$EE$2,BS$4,'SPACELOG 6 BP'!$F$6:$EE$6)+SUMIF('SPACELOG 7 BP'!$F$2:$EE$2,BS$4,'SPACELOG 7 BP'!$F$6:$EE$6)+SUMIF('SPACELOG 8 BP'!$F$2:$EE$2,BS$4,'SPACELOG 8 BP'!$F$6:$EE$6)+SUMIF('SPACELOG 9 BP'!$F$2:$EE$2,BS$4,'SPACELOG 9 BP'!$F$6:$EE$6)+SUMIF('SPACELOG 10 BP'!$F$2:$EE$2,BS$4,'SPACELOG 10 BP'!$F$6:$EE$6)+SUMIF('SPACELOG 11 BP'!$F$2:$EE$2,BS$4,'SPACELOG 11 BP'!$F$6:$EE$6)+SUMIF('SPACELOG 12 BP'!$F$2:$EE$2,BS$4,'SPACELOG 12 BP'!$F$6:$EE$6) -> 128185 | BT6: =SUMIF('reporting montigny'!$F$2:$EE$2,BT$4,'reporting montigny'!$F$6:$EE$6)+SUMIF('reporting boissy'!$F$2:$EE$2,BT$4,'reporting boissy'!$F$6:$EE$6)+SUMIF('reporting moussy'!$F$2:$EE$2,BT$4,'reporting moussy'!$F$6:$EE$6)+SUMIF('reporting trappes'!$F$2:$EE$2,BT$4,'reporting trappes'!$F$6:$EE$6)+SUMIF('SPACELOG 5 BP'!$F$2:$EE$2,BT$4,'SPACELOG 5 BP'!$F$6:$EE$6)+SUMIF('SPACELOG 6 BP'!$F$2:$EE$2,BT$4,'SPACELOG 6 BP'!$F$6:$EE$6)+SUMIF('SPACELOG 7 BP'!$F$2:$EE$2,BT$4,'SPACELOG 7 BP'!$F$6:$EE$6)+SUMIF('SPACELOG 8 BP'!$F$2:$EE$2,BT$4,'SPACELOG 8 BP'!$F$6:$EE$6)+SUMIF('SPACELOG 9 BP'!$F$2:$EE$2,BT$4,'SPACELOG 9 BP'!$F$6:$EE$6)+SUMIF('SPACELOG 10 BP'!$F$2:$EE$2,BT$4,'SPACELOG 10 BP'!$F$6:$EE$6)+SUMIF('SPACELOG 11 BP'!$F$2:$EE$2,BT$4,'SPACELOG 11 BP'!$F$6:$EE$6)+SUMIF('SPACELOG 12 BP'!$F$2:$EE$2,BT$4,'SPACELOG 12 BP'!$F$6:$EE$6) -> 128185 | BU6: =SUMIF('reporting montigny'!$F$2:$EE$2,BU$4,'reporting montigny'!$F$6:$EE$6)+SUMIF('reporting boissy'!$F$2:$EE$2,BU$4,'reporting boissy'!$F$6:$EE$6)+SUMIF('reporting moussy'!$F$2:$EE$2,BU$4,'reporting moussy'!$F$6:$EE$6)+SUMIF('reporting trappes'!$F$2:$EE$2,BU$4,'reporting trappes'!$F$6:$EE$6)+SUMIF('SPACELOG 5 BP'!$F$2:$EE$2,BU$4,'SPACELOG 5 BP'!$F$6:$EE$6)+SUMIF('SPACELOG 6 BP'!$F$2:$EE$2,BU$4,'SPACELOG 6 BP'!$F$6:$EE$6)+SUMIF('SPACELOG 7 BP'!$F$2:$EE$2,BU$4,'SPACELOG 7 BP'!$F$6:$EE$6)+SUMIF('SPACELOG 8 BP'!$F$2:$EE$2,BU$4,'SPACELOG 8 BP'!$F$6:$EE$6)+SUMIF('SPACELOG 9 BP'!$F$2:$EE$2,BU$4,'SPACELOG 9 BP'!$F$6:$EE$6)+SUMIF('SPACELOG 10 BP'!$F$2:$EE$2,BU$4,'SPACELOG 10 BP'!$F$6:$EE$6)+SUMIF('SPACELOG 11 BP'!$F$2:$EE$2,BU$4,'SPACELOG 11 BP'!$F$6:$EE$6)+SUMIF('SPACELOG 12 BP'!$F$2:$EE$2,BU$4,'SPACELOG 12 BP'!$F$6:$EE$6) -> 128185 | BV6: =SUMIF('reporting montigny'!$F$2:$EE$2,BV$4,'reporting montigny'!$F$6:$EE$6)+SUMIF('reporting boissy'!$F$2:$EE$2,BV$4,'reporting boissy'!$F$6:$EE$6)+SUMIF('reporting moussy'!$F$2:$EE$2,BV$4,'reporting moussy'!$F$6:$EE$6)+SUMIF('reporting trappes'!$F$2:$EE$2,BV$4,'reporting trappes'!$F$6:$EE$6)+SUMIF('SPACELOG 5 BP'!$F$2:$EE$2,BV$4,'SPACELOG 5 BP'!$F$6:$EE$6)+SUMIF('SPACELOG 6 BP'!$F$2:$EE$2,BV$4,'SPACELOG 6 BP'!$F$6:$EE$6)+SUMIF('SPACELOG 7 BP'!$F$2:$EE$2,BV$4,'SPACELOG 7 BP'!$F$6:$EE$6)+SUMIF('SPACELOG 8 BP'!$F$2:$EE$2,BV$4,'SPACELOG 8 BP'!$F$6:$EE$6)+SUMIF('SPACELOG 9 BP'!$F$2:$EE$2,BV$4,'SPACELOG 9 BP'!$F$6:$EE$6)+SUMIF('SPACELOG 10 BP'!$F$2:$EE$2,BV$4,'SPACELOG 10 BP'!$F$6:$EE$6)+SUMIF('SPACELOG 11 BP'!$F$2:$EE$2,BV$4,'SPACELOG 11 BP'!$F$6:$EE$6)+SUMIF('SPACELOG 12 BP'!$F$2:$EE$2,BV$4,'SPACELOG 12 BP'!$F$6:$EE$6) -> 128185 | BW6: =SUMIF('reporting montigny'!$F$2:$EE$2,BW$4,'reporting montigny'!$F$6:$EE$6)+SUMIF('reporting boissy'!$F$2:$EE$2,BW$4,'reporting boissy'!$F$6:$EE$6)+SUMIF('reporting moussy'!$F$2:$EE$2,BW$4,'reporting moussy'!$F$6:$EE$6)+SUMIF('reporting trappes'!$F$2:$EE$2,BW$4,'reporting trappes'!$F$6:$EE$6)+SUMIF('SPACELOG 5 BP'!$F$2:$EE$2,BW$4,'SPACELOG 5 BP'!$F$6:$EE$6)+SUMIF('SPACELOG 6 BP'!$F$2:$EE$2,BW$4,'SPACELOG 6 BP'!$F$6:$EE$6)+SUMIF('SPACELOG 7 BP'!$F$2:$EE$2,BW$4,'SPACELOG 7 BP'!$F$6:$EE$6)+SUMIF('SPACELOG 8 BP'!$F$2:$EE$2,BW$4,'SPACELOG 8 BP'!$F$6:$EE$6)+SUMIF('SPACELOG 9 BP'!$F$2:$EE$2,BW$4,'SPACELOG 9 BP'!$F$6:$EE$6)+SUMIF('SPACELOG 10 BP'!$F$2:$EE$2,BW$4,'SPACELOG 10 BP'!$F$6:$EE$6)+SUMIF('SPACELOG 11 BP'!$F$2:$EE$2,BW$4,'SPACELOG 11 BP'!$F$6:$EE$6)+SUMIF('SPACELOG 12 BP'!$F$2:$EE$2,BW$4,'SPACELOG 12 BP'!$F$6:$EE$6) -> 128185 | BX6: =SUMIF('reporting montigny'!$F$2:$EE$2,BX$4,'reporting montigny'!$F$6:$EE$6)+SUMIF('reporting boissy'!$F$2:$EE$2,BX$4,'reporting boissy'!$F$6:$EE$6)+SUMIF('reporting moussy'!$F$2:$EE$2,BX$4,'reporting moussy'!$F$6:$EE$6)+SUMIF('reporting trappes'!$F$2:$EE$2,BX$4,'reporting trappes'!$F$6:$EE$6)+SUMIF('SPACELOG 5 BP'!$F$2:$EE$2,BX$4,'SPACELOG 5 BP'!$F$6:$EE$6)+SUMIF('SPACELOG 6 BP'!$F$2:$EE$2,BX$4,'SPACELOG 6 BP'!$F$6:$EE$6)+SUMIF('SPACELOG 7 BP'!$F$2:$EE$2,BX$4,'SPACELOG 7 BP'!$F$6:$EE$6)+SUMIF('SPACELOG 8 BP'!$F$2:$EE$2,BX$4,'SPACELOG 8 BP'!$F$6:$EE$6)+SUMIF('SPACELOG 9 BP'!$F$2:$EE$2,BX$4,'SPACELOG 9 BP'!$F$6:$EE$6)+SUMIF('SPACELOG 10 BP'!$F$2:$EE$2,BX$4,'SPACELOG 10 BP'!$F$6:$EE$6)+SUMIF('SPACELOG 11 BP'!$F$2:$EE$2,BX$4,'SPACELOG 11 BP'!$F$6:$EE$6)+SUMIF('SPACELOG 12 BP'!$F$2:$EE$2,BX$4,'SPACELOG 12 BP'!$F$6:$EE$6) -> 128185 | BY6: =SUMIF('reporting montigny'!$F$2:$EE$2,BY$4,'reporting montigny'!$F$6:$EE$6)+SUMIF('reporting boissy'!$F$2:$EE$2,BY$4,'reporting boissy'!$F$6:$EE$6)+SUMIF('reporting moussy'!$F$2:$EE$2,BY$4,'reporting moussy'!$F$6:$EE$6)+SUMIF('reporting trappes'!$F$2:$EE$2,BY$4,'reporting trappes'!$F$6:$EE$6)+SUMIF('SPACELOG 5 BP'!$F$2:$EE$2,BY$4,'SPACELOG 5 BP'!$F$6:$EE$6)+SUMIF('SPACELOG 6 BP'!$F$2:$EE$2,BY$4,'SPACELOG 6 BP'!$F$6:$EE$6)+SUMIF('SPACELOG 7 BP'!$F$2:$EE$2,BY$4,'SPACELOG 7 BP'!$F$6:$EE$6)+SUMIF('SPACELOG 8 BP'!$F$2:$EE$2,BY$4,'SPACELOG 8 BP'!$F$6:$EE$6)+SUMIF('SPACELOG 9 BP'!$F$2:$EE$2,BY$4,'SPACELOG 9 BP'!$F$6:$EE$6)+SUMIF('SPACELOG 10 BP'!$F$2:$EE$2,BY$4,'SPACELOG 10 BP'!$F$6:$EE$6)+SUMIF('SPACELOG 11 BP'!$F$2:$EE$2,BY$4,'SPACELOG 11 BP'!$F$6:$EE$6)+SUMIF('SPACELOG 12 BP'!$F$2:$EE$2,BY$4,'SPACELOG 12 BP'!$F$6:$EE$6) -> 128185 | BZ6: =SUMIF('reporting montigny'!$F$2:$EE$2,BZ$4,'reporting montigny'!$F$6:$EE$6)+SUMIF('reporting boissy'!$F$2:$EE$2,BZ$4,'reporting boissy'!$F$6:$EE$6)+SUMIF('reporting moussy'!$F$2:$EE$2,BZ$4,'reporting moussy'!$F$6:$EE$6)+SUMIF('reporting trappes'!$F$2:$EE$2,BZ$4,'reporting trappes'!$F$6:$EE$6)+SUMIF('SPACELOG 5 BP'!$F$2:$EE$2,BZ$4,'SPACELOG 5 BP'!$F$6:$EE$6)+SUMIF('SPACELOG 6 BP'!$F$2:$EE$2,BZ$4,'SPACELOG 6 BP'!$F$6:$EE$6)+SUMIF('SPACELOG 7 BP'!$F$2:$EE$2,BZ$4,'SPACELOG 7 BP'!$F$6:$EE$6)+SUMIF('SPACELOG 8 BP'!$F$2:$EE$2,BZ$4,'SPACELOG 8 BP'!$F$6:$EE$6)+SUMIF('SPACELOG 9 BP'!$F$2:$EE$2,BZ$4,'SPACELOG 9 BP'!$F$6:$EE$6)+SUMIF('SPACELOG 10 BP'!$F$2:$EE$2,BZ$4,'SPACELOG 10 BP'!$F$6:$EE$6)+SUMIF('SPACELOG 11 BP'!$F$2:$EE$2,BZ$4,'SPACELOG 11 BP'!$F$6:$EE$6)+SUMIF('SPACELOG 12 BP'!$F$2:$EE$2,BZ$4,'SPACELOG 12 BP'!$F$6:$EE$6) -> 128185 | ... CD6: =SUMIF('reporting montigny'!$F$2:$EE$2,CD$4,'reporting montigny'!$F$6:$EE$6)+SUMIF('reporting boissy'!$F$2:$EE$2,CD$4,'reporting boissy'!$F$6:$EE$6)+SUMIF('reporting moussy'!$F$2:$EE$2,CD$4,'reporting moussy'!$F$6:$EE$6)+SUMIF('reporting trappes'!$F$2:$EE$2,CD$4,'reporting trappes'!$F$6:$EE$6)+SUMIF('SPACELOG 5 BP'!$F$2:$EE$2,CD$4,'SPACELOG 5 BP'!$F$6:$EE$6)+SUMIF('SPACELOG 6 BP'!$F$2:$EE$2,CD$4,'SPACELOG 6 BP'!$F$6:$EE$6)+SUMIF('SPACELOG 7 BP'!$F$2:$EE$2,CD$4,'SPACELOG 7 BP'!$F$6:$EE$6)+SUMIF('SPACELOG 8 BP'!$F$2:$EE$2,CD$4,'SPACELOG 8 BP'!$F$6:$EE$6)+SUMIF('SPACELOG 9 BP'!$F$2:$EE$2,CD$4,'SPACELOG 9 BP'!$F$6:$EE$6)+SUMIF('SPACELOG 10 BP'!$F$2:$EE$2,CD$4,'SPACELOG 10 BP'!$F$6:$EE$6)+SUMIF('SPACELOG 11 BP'!$F$2:$EE$2,CD$4,'SPACELOG 11 BP'!$F$6:$EE$6)+SUMIF('SPACELOG 12 BP'!$F$2:$EE$2,CD$4,'SPACELOG 12 BP'!$F$6:$EE$6) -> 128185 | CE6: =SUM(BS6:CD6) -> 1538220 | CF6: =SUMIF('reporting montigny'!$F$2:$EE$2,CF$4,'reporting montigny'!$F$6:$EE$6)+SUMIF('reporting boissy'!$F$2:$EE$2,CF$4,'reporting boissy'!$F$6:$EE$6)+SUMIF('reporting moussy'!$F$2:$EE$2,CF$4,'reporting moussy'!$F$6:$EE$6)+SUMIF('reporting trappes'!$F$2:$EE$2,CF$4,'reporting trappes'!$F$6:$EE$6)+SUMIF('SPACELOG 5 BP'!$F$2:$EE$2,CF$4,'SPACELOG 5 BP'!$F$6:$EE$6)+SUMIF('SPACELOG 6 BP'!$F$2:$EE$2,CF$4,'SPACELOG 6 BP'!$F$6:$EE$6)+SUMIF('SPACELOG 7 BP'!$F$2:$EE$2,CF$4,'SPACELOG 7 BP'!$F$6:$EE$6)+SUMIF('SPACELOG 8 BP'!$F$2:$EE$2,CF$4,'SPACELOG 8 BP'!$F$6:$EE$6)+SUMIF('SPACELOG 9 BP'!$F$2:$EE$2,CF$4,'SPACELOG 9 BP'!$F$6:$EE$6)+SUMIF('SPACELOG 10 BP'!$F$2:$EE$2,CF$4,'SPACELOG 10 BP'!$F$6:$EE$6)+SUMIF('SPACELOG 11 BP'!$F$2:$EE$2,CF$4,'SPACELOG 11 BP'!$F$6:$EE$6)+SUMIF('SPACELOG 12 BP'!$F$2:$EE$2,CF$4,'SPACELOG 12 BP'!$F$6:$EE$6) -> 128185 | CG6: =SUMIF('reporting montigny'!$F$2:$EE$2,CG$4,'reporting montigny'!$F$6:$EE$6)+SUMIF('reporting boissy'!$F$2:$EE$2,CG$4,'reporting boissy'!$F$6:$EE$6)+SUMIF('reporting moussy'!$F$2:$EE$2,CG$4,'reporting moussy'!$F$6:$EE$6)+SUMIF('reporting trappes'!$F$2:$EE$2,CG$4,'reporting trappes'!$F$6:$EE$6)+SUMIF('SPACELOG 5 BP'!$F$2:$EE$2,CG$4,'SPACELOG 5 BP'!$F$6:$EE$6)+SUMIF('SPACELOG 6 BP'!$F$2:$EE$2,CG$4,'SPACELOG 6 BP'!$F$6:$EE$6)+SUMIF('SPACELOG 7 BP'!$F$2:$EE$2,CG$4,'SPACELOG 7 BP'!$F$6:$EE$6)+SUMIF('SPACELOG 8 BP'!$F$2:$EE$2,CG$4,'SPACELOG 8 BP'!$F$6:$EE$6)+SUMIF('SPACELOG 9 BP'!$F$2:$EE$2,CG$4,'SPACELOG 9 BP'!$F$6:$EE$6)+SUMIF('SPACELOG 10 BP'!$F$2:$EE$2,CG$4,'SPACELOG 10 BP'!$F$6:$EE$6)+SUMIF('SPACELOG 11 BP'!$F$2:$EE$2,CG$4,'SPACELOG 11 BP'!$F$6:$EE$6)+SUMIF('SPACELOG 12 BP'!$F$2:$EE$2,CG$4,'SPACELOG 12 BP'!$F$6:$EE$6) -> 128185 | CH6: =SUMIF('reporting montigny'!$F$2:$EE$2,CH$4,'reporting montigny'!$F$6:$EE$6)+SUMIF('reporting boissy'!$F$2:$EE$2,CH$4,'reporting boissy'!$F$6:$EE$6)+SUMIF('reporting moussy'!$F$2:$EE$2,CH$4,'reporting moussy'!$F$6:$EE$6)+SUMIF('reporting trappes'!$F$2:$EE$2,CH$4,'reporting trappes'!$F$6:$EE$6)+SUMIF('SPACELOG 5 BP'!$F$2:$EE$2,CH$4,'SPACELOG 5 BP'!$F$6:$EE$6)+SUMIF('SPACELOG 6 BP'!$F$2:$EE$2,CH$4,'SPACELOG 6 BP'!$F$6:$EE$6)+SUMIF('SPACELOG 7 BP'!$F$2:$EE$2,CH$4,'SPACELOG 7 BP'!$F$6:$EE$6)+SUMIF('SPACELOG 8 BP'!$F$2:$EE$2,CH$4,'SPACELOG 8 BP'!$F$6:$EE$6)+SUMIF('SPACELOG 9 BP'!$F$2:$EE$2,CH$4,'SPACELOG 9 BP'!$F$6:$EE$6)+SUMIF('SPACELOG 10 BP'!$F$2:$EE$2,CH$4,'SPACELOG 10 BP'!$F$6:$EE$6)+SUMIF('SPACELOG 11 BP'!$F$2:$EE$2,CH$4,'SPACELOG 11 BP'!$F$6:$EE$6)+SUMIF('SPACELOG 12 BP'!$F$2:$EE$2,CH$4,'SPACELOG 12 BP'!$F$6:$EE$6) -> 128185 | CI6: =SUMIF('reporting montigny'!$F$2:$EE$2,CI$4,'reporting montigny'!$F$6:$EE$6)+SUMIF('reporting boissy'!$F$2:$EE$2,CI$4,'reporting boissy'!$F$6:$EE$6)+SUMIF('reporting moussy'!$F$2:$EE$2,CI$4,'reporting moussy'!$F$6:$EE$6)+SUMIF('reporting trappes'!$F$2:$EE$2,CI$4,'reporting trappes'!$F$6:$EE$6)+SUMIF('SPACELOG 5 BP'!$F$2:$EE$2,CI$4,'SPACELOG 5 BP'!$F$6:$EE$6)+SUMIF('SPACELOG 6 BP'!$F$2:$EE$2,CI$4,'SPACELOG 6 BP'!$F$6:$EE$6)+SUMIF('SPACELOG 7 BP'!$F$2:$EE$2,CI$4,'SPACELOG 7 BP'!$F$6:$EE$6)+SUMIF('SPACELOG 8 BP'!$F$2:$EE$2,CI$4,'SPACELOG 8 BP'!$F$6:$EE$6)+SUMIF('SPACELOG 9 BP'!$F$2:$EE$2,CI$4,'SPACELOG 9 BP'!$F$6:$EE$6)+SUMIF('SPACELOG 10 BP'!$F$2:$EE$2,CI$4,'SPACELOG 10 BP'!$F$6:$EE$6)+SUMIF('SPACELOG 11 BP'!$F$2:$EE$2,CI$4,'SPACELOG 11 BP'!$F$6:$EE$6)+SUMIF('SPACELOG 12 BP'!$F$2:$EE$2,CI$4,'SPACELOG 12 BP'!$F$6:$EE$6) -> 128185 | CJ6: =SUMIF('reporting montigny'!$F$2:$EE$2,CJ$4,'reporting montigny'!$F$6:$EE$6)+SUMIF('reporting boissy'!$F$2:$EE$2,CJ$4,'reporting boissy'!$F$6:$EE$6)+SUMIF('reporting moussy'!$F$2:$EE$2,CJ$4,'reporting moussy'!$F$6:$EE$6)+SUMIF('reporting trappes'!$F$2:$EE$2,CJ$4,'reporting trappes'!$F$6:$EE$6)+SUMIF('SPACELOG 5 BP'!$F$2:$EE$2,CJ$4,'SPACELOG 5 BP'!$F$6:$EE$6)+SUMIF('SPACELOG 6 BP'!$F$2:$EE$2,CJ$4,'SPACELOG 6 BP'!$F$6:$EE$6)+SUMIF('SPACELOG 7 BP'!$F$2:$EE$2,CJ$4,'SPACELOG 7 BP'!$F$6:$EE$6)+SUMIF('SPACELOG 8 BP'!$F$2:$EE$2,CJ$4,'SPACELOG 8 BP'!$F$6:$EE$6)+SUMIF('SPACELOG 9 BP'!$F$2:$EE$2,CJ$4,'SPACELOG 9 BP'!$F$6:$EE$6)+SUMIF('SPACELOG 10 BP'!$F$2:$EE$2,CJ$4,'SPACELOG 10 BP'!$F$6:$EE$6)+SUMIF('SPACELOG 11 BP'!$F$2:$EE$2,CJ$4,'SPACELOG 11 BP'!$F$6:$EE$6)+SUMIF('SPACELOG 12 BP'!$F$2:$EE$2,CJ$4,'SPACELOG 12 BP'!$F$6:$EE$6) -> 128185 | CK6: =SUMIF('reporting montigny'!$F$2:$EE$2,CK$4,'reporting montigny'!$F$6:$EE$6)+SUMIF('reporting boissy'!$F$2:$EE$2,CK$4,'reporting boissy'!$F$6:$EE$6)+SUMIF('reporting moussy'!$F$2:$EE$2,CK$4,'reporting moussy'!$F$6:$EE$6)+SUMIF('reporting trappes'!$F$2:$EE$2,CK$4,'reporting trappes'!$F$6:$EE$6)+SUMIF('SPACELOG 5 BP'!$F$2:$EE$2,CK$4,'SPACELOG 5 BP'!$F$6:$EE$6)+SUMIF('SPACELOG 6 BP'!$F$2:$EE$2,CK$4,'SPACELOG 6 BP'!$F$6:$EE$6)+SUMIF('SPACELOG 7 BP'!$F$2:$EE$2,CK$4,'SPACELOG 7 BP'!$F$6:$EE$6)+SUMIF('SPACELOG 8 BP'!$F$2:$EE$2,CK$4,'SPACELOG 8 BP'!$F$6:$EE$6)+SUMIF('SPACELOG 9 BP'!$F$2:$EE$2,CK$4,'SPACELOG 9 BP'!$F$6:$EE$6)+SUMIF('SPACELOG 10 BP'!$F$2:$EE$2,CK$4,'SPACELOG 10 BP'!$F$6:$EE$6)+SUMIF('SPACELOG 11 BP'!$F$2:$EE$2,CK$4,'SPACELOG 11 BP'!$F$6:$EE$6)+SUMIF('SPACELOG 12 BP'!$F$2:$EE$2,CK$4,'SPACELOG 12 BP'!$F$6:$EE$6) -> 128185 | CL6: =SUMIF('reporting montigny'!$F$2:$EE$2,CL$4,'reporting montigny'!$F$6:$EE$6)+SUMIF('reporting boissy'!$F$2:$EE$2,CL$4,'reporting boissy'!$F$6:$EE$6)+SUMIF('reporting moussy'!$F$2:$EE$2,CL$4,'reporting moussy'!$F$6:$EE$6)+SUMIF('reporting trappes'!$F$2:$EE$2,CL$4,'reporting trappes'!$F$6:$EE$6)+SUMIF('SPACELOG 5 BP'!$F$2:$EE$2,CL$4,'SPACELOG 5 BP'!$F$6:$EE$6)+SUMIF('SPACELOG 6 BP'!$F$2:$EE$2,CL$4,'SPACELOG 6 BP'!$F$6:$EE$6)+SUMIF('SPACELOG 7 BP'!$F$2:$EE$2,CL$4,'SPACELOG 7 BP'!$F$6:$EE$6)+SUMIF('SPACELOG 8 BP'!$F$2:$EE$2,CL$4,'SPACELOG 8 BP'!$F$6:$EE$6)+SUMIF('SPACELOG 9 BP'!$F$2:$EE$2,CL$4,'SPACELOG 9 BP'!$F$6:$EE$6)+SUMIF('SPACELOG 10 BP'!$F$2:$EE$2,CL$4,'SPACELOG 10 BP'!$F$6:$EE$6)+SUMIF('SPACELOG 11 BP'!$F$2:$EE$2,CL$4,'SPACELOG 11 BP'!$F$6:$EE$6)+SUMIF('SPACELOG 12 BP'!$F$2:$EE$2,CL$4,'SPACELOG 12 BP'!$F$6:$EE$6) -> 128185 | CM6: =SUMIF('reporting montigny'!$F$2:$EE$2,CM$4,'reporting montigny'!$F$6:$EE$6)+SUMIF('reporting boissy'!$F$2:$EE$2,CM$4,'reporting boissy'!$F$6:$EE$6)+SUMIF('reporting moussy'!$F$2:$EE$2,CM$4,'reporting moussy'!$F$6:$EE$6)+SUMIF('reporting trappes'!$F$2:$EE$2,CM$4,'reporting trappes'!$F$6:$EE$6)+SUMIF('SPACELOG 5 BP'!$F$2:$EE$2,CM$4,'SPACELOG 5 BP'!$F$6:$EE$6)+SUMIF('SPACELOG 6 BP'!$F$2:$EE$2,CM$4,'SPACELOG 6 BP'!$F$6:$EE$6)+SUMIF('SPACELOG 7 BP'!$F$2:$EE$2,CM$4,'SPACELOG 7 BP'!$F$6:$EE$6)+SUMIF('SPACELOG 8 BP'!$F$2:$EE$2,CM$4,'SPACELOG 8 BP'!$F$6:$EE$6)+SUMIF('SPACELOG 9 BP'!$F$2:$EE$2,CM$4,'SPACELOG 9 BP'!$F$6:$EE$6)+SUMIF('SPACELOG 10 BP'!$F$2:$EE$2,CM$4,'SPACELOG 10 BP'!$F$6:$EE$6)+SUMIF('SPACELOG 11 BP'!$F$2:$EE$2,CM$4,'SPACELOG 11 BP'!$F$6:$EE$6)+SUMIF('SPACELOG 12 BP'!$F$2:$EE$2,CM$4,'SPACELOG 12 BP'!$F$6:$EE$6) -> 128185 | ... CQ6: =SUMIF('reporting montigny'!$F$2:$EE$2,CQ$4,'reporting montigny'!$F$6:$EE$6)+SUMIF('reporting boissy'!$F$2:$EE$2,CQ$4,'reporting boissy'!$F$6:$EE$6)+SUMIF('reporting moussy'!$F$2:$EE$2,CQ$4,'reporting moussy'!$F$6:$EE$6)+SUMIF('reporting trappes'!$F$2:$EE$2,CQ$4,'reporting trappes'!$F$6:$EE$6)+SUMIF('SPACELOG 5 BP'!$F$2:$EE$2,CQ$4,'SPACELOG 5 BP'!$F$6:$EE$6)+SUMIF('SPACELOG 6 BP'!$F$2:$EE$2,CQ$4,'SPACELOG 6 BP'!$F$6:$EE$6)+SUMIF('SPACELOG 7 BP'!$F$2:$EE$2,CQ$4,'SPACELOG 7 BP'!$F$6:$EE$6)+SUMIF('SPACELOG 8 BP'!$F$2:$EE$2,CQ$4,'SPACELOG 8 BP'!$F$6:$EE$6)+SUMIF('SPACELOG 9 BP'!$F$2:$EE$2,CQ$4,'SPACELOG 9 BP'!$F$6:$EE$6)+SUMIF('SPACELOG 10 BP'!$F$2:$EE$2,CQ$4,'SPACELOG 10 BP'!$F$6:$EE$6)+SUMIF('SPACELOG 11 BP'!$F$2:$EE$2,CQ$4,'SPACELOG 11 BP'!$F$6:$EE$6)+SUMIF('SPACELOG 12 BP'!$F$2:$EE$2,CQ$4,'SPACELOG 12 BP'!$F$6:$EE$6) -> 128185 | CR6: =SUM(CF6:CQ6) -> 1538220 | CS6: =SUMIF('reporting montigny'!$F$2:$EE$2,CS$4,'reporting montigny'!$F$6:$EE$6)+SUMIF('reporting boissy'!$F$2:$EE$2,CS$4,'reporting boissy'!$F$6:$EE$6)+SUMIF('reporting moussy'!$F$2:$EE$2,CS$4,'reporting moussy'!$F$6:$EE$6)+SUMIF('reporting trappes'!$F$2:$EE$2,CS$4,'reporting trappes'!$F$6:$EE$6)+SUMIF('SPACELOG 5 BP'!$F$2:$EE$2,CS$4,'SPACELOG 5 BP'!$F$6:$EE$6)+SUMIF('SPACELOG 6 BP'!$F$2:$EE$2,CS$4,'SPACELOG 6 BP'!$F$6:$EE$6)+SUMIF('SPACELOG 7 BP'!$F$2:$EE$2,CS$4,'SPACELOG 7 BP'!$F$6:$EE$6)+SUMIF('SPACELOG 8 BP'!$F$2:$EE$2,CS$4,'SPACELOG 8 BP'!$F$6:$EE$6)+SUMIF('SPACELOG 9 BP'!$F$2:$EE$2,CS$4,'SPACELOG 9 BP'!$F$6:$EE$6)+SUMIF('SPACELOG 10 BP'!$F$2:$EE$2,CS$4,'SPACELOG 10 BP'!$F$6:$EE$6)+SUMIF('SPACELOG 11 BP'!$F$2:$EE$2,CS$4,'SPACELOG 11 BP'!$F$6:$EE$6)+SUMIF('SPACELOG 12 BP'!$F$2:$EE$2,CS$4,'SPACELOG 12 BP'!$F$6:$EE$6) -> 128185 | CT6: =SUMIF('reporting montigny'!$F$2:$EE$2,CT$4,'reporting montigny'!$F$6:$EE$6)+SUMIF('reporting boissy'!$F$2:$EE$2,CT$4,'reporting boissy'!$F$6:$EE$6)+SUMIF('reporting moussy'!$F$2:$EE$2,CT$4,'reporting moussy'!$F$6:$EE$6)+SUMIF('reporting trappes'!$F$2:$EE$2,CT$4,'reporting trappes'!$F$6:$EE$6)+SUMIF('SPACELOG 5 BP'!$F$2:$EE$2,CT$4,'SPACELOG 5 BP'!$F$6:$EE$6)+SUMIF('SPACELOG 6 BP'!$F$2:$EE$2,CT$4,'SPACELOG 6 BP'!$F$6:$EE$6)+SUMIF('SPACELOG 7 BP'!$F$2:$EE$2,CT$4,'SPACELOG 7 BP'!$F$6:$EE$6)+SUMIF('SPACELOG 8 BP'!$F$2:$EE$2,CT$4,'SPACELOG 8 BP'!$F$6:$EE$6)+SUMIF('SPACELOG 9 BP'!$F$2:$EE$2,CT$4,'SPACELOG 9 BP'!$F$6:$EE$6)+SUMIF('SPACELOG 10 BP'!$F$2:$EE$2,CT$4,'SPACELOG 10 BP'!$F$6:$EE$6)+SUMIF('SPACELOG 11 BP'!$F$2:$EE$2,CT$4,'SPACELOG 11 BP'!$F$6:$EE$6)+SUMIF('SPACELOG 12 BP'!$F$2:$EE$2,CT$4,'SPACELOG 12 BP'!$F$6:$EE$6) -> 128185 | CU6: =SUMIF('reporting montigny'!$F$2:$EE$2,CU$4,'reporting montigny'!$F$6:$EE$6)+SUMIF('reporting boissy'!$F$2:$EE$2,CU$4,'reporting boissy'!$F$6:$EE$6)+SUMIF('reporting moussy'!$F$2:$EE$2,CU$4,'reporting moussy'!$F$6:$EE$6)+SUMIF('reporting trappes'!$F$2:$EE$2,CU$4,'reporting trappes'!$F$6:$EE$6)+SUMIF('SPACELOG 5 BP'!$F$2:$EE$2,CU$4,'SPACELOG 5 BP'!$F$6:$EE$6)+SUMIF('SPACELOG 6 BP'!$F$2:$EE$2,CU$4,'SPACELOG 6 BP'!$F$6:$EE$6)+SUMIF('SPACELOG 7 BP'!$F$2:$EE$2,CU$4,'SPACELOG 7 BP'!$F$6:$EE$6)+SUMIF('SPACELOG 8 BP'!$F$2:$EE$2,CU$4,'SPACELOG 8 BP'!$F$6:$EE$6)+SUMIF('SPACELOG 9 BP'!$F$2:$EE$2,CU$4,'SPACELOG 9 BP'!$F$6:$EE$6)+SUMIF('SPACELOG 10 BP'!$F$2:$EE$2,CU$4,'SPACELOG 10 BP'!$F$6:$EE$6)+SUMIF('SPACELOG 11 BP'!$F$2:$EE$2,CU$4,'SPACELOG 11 BP'!$F$6:$EE$6)+SUMIF('SPACELOG 12 BP'!$F$2:$EE$2,CU$4,'SPACELOG 12 BP'!$F$6:$EE$6) -> 128185 | CV6: =SUMIF('reporting montigny'!$F$2:$EE$2,CV$4,'reporting montigny'!$F$6:$EE$6)+SUMIF('reporting boissy'!$F$2:$EE$2,CV$4,'reporting boissy'!$F$6:$EE$6)+SUMIF('reporting moussy'!$F$2:$EE$2,CV$4,'reporting moussy'!$F$6:$EE$6)+SUMIF('reporting trappes'!$F$2:$EE$2,CV$4,'reporting trappes'!$F$6:$EE$6)+SUMIF('SPACELOG 5 BP'!$F$2:$EE$2,CV$4,'SPACELOG 5 BP'!$F$6:$EE$6)+SUMIF('SPACELOG 6 BP'!$F$2:$EE$2,CV$4,'SPACELOG 6 BP'!$F$6:$EE$6)+SUMIF('SPACELOG 7 BP'!$F$2:$EE$2,CV$4,'SPACELOG 7 BP'!$F$6:$EE$6)+SUMIF('SPACELOG 8 BP'!$F$2:$EE$2,CV$4,'SPACELOG 8 BP'!$F$6:$EE$6)+SUMIF('SPACELOG 9 BP'!$F$2:$EE$2,CV$4,'SPACELOG 9 BP'!$F$6:$EE$6)+SUMIF('SPACELOG 10 BP'!$F$2:$EE$2,CV$4,'SPACELOG 10 BP'!$F$6:$EE$6)+SUMIF('SPACELOG 11 BP'!$F$2:$EE$2,CV$4,'SPACELOG 11 BP'!$F$6:$EE$6)+SUMIF('SPACELOG 12 BP'!$F$2:$EE$2,CV$4,'SPACELOG 12 BP'!$F$6:$EE$6) -> 128185 | CW6: =SUMIF('reporting montigny'!$F$2:$EE$2,CW$4,'reporting montigny'!$F$6:$EE$6)+SUMIF('reporting boissy'!$F$2:$EE$2,CW$4,'reporting boissy'!$F$6:$EE$6)+SUMIF('reporting moussy'!$F$2:$EE$2,CW$4,'reporting moussy'!$F$6:$EE$6)+SUMIF('reporting trappes'!$F$2:$EE$2,CW$4,'reporting trappes'!$F$6:$EE$6)+SUMIF('SPACELOG 5 BP'!$F$2:$EE$2,CW$4,'SPACELOG 5 BP'!$F$6:$EE$6)+SUMIF('SPACELOG 6 BP'!$F$2:$EE$2,CW$4,'SPACELOG 6 BP'!$F$6:$EE$6)+SUMIF('SPACELOG 7 BP'!$F$2:$EE$2,CW$4,'SPACELOG 7 BP'!$F$6:$EE$6)+SUMIF('SPACELOG 8 BP'!$F$2:$EE$2,CW$4,'SPACELOG 8 BP'!$F$6:$EE$6)+SUMIF('SPACELOG 9 BP'!$F$2:$EE$2,CW$4,'SPACELOG 9 BP'!$F$6:$EE$6)+SUMIF('SPACELOG 10 BP'!$F$2:$EE$2,CW$4,'SPACELOG 10 BP'!$F$6:$EE$6)+SUMIF('SPACELOG 11 BP'!$F$2:$EE$2,CW$4,'SPACELOG 11 BP'!$F$6:$EE$6)+SUMIF('SPACELOG 12 BP'!$F$2:$EE$2,CW$4,'SPACELOG 12 BP'!$F$6:$EE$6) -> 128185 | CX6: =SUMIF('reporting montigny'!$F$2:$EE$2,CX$4,'reporting montigny'!$F$6:$EE$6)+SUMIF('reporting boissy'!$F$2:$EE$2,CX$4,'reporting boissy'!$F$6:$EE$6)+SUMIF('reporting moussy'!$F$2:$EE$2,CX$4,'reporting moussy'!$F$6:$EE$6)+SUMIF('reporting trappes'!$F$2:$EE$2,CX$4,'reporting trappes'!$F$6:$EE$6)+SUMIF('SPACELOG 5 BP'!$F$2:$EE$2,CX$4,'SPACELOG 5 BP'!$F$6:$EE$6)+SUMIF('SPACELOG 6 BP'!$F$2:$EE$2,CX$4,'SPACELOG 6 BP'!$F$6:$EE$6)+SUMIF('SPACELOG 7 BP'!$F$2:$EE$2,CX$4,'SPACELOG 7 BP'!$F$6:$EE$6)+SUMIF('SPACELOG 8 BP'!$F$2:$EE$2,CX$4,'SPACELOG 8 BP'!$F$6:$EE$6)+SUMIF('SPACELOG 9 BP'!$F$2:$EE$2,CX$4,'SPACELOG 9 BP'!$F$6:$EE$6)+SUMIF('SPACELOG 10 BP'!$F$2:$EE$2,CX$4,'SPACELOG 10 BP'!$F$6:$EE$6)+SUMIF('SPACELOG 11 BP'!$F$2:$EE$2,CX$4,'SPACELOG 11 BP'!$F$6:$EE$6)+SUMIF('SPACELOG 12 BP'!$F$2:$EE$2,CX$4,'SPACELOG 12 BP'!$F$6:$EE$6) -> 128185 | CY6: =SUMIF('reporting montigny'!$F$2:$EE$2,CY$4,'reporting montigny'!$F$6:$EE$6)+SUMIF('reporting boissy'!$F$2:$EE$2,CY$4,'reporting boissy'!$F$6:$EE$6)+SUMIF('reporting moussy'!$F$2:$EE$2,CY$4,'reporting moussy'!$F$6:$EE$6)+SUMIF('reporting trappes'!$F$2:$EE$2,CY$4,'reporting trappes'!$F$6:$EE$6)+SUMIF('SPACELOG 5 BP'!$F$2:$EE$2,CY$4,'SPACELOG 5 BP'!$F$6:$EE$6)+SUMIF('SPACELOG 6 BP'!$F$2:$EE$2,CY$4,'SPACELOG 6 BP'!$F$6:$EE$6)+SUMIF('SPACELOG 7 BP'!$F$2:$EE$2,CY$4,'SPACELOG 7 BP'!$F$6:$EE$6)+SUMIF('SPACELOG 8 BP'!$F$2:$EE$2,CY$4,'SPACELOG 8 BP'!$F$6:$EE$6)+SUMIF('SPACELOG 9 BP'!$F$2:$EE$2,CY$4,'SPACELOG 9 BP'!$F$6:$EE$6)+SUMIF('SPACELOG 10 BP'!$F$2:$EE$2,CY$4,'SPACELOG 10 BP'!$F$6:$EE$6)+SUMIF('SPACELOG 11 BP'!$F$2:$EE$2,CY$4,'SPACELOG 11 BP'!$F$6:$EE$6)+SUMIF('SPACELOG 12 BP'!$F$2:$EE$2,CY$4,'SPACELOG 12 BP'!$F$6:$EE$6) -> 128185 | CZ6: =SUMIF('reporting montigny'!$F$2:$EE$2,CZ$4,'reporting montigny'!$F$6:$EE$6)+SUMIF('reporting boissy'!$F$2:$EE$2,CZ$4,'reporting boissy'!$F$6:$EE$6)+SUMIF('reporting moussy'!$F$2:$EE$2,CZ$4,'reporting moussy'!$F$6:$EE$6)+SUMIF('reporting trappes'!$F$2:$EE$2,CZ$4,'reporting trappes'!$F$6:$EE$6)+SUMIF('SPACELOG 5 BP'!$F$2:$EE$2,CZ$4,'SPACELOG 5 BP'!$F$6:$EE$6)+SUMIF('SPACELOG 6 BP'!$F$2:$EE$2,CZ$4,'SPACELOG 6 BP'!$F$6:$EE$6)+SUMIF('SPACELOG 7 BP'!$F$2:$EE$2,CZ$4,'SPACELOG 7 BP'!$F$6:$EE$6)+SUMIF('SPACELOG 8 BP'!$F$2:$EE$2,CZ$4,'SPACELOG 8 BP'!$F$6:$EE$6)+SUMIF('SPACELOG 9 BP'!$F$2:$EE$2,CZ$4,'SPACELOG 9 BP'!$F$6:$EE$6)+SUMIF('SPACELOG 10 BP'!$F$2:$EE$2,CZ$4,'SPACELOG 10 BP'!$F$6:$EE$6)+SUMIF('SPACELOG 11 BP'!$F$2:$EE$2,CZ$4,'SPACELOG 11 BP'!$F$6:$EE$6)+SUMIF('SPACELOG 12 BP'!$F$2:$EE$2,CZ$4,'SPACELOG 12 BP'!$F$6:$EE$6) -> 128185 | ... DD6: =SUMIF('reporting montigny'!$F$2:$EE$2,DD$4,'reporting montigny'!$F$6:$EE$6)+SUMIF('reporting boissy'!$F$2:$EE$2,DD$4,'reporting boissy'!$F$6:$EE$6)+SUMIF('reporting moussy'!$F$2:$EE$2,DD$4,'reporting moussy'!$F$6:$EE$6)+SUMIF('reporting trappes'!$F$2:$EE$2,DD$4,'reporting trappes'!$F$6:$EE$6)+SUMIF('SPACELOG 5 BP'!$F$2:$EE$2,DD$4,'SPACELOG 5 BP'!$F$6:$EE$6)+SUMIF('SPACELOG 6 BP'!$F$2:$EE$2,DD$4,'SPACELOG 6 BP'!$F$6:$EE$6)+SUMIF('SPACELOG 7 BP'!$F$2:$EE$2,DD$4,'SPACELOG 7 BP'!$F$6:$EE$6)+SUMIF('SPACELOG 8 BP'!$F$2:$EE$2,DD$4,'SPACELOG 8 BP'!$F$6:$EE$6)+SUMIF('SPACELOG 9 BP'!$F$2:$EE$2,DD$4,'SPACELOG 9 BP'!$F$6:$EE$6)+SUMIF('SPACELOG 10 BP'!$F$2:$EE$2,DD$4,'SPACELOG 10 BP'!$F$6:$EE$6)+SUMIF('SPACELOG 11 BP'!$F$2:$EE$2,DD$4,'SPACELOG 11 BP'!$F$6:$EE$6)+SUMIF('SPACELOG 12 BP'!$F$2:$EE$2,DD$4,'SPACELOG 12 BP'!$F$6:$EE$6) -> 128185 | DE6: =SUM(CS6:DD6) -> 1538220 | DF6: =SUMIF('reporting montigny'!$F$2:$EE$2,DF$4,'reporting montigny'!$F$6:$EE$6)+SUMIF('reporting boissy'!$F$2:$EE$2,DF$4,'reporting boissy'!$F$6:$EE$6)+SUMIF('reporting moussy'!$F$2:$EE$2,DF$4,'reporting moussy'!$F$6:$EE$6)+SUMIF('reporting trappes'!$F$2:$EE$2,DF$4,'reporting trappes'!$F$6:$EE$6)+SUMIF('SPACELOG 5 BP'!$F$2:$EE$2,DF$4,'SPACELOG 5 BP'!$F$6:$EE$6)+SUMIF('SPACELOG 6 BP'!$F$2:$EE$2,DF$4,'SPACELOG 6 BP'!$F$6:$EE$6)+SUMIF('SPACELOG 7 BP'!$F$2:$EE$2,DF$4,'SPACELOG 7 BP'!$F$6:$EE$6)+SUMIF('SPACELOG 8 BP'!$F$2:$EE$2,DF$4,'SPACELOG 8 BP'!$F$6:$EE$6)+SUMIF('SPACELOG 9 BP'!$F$2:$EE$2,DF$4,'SPACELOG 9 BP'!$F$6:$EE$6)+SUMIF('SPACELOG 10 BP'!$F$2:$EE$2,DF$4,'SPACELOG 10 BP'!$F$6:$EE$6)+SUMIF('SPACELOG 11 BP'!$F$2:$EE$2,DF$4,'SPACELOG 11 BP'!$F$6:$EE$6)+SUMIF('SPACELOG 12 BP'!$F$2:$EE$2,DF$4,'SPACELOG 12 BP'!$F$6:$EE$6) -> 128185 | DG6: =SUMIF('reporting montigny'!$F$2:$EE$2,DG$4,'reporting montigny'!$F$6:$EE$6)+SUMIF('reporting boissy'!$F$2:$EE$2,DG$4,'reporting boissy'!$F$6:$EE$6)+SUMIF('reporting moussy'!$F$2:$EE$2,DG$4,'reporting moussy'!$F$6:$EE$6)+SUMIF('reporting trappes'!$F$2:$EE$2,DG$4,'reporting trappes'!$F$6:$EE$6)+SUMIF('SPACELOG 5 BP'!$F$2:$EE$2,DG$4,'SPACELOG 5 BP'!$F$6:$EE$6)+SUMIF('SPACELOG 6 BP'!$F$2:$EE$2,DG$4,'SPACELOG 6 BP'!$F$6:$EE$6)+SUMIF('SPACELOG 7 BP'!$F$2:$EE$2,DG$4,'SPACELOG 7 BP'!$F$6:$EE$6)+SUMIF('SPACELOG 8 BP'!$F$2:$EE$2,DG$4,'SPACELOG 8 BP'!$F$6:$EE$6)+SUMIF('SPACELOG 9 BP'!$F$2:$EE$2,DG$4,'SPACELOG 9 BP'!$F$6:$EE$6)+SUMIF('SPACELOG 10 BP'!$F$2:$EE$2,DG$4,'SPACELOG 10 BP'!$F$6:$EE$6)+SUMIF('SPACELOG 11 BP'!$F$2:$EE$2,DG$4,'SPACELOG 11 BP'!$F$6:$EE$6)+SUMIF('SPACELOG 12 BP'!$F$2:$EE$2,DG$4,'SPACELOG 12 BP'!$F$6:$EE$6) -> 128185 | DH6: =SUMIF('reporting montigny'!$F$2:$EE$2,DH$4,'reporting montigny'!$F$6:$EE$6)+SUMIF('reporting boissy'!$F$2:$EE$2,DH$4,'reporting boissy'!$F$6:$EE$6)+SUMIF('reporting moussy'!$F$2:$EE$2,DH$4,'reporting moussy'!$F$6:$EE$6)+SUMIF('reporting trappes'!$F$2:$EE$2,DH$4,'reporting trappes'!$F$6:$EE$6)+SUMIF('SPACELOG 5 BP'!$F$2:$EE$2,DH$4,'SPACELOG 5 BP'!$F$6:$EE$6)+SUMIF('SPACELOG 6 BP'!$F$2:$EE$2,DH$4,'SPACELOG 6 BP'!$F$6:$EE$6)+SUMIF('SPACELOG 7 BP'!$F$2:$EE$2,DH$4,'SPACELOG 7 BP'!$F$6:$EE$6)+SUMIF('SPACELOG 8 BP'!$F$2:$EE$2,DH$4,'SPACELOG 8 BP'!$F$6:$EE$6)+SUMIF('SPACELOG 9 BP'!$F$2:$EE$2,DH$4,'SPACELOG 9 BP'!$F$6:$EE$6)+SUMIF('SPACELOG 10 BP'!$F$2:$EE$2,DH$4,'SPACELOG 10 BP'!$F$6:$EE$6)+SUMIF('SPACELOG 11 BP'!$F$2:$EE$2,DH$4,'SPACELOG 11 BP'!$F$6:$EE$6)+SUMIF('SPACELOG 12 BP'!$F$2:$EE$2,DH$4,'SPACELOG 12 BP'!$F$6:$EE$6) -> 128185 | DI6: =SUMIF('reporting montigny'!$F$2:$EE$2,DI$4,'reporting montigny'!$F$6:$EE$6)+SUMIF('reporting boissy'!$F$2:$EE$2,DI$4,'reporting boissy'!$F$6:$EE$6)+SUMIF('reporting moussy'!$F$2:$EE$2,DI$4,'reporting moussy'!$F$6:$EE$6)+SUMIF('reporting trappes'!$F$2:$EE$2,DI$4,'reporting trappes'!$F$6:$EE$6)+SUMIF('SPACELOG 5 BP'!$F$2:$EE$2,DI$4,'SPACELOG 5 BP'!$F$6:$EE$6)+SUMIF('SPACELOG 6 BP'!$F$2:$EE$2,DI$4,'SPACELOG 6 BP'!$F$6:$EE$6)+SUMIF('SPACELOG 7 BP'!$F$2:$EE$2,DI$4,'SPACELOG 7 BP'!$F$6:$EE$6)+SUMIF('SPACELOG 8 BP'!$F$2:$EE$2,DI$4,'SPACELOG 8 BP'!$F$6:$EE$6)+SUMIF('SPACELOG 9 BP'!$F$2:$EE$2,DI$4,'SPACELOG 9 BP'!$F$6:$EE$6)+SUMIF('SPACELOG 10 BP'!$F$2:$EE$2,DI$4,'SPACELOG 10 BP'!$F$6:$EE$6)+SUMIF('SPACELOG 11 BP'!$F$2:$EE$2,DI$4,'SPACELOG 11 BP'!$F$6:$EE$6)+SUMIF('SPACELOG 12 BP'!$F$2:$EE$2,DI$4,'SPACELOG 12 BP'!$F$6:$EE$6) -> 128185 | DJ6: =SUMIF('reporting montigny'!$F$2:$EE$2,DJ$4,'reporting montigny'!$F$6:$EE$6)+SUMIF('reporting boissy'!$F$2:$EE$2,DJ$4,'reporting boissy'!$F$6:$EE$6)+SUMIF('reporting moussy'!$F$2:$EE$2,DJ$4,'reporting moussy'!$F$6:$EE$6)+SUMIF('reporting trappes'!$F$2:$EE$2,DJ$4,'reporting trappes'!$F$6:$EE$6)+SUMIF('SPACELOG 5 BP'!$F$2:$EE$2,DJ$4,'SPACELOG 5 BP'!$F$6:$EE$6)+SUMIF('SPACELOG 6 BP'!$F$2:$EE$2,DJ$4,'SPACELOG 6 BP'!$F$6:$EE$6)+SUMIF('SPACELOG 7 BP'!$F$2:$EE$2,DJ$4,'SPACELOG 7 BP'!$F$6:$EE$6)+SUMIF('SPACELOG 8 BP'!$F$2:$EE$2,DJ$4,'SPACELOG 8 BP'!$F$6:$EE$6)+SUMIF('SPACELOG 9 BP'!$F$2:$EE$2,DJ$4,'SPACELOG 9 BP'!$F$6:$EE$6)+SUMIF('SPACELOG 10 BP'!$F$2:$EE$2,DJ$4,'SPACELOG 10 BP'!$F$6:$EE$6)+SUMIF('SPACELOG 11 BP'!$F$2:$EE$2,DJ$4,'SPACELOG 11 BP'!$F$6:$EE$6)+SUMIF('SPACELOG 12 BP'!$F$2:$EE$2,DJ$4,'SPACELOG 12 BP'!$F$6:$EE$6) -> 128185 | DK6: =SUMIF('reporting montigny'!$F$2:$EE$2,DK$4,'reporting montigny'!$F$6:$EE$6)+SUMIF('reporting boissy'!$F$2:$EE$2,DK$4,'reporting boissy'!$F$6:$EE$6)+SUMIF('reporting moussy'!$F$2:$EE$2,DK$4,'reporting moussy'!$F$6:$EE$6)+SUMIF('reporting trappes'!$F$2:$EE$2,DK$4,'reporting trappes'!$F$6:$EE$6)+SUMIF('SPACELOG 5 BP'!$F$2:$EE$2,DK$4,'SPACELOG 5 BP'!$F$6:$EE$6)+SUMIF('SPACELOG 6 BP'!$F$2:$EE$2,DK$4,'SPACELOG 6 BP'!$F$6:$EE$6)+SUMIF('SPACELOG 7 BP'!$F$2:$EE$2,DK$4,'SPACELOG 7 BP'!$F$6:$EE$6)+SUMIF('SPACELOG 8 BP'!$F$2:$EE$2,DK$4,'SPACELOG 8 BP'!$F$6:$EE$6)+SUMIF('SPACELOG 9 BP'!$F$2:$EE$2,DK$4,'SPACELOG 9 BP'!$F$6:$EE$6)+SUMIF('SPACELOG 10 BP'!$F$2:$EE$2,DK$4,'SPACELOG 10 BP'!$F$6:$EE$6)+SUMIF('SPACELOG 11 BP'!$F$2:$EE$2,DK$4,'SPACELOG 11 BP'!$F$6:$EE$6)+SUMIF('SPACELOG 12 BP'!$F$2:$EE$2,DK$4,'SPACELOG 12 BP'!$F$6:$EE$6) -> 128185 | DL6: =SUMIF('reporting montigny'!$F$2:$EE$2,DL$4,'reporting montigny'!$F$6:$EE$6)+SUMIF('reporting boissy'!$F$2:$EE$2,DL$4,'reporting boissy'!$F$6:$EE$6)+SUMIF('reporting moussy'!$F$2:$EE$2,DL$4,'reporting moussy'!$F$6:$EE$6)+SUMIF('reporting trappes'!$F$2:$EE$2,DL$4,'reporting trappes'!$F$6:$EE$6)+SUMIF('SPACELOG 5 BP'!$F$2:$EE$2,DL$4,'SPACELOG 5 BP'!$F$6:$EE$6)+SUMIF('SPACELOG 6 BP'!$F$2:$EE$2,DL$4,'SPACELOG 6 BP'!$F$6:$EE$6)+SUMIF('SPACELOG 7 BP'!$F$2:$EE$2,DL$4,'SPACELOG 7 BP'!$F$6:$EE$6)+SUMIF('SPACELOG 8 BP'!$F$2:$EE$2,DL$4,'SPACELOG 8 BP'!$F$6:$EE$6)+SUMIF('SPACELOG 9 BP'!$F$2:$EE$2,DL$4,'SPACELOG 9 BP'!$F$6:$EE$6)+SUMIF('SPACELOG 10 BP'!$F$2:$EE$2,DL$4,'SPACELOG 10 BP'!$F$6:$EE$6)+SUMIF('SPACELOG 11 BP'!$F$2:$EE$2,DL$4,'SPACELOG 11 BP'!$F$6:$EE$6)+SUMIF('SPACELOG 12 BP'!$F$2:$EE$2,DL$4,'SPACELOG 12 BP'!$F$6:$EE$6) -> 128185 | DM6: =SUMIF('reporting montigny'!$F$2:$EE$2,DM$4,'reporting montigny'!$F$6:$EE$6)+SUMIF('reporting boissy'!$F$2:$EE$2,DM$4,'reporting boissy'!$F$6:$EE$6)+SUMIF('reporting moussy'!$F$2:$EE$2,DM$4,'reporting moussy'!$F$6:$EE$6)+SUMIF('reporting trappes'!$F$2:$EE$2,DM$4,'reporting trappes'!$F$6:$EE$6)+SUMIF('SPACELOG 5 BP'!$F$2:$EE$2,DM$4,'SPACELOG 5 BP'!$F$6:$EE$6)+SUMIF('SPACELOG 6 BP'!$F$2:$EE$2,DM$4,'SPACELOG 6 BP'!$F$6:$EE$6)+SUMIF('SPACELOG 7 BP'!$F$2:$EE$2,DM$4,'SPACELOG 7 BP'!$F$6:$EE$6)+SUMIF('SPACELOG 8 BP'!$F$2:$EE$2,DM$4,'SPACELOG 8 BP'!$F$6:$EE$6)+SUMIF('SPACELOG 9 BP'!$F$2:$EE$2,DM$4,'SPACELOG 9 BP'!$F$6:$EE$6)+SUMIF('SPACELOG 10 BP'!$F$2:$EE$2,DM$4,'SPACELOG 10 BP'!$F$6:$EE$6)+SUMIF('SPACELOG 11 BP'!$F$2:$EE$2,DM$4,'SPACELOG 11 BP'!$F$6:$EE$6)+SUMIF('SPACELOG 12 BP'!$F$2:$EE$2,DM$4,'SPACELOG 12 BP'!$F$6:$EE$6) -> 128185 | ... DQ6: =SUMIF('reporting montigny'!$F$2:$EE$2,DQ$4,'reporting montigny'!$F$6:$EE$6)+SUMIF('reporting boissy'!$F$2:$EE$2,DQ$4,'reporting boissy'!$F$6:$EE$6)+SUMIF('reporting moussy'!$F$2:$EE$2,DQ$4,'reporting moussy'!$F$6:$EE$6)+SUMIF('reporting trappes'!$F$2:$EE$2,DQ$4,'reporting trappes'!$F$6:$EE$6)+SUMIF('SPACELOG 5 BP'!$F$2:$EE$2,DQ$4,'SPACELOG 5 BP'!$F$6:$EE$6)+SUMIF('SPACELOG 6 BP'!$F$2:$EE$2,DQ$4,'SPACELOG 6 BP'!$F$6:$EE$6)+SUMIF('SPACELOG 7 BP'!$F$2:$EE$2,DQ$4,'SPACELOG 7 BP'!$F$6:$EE$6)+SUMIF('SPACELOG 8 BP'!$F$2:$EE$2,DQ$4,'SPACELOG 8 BP'!$F$6:$EE$6)+SUMIF('SPACELOG 9 BP'!$F$2:$EE$2,DQ$4,'SPACELOG 9 BP'!$F$6:$EE$6)+SUMIF('SPACELOG 10 BP'!$F$2:$EE$2,DQ$4,'SPACELOG 10 BP'!$F$6:$EE$6)+SUMIF('SPACELOG 11 BP'!$F$2:$EE$2,DQ$4,'SPACELOG 11 BP'!$F$6:$EE$6)+SUMIF('SPACELOG 12 BP'!$F$2:$EE$2,DQ$4,'SPACELOG 12 BP'!$F$6:$EE$6) -> 128185 | DR6: =SUM(DF6:DQ6) -> 1538220
E7: Loyer | F7: =SUMIF('reporting montigny'!$F$2:$EE$2,F$4,'reporting montigny'!$F$7:$EE$7)+SUMIF('reporting boissy'!$F$2:$EE$2,F$4,'reporting boissy'!$F$7:$EE$7)+SUMIF('reporting moussy'!$F$2:$EE$2,F$4,'reporting moussy'!$F$7:$EE$7)+SUMIF('reporting trappes'!$F$2:$EE$2,F$4,'reporting trappes'!$F$7:$EE$7)+SUMIF('SPACELOG 5 BP'!$F$2:$EE$2,F$4,'SPACELOG 5 BP'!$F$7:$EE$7)+SUMIF('SPACELOG 6 BP'!$F$2:$EE$2,F$4,'SPACELOG 6 BP'!$F$7:$EE$7)+SUMIF('SPACELOG 7 BP'!$F$2:$EE$2,F$4,'SPACELOG 7 BP'!$F$7:$EE$7)+SUMIF('SPACELOG 8 BP'!$F$2:$EE$2,F$4,'SPACELOG 8 BP'!$F$7:$EE$7)+SUMIF('SPACELOG 9 BP'!$F$2:$EE$2,F$4,'SPACELOG 9 BP'!$F$7:$EE$7)+SUMIF('SPACELOG 10 BP'!$F$2:$EE$2,F$4,'SPACELOG 10 BP'!$F$7:$EE$7)+SUMIF('SPACELOG 11 BP'!$F$2:$EE$2,F$4,'SPACELOG 11 BP'!$F$7:$EE$7)+SUMIF('SPACELOG 12 BP'!$F$2:$EE$2,F$4,'SPACELOG 12 BP'!$F$7:$EE$7) -> 66142 | G7: =SUMIF('reporting montigny'!$F$2:$EE$2,G$4,'reporting montigny'!$F$7:$EE$7)+SUMIF('reporting boissy'!$F$2:$EE$2,G$4,'reporting boissy'!$F$7:$EE$7)+SUMIF('reporting moussy'!$F$2:$EE$2,G$4,'reporting moussy'!$F$7:$EE$7)+SUMIF('reporting trappes'!$F$2:$EE$2,G$4,'reporting trappes'!$F$7:$EE$7)+SUMIF('SPACELOG 5 BP'!$F$2:$EE$2,G$4,'SPACELOG 5 BP'!$F$7:$EE$7)+SUMIF('SPACELOG 6 BP'!$F$2:$EE$2,G$4,'SPACELOG 6 BP'!$F$7:$EE$7)+SUMIF('SPACELOG 7 BP'!$F$2:$EE$2,G$4,'SPACELOG 7 BP'!$F$7:$EE$7)+SUMIF('SPACELOG 8 BP'!$F$2:$EE$2,G$4,'SPACELOG 8 BP'!$F$7:$EE$7)+SUMIF('SPACELOG 9 BP'!$F$2:$EE$2,G$4,'SPACELOG 9 BP'!$F$7:$EE$7)+SUMIF('SPACELOG 10 BP'!$F$2:$EE$2,G$4,'SPACELOG 10 BP'!$F$7:$EE$7)+SUMIF('SPACELOG 11 BP'!$F$2:$EE$2,G$4,'SPACELOG 11 BP'!$F$7:$EE$7)+SUMIF('SPACELOG 12 BP'!$F$2:$EE$2,G$4,'SPACELOG 12 BP'!$F$7:$EE$7) -> 67910 | H7: =SUMIF('reporting montigny'!$F$2:$EE$2,H$4,'reporting montigny'!$F$7:$EE$7)+SUMIF('reporting boissy'!$F$2:$EE$2,H$4,'reporting boissy'!$F$7:$EE$7)+SUMIF('reporting moussy'!$F$2:$EE$2,H$4,'reporting moussy'!$F$7:$EE$7)+SUMIF('reporting trappes'!$F$2:$EE$2,H$4,'reporting trappes'!$F$7:$EE$7)+SUMIF('SPACELOG 5 BP'!$F$2:$EE$2,H$4,'SPACELOG 5 BP'!$F$7:$EE$7)+SUMIF('SPACELOG 6 BP'!$F$2:$EE$2,H$4,'SPACELOG 6 BP'!$F$7:$EE$7)+SUMIF('SPACELOG 7 BP'!$F$2:$EE$2,H$4,'SPACELOG 7 BP'!$F$7:$EE$7)+SUMIF('SPACELOG 8 BP'!$F$2:$EE$2,H$4,'SPACELOG 8 BP'!$F$7:$EE$7)+SUMIF('SPACELOG 9 BP'!$F$2:$EE$2,H$4,'SPACELOG 9 BP'!$F$7:$EE$7)+SUMIF('SPACELOG 10 BP'!$F$2:$EE$2,H$4,'SPACELOG 10 BP'!$F$7:$EE$7)+SUMIF('SPACELOG 11 BP'!$F$2:$EE$2,H$4,'SPACELOG 11 BP'!$F$7:$EE$7)+SUMIF('SPACELOG 12 BP'!$F$2:$EE$2,H$4,'SPACELOG 12 BP'!$F$7:$EE$7) -> 69810 | I7: =SUMIF('reporting montigny'!$F$2:$EE$2,I$4,'reporting montigny'!$F$7:$EE$7)+SUMIF('reporting boissy'!$F$2:$EE$2,I$4,'reporting boissy'!$F$7:$EE$7)+SUMIF('reporting moussy'!$F$2:$EE$2,I$4,'reporting moussy'!$F$7:$EE$7)+SUMIF('reporting trappes'!$F$2:$EE$2,I$4,'reporting trappes'!$F$7:$EE$7)+SUMIF('SPACELOG 5 BP'!$F$2:$EE$2,I$4,'SPACELOG 5 BP'!$F$7:$EE$7)+SUMIF('SPACELOG 6 BP'!$F$2:$EE$2,I$4,'SPACELOG 6 BP'!$F$7:$EE$7)+SUMIF('SPACELOG 7 BP'!$F$2:$EE$2,I$4,'SPACELOG 7 BP'!$F$7:$EE$7)+SUMIF('SPACELOG 8 BP'!$F$2:$EE$2,I$4,'SPACELOG 8 BP'!$F$7:$EE$7)+SUMIF('SPACELOG 9 BP'!$F$2:$EE$2,I$4,'SPACELOG 9 BP'!$F$7:$EE$7)+SUMIF('SPACELOG 10 BP'!$F$2:$EE$2,I$4,'SPACELOG 10 BP'!$F$7:$EE$7)+SUMIF('SPACELOG 11 BP'!$F$2:$EE$2,I$4,'SPACELOG 11 BP'!$F$7:$EE$7)+SUMIF('SPACELOG 12 BP'!$F$2:$EE$2,I$4,'SPACELOG 12 BP'!$F$7:$EE$7) -> 76242 | J7: =SUMIF('reporting montigny'!$F$2:$EE$2,J$4,'reporting montigny'!$F$7:$EE$7)+SUMIF('reporting boissy'!$F$2:$EE$2,J$4,'reporting boissy'!$F$7:$EE$7)+SUMIF('reporting moussy'!$F$2:$EE$2,J$4,'reporting moussy'!$F$7:$EE$7)+SUMIF('reporting trappes'!$F$2:$EE$2,J$4,'reporting trappes'!$F$7:$EE$7)+SUMIF('SPACELOG 5 BP'!$F$2:$EE$2,J$4,'SPACELOG 5 BP'!$F$7:$EE$7)+SUMIF('SPACELOG 6 BP'!$F$2:$EE$2,J$4,'SPACELOG 6 BP'!$F$7:$EE$7)+SUMIF('SPACELOG 7 BP'!$F$2:$EE$2,J$4,'SPACELOG 7 BP'!$F$7:$EE$7)+SUMIF('SPACELOG 8 BP'!$F$2:$EE$2,J$4,'SPACELOG 8 BP'!$F$7:$EE$7)+SUMIF('SPACELOG 9 BP'!$F$2:$EE$2,J$4,'SPACELOG 9 BP'!$F$7:$EE$7)+SUMIF('SPACELOG 10 BP'!$F$2:$EE$2,J$4,'SPACELOG 10 BP'!$F$7:$EE$7)+SUMIF('SPACELOG 11 BP'!$F$2:$EE$2,J$4,'SPACELOG 11 BP'!$F$7:$EE$7)+SUMIF('SPACELOG 12 BP'!$F$2:$EE$2,J$4,'SPACELOG 12 BP'!$F$7:$EE$7) -> 77910 | K7: =SUMIF('reporting montigny'!$F$2:$EE$2,K$4,'reporting montigny'!$F$7:$EE$7)+SUMIF('reporting boissy'!$F$2:$EE$2,K$4,'reporting boissy'!$F$7:$EE$7)+SUMIF('reporting moussy'!$F$2:$EE$2,K$4,'reporting moussy'!$F$7:$EE$7)+SUMIF('reporting trappes'!$F$2:$EE$2,K$4,'reporting trappes'!$F$7:$EE$7)+SUMIF('SPACELOG 5 BP'!$F$2:$EE$2,K$4,'SPACELOG 5 BP'!$F$7:$EE$7)+SUMIF('SPACELOG 6 BP'!$F$2:$EE$2,K$4,'SPACELOG 6 BP'!$F$7:$EE$7)+SUMIF('SPACELOG 7 BP'!$F$2:$EE$2,K$4,'SPACELOG 7 BP'!$F$7:$EE$7)+SUMIF('SPACELOG 8 BP'!$F$2:$EE$2,K$4,'SPACELOG 8 BP'!$F$7:$EE$7)+SUMIF('SPACELOG 9 BP'!$F$2:$EE$2,K$4,'SPACELOG 9 BP'!$F$7:$EE$7)+SUMIF('SPACELOG 10 BP'!$F$2:$EE$2,K$4,'SPACELOG 10 BP'!$F$7:$EE$7)+SUMIF('SPACELOG 11 BP'!$F$2:$EE$2,K$4,'SPACELOG 11 BP'!$F$7:$EE$7)+SUMIF('SPACELOG 12 BP'!$F$2:$EE$2,K$4,'SPACELOG 12 BP'!$F$7:$EE$7) -> 78310 | L7: =SUMIF('reporting montigny'!$F$2:$EE$2,L$4,'reporting montigny'!$F$7:$EE$7)+SUMIF('reporting boissy'!$F$2:$EE$2,L$4,'reporting boissy'!$F$7:$EE$7)+SUMIF('reporting moussy'!$F$2:$EE$2,L$4,'reporting moussy'!$F$7:$EE$7)+SUMIF('reporting trappes'!$F$2:$EE$2,L$4,'reporting trappes'!$F$7:$EE$7)+SUMIF('SPACELOG 5 BP'!$F$2:$EE$2,L$4,'SPACELOG 5 BP'!$F$7:$EE$7)+SUMIF('SPACELOG 6 BP'!$F$2:$EE$2,L$4,'SPACELOG 6 BP'!$F$7:$EE$7)+SUMIF('SPACELOG 7 BP'!$F$2:$EE$2,L$4,'SPACELOG 7 BP'!$F$7:$EE$7)+SUMIF('SPACELOG 8 BP'!$F$2:$EE$2,L$4,'SPACELOG 8 BP'!$F$7:$EE$7)+SUMIF('SPACELOG 9 BP'!$F$2:$EE$2,L$4,'SPACELOG 9 BP'!$F$7:$EE$7)+SUMIF('SPACELOG 10 BP'!$F$2:$EE$2,L$4,'SPACELOG 10 BP'!$F$7:$EE$7)+SUMIF('SPACELOG 11 BP'!$F$2:$EE$2,L$4,'SPACELOG 11 BP'!$F$7:$EE$7)+SUMIF('SPACELOG 12 BP'!$F$2:$EE$2,L$4,'SPACELOG 12 BP'!$F$7:$EE$7) -> 76610 | M7: =SUMIF('reporting montigny'!$F$2:$EE$2,M$4,'reporting montigny'!$F$7:$EE$7)+SUMIF('reporting boissy'!$F$2:$EE$2,M$4,'reporting boissy'!$F$7:$EE$7)+SUMIF('reporting moussy'!$F$2:$EE$2,M$4,'reporting moussy'!$F$7:$EE$7)+SUMIF('reporting trappes'!$F$2:$EE$2,M$4,'reporting trappes'!$F$7:$EE$7)+SUMIF('SPACELOG 5 BP'!$F$2:$EE$2,M$4,'SPACELOG 5 BP'!$F$7:$EE$7)+SUMIF('SPACELOG 6 BP'!$F$2:$EE$2,M$4,'SPACELOG 6 BP'!$F$7:$EE$7)+SUMIF('SPACELOG 7 BP'!$F$2:$EE$2,M$4,'SPACELOG 7 BP'!$F$7:$EE$7)+SUMIF('SPACELOG 8 BP'!$F$2:$EE$2,M$4,'SPACELOG 8 BP'!$F$7:$EE$7)+SUMIF('SPACELOG 9 BP'!$F$2:$EE$2,M$4,'SPACELOG 9 BP'!$F$7:$EE$7)+SUMIF('SPACELOG 10 BP'!$F$2:$EE$2,M$4,'SPACELOG 10 BP'!$F$7:$EE$7)+SUMIF('SPACELOG 11 BP'!$F$2:$EE$2,M$4,'SPACELOG 11 BP'!$F$7:$EE$7)+SUMIF('SPACELOG 12 BP'!$F$2:$EE$2,M$4,'SPACELOG 12 BP'!$F$7:$EE$7) -> 76610 | ... Q7: =SUMIF('reporting montigny'!$F$2:$EE$2,Q$4,'reporting montigny'!$F$7:$EE$7)+SUMIF('reporting boissy'!$F$2:$EE$2,Q$4,'reporting boissy'!$F$7:$EE$7)+SUMIF('reporting moussy'!$F$2:$EE$2,Q$4,'reporting moussy'!$F$7:$EE$7)+SUMIF('reporting trappes'!$F$2:$EE$2,Q$4,'reporting trappes'!$F$7:$EE$7)+SUMIF('SPACELOG 5 BP'!$F$2:$EE$2,Q$4,'SPACELOG 5 BP'!$F$7:$EE$7)+SUMIF('SPACELOG 6 BP'!$F$2:$EE$2,Q$4,'SPACELOG 6 BP'!$F$7:$EE$7)+SUMIF('SPACELOG 7 BP'!$F$2:$EE$2,Q$4,'SPACELOG 7 BP'!$F$7:$EE$7)+SUMIF('SPACELOG 8 BP'!$F$2:$EE$2,Q$4,'SPACELOG 8 BP'!$F$7:$EE$7)+SUMIF('SPACELOG 9 BP'!$F$2:$EE$2,Q$4,'SPACELOG 9 BP'!$F$7:$EE$7)+SUMIF('SPACELOG 10 BP'!$F$2:$EE$2,Q$4,'SPACELOG 10 BP'!$F$7:$EE$7)+SUMIF('SPACELOG 11 BP'!$F$2:$EE$2,Q$4,'SPACELOG 11 BP'!$F$7:$EE$7)+SUMIF('SPACELOG 12 BP'!$F$2:$EE$2,Q$4,'SPACELOG 12 BP'!$F$7:$EE$7) -> 88960 | R7: =SUM(F7:Q7) -> 918184 | S7: =SUMIF('reporting montigny'!$F$2:$EE$2,S$4,'reporting montigny'!$F$7:$EE$7)+SUMIF('reporting boissy'!$F$2:$EE$2,S$4,'reporting boissy'!$F$7:$EE$7)+SUMIF('reporting moussy'!$F$2:$EE$2,S$4,'reporting moussy'!$F$7:$EE$7)+SUMIF('reporting trappes'!$F$2:$EE$2,S$4,'reporting trappes'!$F$7:$EE$7)+SUMIF('SPACELOG 5 BP'!$F$2:$EE$2,S$4,'SPACELOG 5 BP'!$F$7:$EE$7)+SUMIF('SPACELOG 6 BP'!$F$2:$EE$2,S$4,'SPACELOG 6 BP'!$F$7:$EE$7)+SUMIF('SPACELOG 7 BP'!$F$2:$EE$2,S$4,'SPACELOG 7 BP'!$F$7:$EE$7)+SUMIF('SPACELOG 8 BP'!$F$2:$EE$2,S$4,'SPACELOG 8 BP'!$F$7:$EE$7)+SUMIF('SPACELOG 9 BP'!$F$2:$EE$2,S$4,'SPACELOG 9 BP'!$F$7:$EE$7)+SUMIF('SPACELOG 10 BP'!$F$2:$EE$2,S$4,'SPACELOG 10 BP'!$F$7:$EE$7)+SUMIF('SPACELOG 11 BP'!$F$2:$EE$2,S$4,'SPACELOG 11 BP'!$F$7:$EE$7)+SUMIF('SPACELOG 12 BP'!$F$2:$EE$2,S$4,'SPACELOG 12 BP'!$F$7:$EE$7) -> 84560 | T7: =SUMIF('reporting montigny'!$F$2:$EE$2,T$4,'reporting montigny'!$F$7:$EE$7)+SUMIF('reporting boissy'!$F$2:$EE$2,T$4,'reporting boissy'!$F$7:$EE$7)+SUMIF('reporting moussy'!$F$2:$EE$2,T$4,'reporting moussy'!$F$7:$EE$7)+SUMIF('reporting trappes'!$F$2:$EE$2,T$4,'reporting trappes'!$F$7:$EE$7)+SUMIF('SPACELOG 5 BP'!$F$2:$EE$2,T$4,'SPACELOG 5 BP'!$F$7:$EE$7)+SUMIF('SPACELOG 6 BP'!$F$2:$EE$2,T$4,'SPACELOG 6 BP'!$F$7:$EE$7)+SUMIF('SPACELOG 7 BP'!$F$2:$EE$2,T$4,'SPACELOG 7 BP'!$F$7:$EE$7)+SUMIF('SPACELOG 8 BP'!$F$2:$EE$2,T$4,'SPACELOG 8 BP'!$F$7:$EE$7)+SUMIF('SPACELOG 9 BP'!$F$2:$EE$2,T$4,'SPACELOG 9 BP'!$F$7:$EE$7)+SUMIF('SPACELOG 10 BP'!$F$2:$EE$2,T$4,'SPACELOG 10 BP'!$F$7:$EE$7)+SUMIF('SPACELOG 11 BP'!$F$2:$EE$2,T$4,'SPACELOG 11 BP'!$F$7:$EE$7)+SUMIF('SPACELOG 12 BP'!$F$2:$EE$2,T$4,'SPACELOG 12 BP'!$F$7:$EE$7) -> 86185 | U7: =SUMIF('reporting montigny'!$F$2:$EE$2,U$4,'reporting montigny'!$F$7:$EE$7)+SUMIF('reporting boissy'!$F$2:$EE$2,U$4,'reporting boissy'!$F$7:$EE$7)+SUMIF('reporting moussy'!$F$2:$EE$2,U$4,'reporting moussy'!$F$7:$EE$7)+SUMIF('reporting trappes'!$F$2:$EE$2,U$4,'reporting trappes'!$F$7:$EE$7)+SUMIF('SPACELOG 5 BP'!$F$2:$EE$2,U$4,'SPACELOG 5 BP'!$F$7:$EE$7)+SUMIF('SPACELOG 6 BP'!$F$2:$EE$2,U$4,'SPACELOG 6 BP'!$F$7:$EE$7)+SUMIF('SPACELOG 7 BP'!$F$2:$EE$2,U$4,'SPACELOG 7 BP'!$F$7:$EE$7)+SUMIF('SPACELOG 8 BP'!$F$2:$EE$2,U$4,'SPACELOG 8 BP'!$F$7:$EE$7)+SUMIF('SPACELOG 9 BP'!$F$2:$EE$2,U$4,'SPACELOG 9 BP'!$F$7:$EE$7)+SUMIF('SPACELOG 10 BP'!$F$2:$EE$2,U$4,'SPACELOG 10 BP'!$F$7:$EE$7)+SUMIF('SPACELOG 11 BP'!$F$2:$EE$2,U$4,'SPACELOG 11 BP'!$F$7:$EE$7)+SUMIF('SPACELOG 12 BP'!$F$2:$EE$2,U$4,'SPACELOG 12 BP'!$F$7:$EE$7) -> 89185 | V7: =SUMIF('reporting montigny'!$F$2:$EE$2,V$4,'reporting montigny'!$F$7:$EE$7)+SUMIF('reporting boissy'!$F$2:$EE$2,V$4,'reporting boissy'!$F$7:$EE$7)+SUMIF('reporting moussy'!$F$2:$EE$2,V$4,'reporting moussy'!$F$7:$EE$7)+SUMIF('reporting trappes'!$F$2:$EE$2,V$4,'reporting trappes'!$F$7:$EE$7)+SUMIF('SPACELOG 5 BP'!$F$2:$EE$2,V$4,'SPACELOG 5 BP'!$F$7:$EE$7)+SUMIF('SPACELOG 6 BP'!$F$2:$EE$2,V$4,'SPACELOG 6 BP'!$F$7:$EE$7)+SUMIF('SPACELOG 7 BP'!$F$2:$EE$2,V$4,'SPACELOG 7 BP'!$F$7:$EE$7)+SUMIF('SPACELOG 8 BP'!$F$2:$EE$2,V$4,'SPACELOG 8 BP'!$F$7:$EE$7)+SUMIF('SPACELOG 9 BP'!$F$2:$EE$2,V$4,'SPACELOG 9 BP'!$F$7:$EE$7)+SUMIF('SPACELOG 10 BP'!$F$2:$EE$2,V$4,'SPACELOG 10 BP'!$F$7:$EE$7)+SUMIF('SPACELOG 11 BP'!$F$2:$EE$2,V$4,'SPACELOG 11 BP'!$F$7:$EE$7)+SUMIF('SPACELOG 12 BP'!$F$2:$EE$2,V$4,'SPACELOG 12 BP'!$F$7:$EE$7) -> 83735 | W7: =SUMIF('reporting montigny'!$F$2:$EE$2,W$4,'reporting montigny'!$F$7:$EE$7)+SUMIF('reporting boissy'!$F$2:$EE$2,W$4,'reporting boissy'!$F$7:$EE$7)+SUMIF('reporting moussy'!$F$2:$EE$2,W$4,'reporting moussy'!$F$7:$EE$7)+SUMIF('reporting trappes'!$F$2:$EE$2,W$4,'reporting trappes'!$F$7:$EE$7)+SUMIF('SPACELOG 5 BP'!$F$2:$EE$2,W$4,'SPACELOG 5 BP'!$F$7:$EE$7)+SUMIF('SPACELOG 6 BP'!$F$2:$EE$2,W$4,'SPACELOG 6 BP'!$F$7:$EE$7)+SUMIF('SPACELOG 7 BP'!$F$2:$EE$2,W$4,'SPACELOG 7 BP'!$F$7:$EE$7)+SUMIF('SPACELOG 8 BP'!$F$2:$EE$2,W$4,'SPACELOG 8 BP'!$F$7:$EE$7)+SUMIF('SPACELOG 9 BP'!$F$2:$EE$2,W$4,'SPACELOG 9 BP'!$F$7:$EE$7)+SUMIF('SPACELOG 10 BP'!$F$2:$EE$2,W$4,'SPACELOG 10 BP'!$F$7:$EE$7)+SUMIF('SPACELOG 11 BP'!$F$2:$EE$2,W$4,'SPACELOG 11 BP'!$F$7:$EE$7)+SUMIF('SPACELOG 12 BP'!$F$2:$EE$2,W$4,'SPACELOG 12 BP'!$F$7:$EE$7) -> 94035 | X7: =SUMIF('reporting montigny'!$F$2:$EE$2,X$4,'reporting montigny'!$F$7:$EE$7)+SUMIF('reporting boissy'!$F$2:$EE$2,X$4,'reporting boissy'!$F$7:$EE$7)+SUMIF('reporting moussy'!$F$2:$EE$2,X$4,'reporting moussy'!$F$7:$EE$7)+SUMIF('reporting trappes'!$F$2:$EE$2,X$4,'reporting trappes'!$F$7:$EE$7)+SUMIF('SPACELOG 5 BP'!$F$2:$EE$2,X$4,'SPACELOG 5 BP'!$F$7:$EE$7)+SUMIF('SPACELOG 6 BP'!$F$2:$EE$2,X$4,'SPACELOG 6 BP'!$F$7:$EE$7)+SUMIF('SPACELOG 7 BP'!$F$2:$EE$2,X$4,'SPACELOG 7 BP'!$F$7:$EE$7)+SUMIF('SPACELOG 8 BP'!$F$2:$EE$2,X$4,'SPACELOG 8 BP'!$F$7:$EE$7)+SUMIF('SPACELOG 9 BP'!$F$2:$EE$2,X$4,'SPACELOG 9 BP'!$F$7:$EE$7)+SUMIF('SPACELOG 10 BP'!$F$2:$EE$2,X$4,'SPACELOG 10 BP'!$F$7:$EE$7)+SUMIF('SPACELOG 11 BP'!$F$2:$EE$2,X$4,'SPACELOG 11 BP'!$F$7:$EE$7)+SUMIF('SPACELOG 12 BP'!$F$2:$EE$2,X$4,'SPACELOG 12 BP'!$F$7:$EE$7) -> 93185 | Y7: =SUMIF('reporting montigny'!$F$2:$EE$2,Y$4,'reporting montigny'!$F$7:$EE$7)+SUMIF('reporting boissy'!$F$2:$EE$2,Y$4,'reporting boissy'!$F$7:$EE$7)+SUMIF('reporting moussy'!$F$2:$EE$2,Y$4,'reporting moussy'!$F$7:$EE$7)+SUMIF('reporting trappes'!$F$2:$EE$2,Y$4,'reporting trappes'!$F$7:$EE$7)+SUMIF('SPACELOG 5 BP'!$F$2:$EE$2,Y$4,'SPACELOG 5 BP'!$F$7:$EE$7)+SUMIF('SPACELOG 6 BP'!$F$2:$EE$2,Y$4,'SPACELOG 6 BP'!$F$7:$EE$7)+SUMIF('SPACELOG 7 BP'!$F$2:$EE$2,Y$4,'SPACELOG 7 BP'!$F$7:$EE$7)+SUMIF('SPACELOG 8 BP'!$F$2:$EE$2,Y$4,'SPACELOG 8 BP'!$F$7:$EE$7)+SUMIF('SPACELOG 9 BP'!$F$2:$EE$2,Y$4,'SPACELOG 9 BP'!$F$7:$EE$7)+SUMIF('SPACELOG 10 BP'!$F$2:$EE$2,Y$4,'SPACELOG 10 BP'!$F$7:$EE$7)+SUMIF('SPACELOG 11 BP'!$F$2:$EE$2,Y$4,'SPACELOG 11 BP'!$F$7:$EE$7)+SUMIF('SPACELOG 12 BP'!$F$2:$EE$2,Y$4,'SPACELOG 12 BP'!$F$7:$EE$7) -> 101635 | Z7: =SUMIF('reporting montigny'!$F$2:$EE$2,Z$4,'reporting montigny'!$F$7:$EE$7)+SUMIF('reporting boissy'!$F$2:$EE$2,Z$4,'reporting boissy'!$F$7:$EE$7)+SUMIF('reporting moussy'!$F$2:$EE$2,Z$4,'reporting moussy'!$F$7:$EE$7)+SUMIF('reporting trappes'!$F$2:$EE$2,Z$4,'reporting trappes'!$F$7:$EE$7)+SUMIF('SPACELOG 5 BP'!$F$2:$EE$2,Z$4,'SPACELOG 5 BP'!$F$7:$EE$7)+SUMIF('SPACELOG 6 BP'!$F$2:$EE$2,Z$4,'SPACELOG 6 BP'!$F$7:$EE$7)+SUMIF('SPACELOG 7 BP'!$F$2:$EE$2,Z$4,'SPACELOG 7 BP'!$F$7:$EE$7)+SUMIF('SPACELOG 8 BP'!$F$2:$EE$2,Z$4,'SPACELOG 8 BP'!$F$7:$EE$7)+SUMIF('SPACELOG 9 BP'!$F$2:$EE$2,Z$4,'SPACELOG 9 BP'!$F$7:$EE$7)+SUMIF('SPACELOG 10 BP'!$F$2:$EE$2,Z$4,'SPACELOG 10 BP'!$F$7:$EE$7)+SUMIF('SPACELOG 11 BP'!$F$2:$EE$2,Z$4,'SPACELOG 11 BP'!$F$7:$EE$7)+SUMIF('SPACELOG 12 BP'!$F$2:$EE$2,Z$4,'SPACELOG 12 BP'!$F$7:$EE$7) -> 104185 | ... AD7: =SUMIF('reporting montigny'!$F$2:$EE$2,AD$4,'reporting montigny'!$F$7:$EE$7)+SUMIF('reporting boissy'!$F$2:$EE$2,AD$4,'reporting boissy'!$F$7:$EE$7)+SUMIF('reporting moussy'!$F$2:$EE$2,AD$4,'reporting moussy'!$F$7:$EE$7)+SUMIF('reporting trappes'!$F$2:$EE$2,AD$4,'reporting trappes'!$F$7:$EE$7)+SUMIF('SPACELOG 5 BP'!$F$2:$EE$2,AD$4,'SPACELOG 5 BP'!$F$7:$EE$7)+SUMIF('SPACELOG 6 BP'!$F$2:$EE$2,AD$4,'SPACELOG 6 BP'!$F$7:$EE$7)+SUMIF('SPACELOG 7 BP'!$F$2:$EE$2,AD$4,'SPACELOG 7 BP'!$F$7:$EE$7)+SUMIF('SPACELOG 8 BP'!$F$2:$EE$2,AD$4,'SPACELOG 8 BP'!$F$7:$EE$7)+SUMIF('SPACELOG 9 BP'!$F$2:$EE$2,AD$4,'SPACELOG 9 BP'!$F$7:$EE$7)+SUMIF('SPACELOG 10 BP'!$F$2:$EE$2,AD$4,'SPACELOG 10 BP'!$F$7:$EE$7)+SUMIF('SPACELOG 11 BP'!$F$2:$EE$2,AD$4,'SPACELOG 11 BP'!$F$7:$EE$7)+SUMIF('SPACELOG 12 BP'!$F$2:$EE$2,AD$4,'SPACELOG 12 BP'!$F$7:$EE$7) -> 114385 | AE7: =SUM(S7:AD7) -> 1178945 | AF7: =SUMIF('reporting montigny'!$F$2:$EE$2,AF$4,'reporting montigny'!$F$7:$EE$7)+SUMIF('reporting boissy'!$F$2:$EE$2,AF$4,'reporting boissy'!$F$7:$EE$7)+SUMIF('reporting moussy'!$F$2:$EE$2,AF$4,'reporting moussy'!$F$7:$EE$7)+SUMIF('reporting trappes'!$F$2:$EE$2,AF$4,'reporting trappes'!$F$7:$EE$7)+SUMIF('SPACELOG 5 BP'!$F$2:$EE$2,AF$4,'SPACELOG 5 BP'!$F$7:$EE$7)+SUMIF('SPACELOG 6 BP'!$F$2:$EE$2,AF$4,'SPACELOG 6 BP'!$F$7:$EE$7)+SUMIF('SPACELOG 7 BP'!$F$2:$EE$2,AF$4,'SPACELOG 7 BP'!$F$7:$EE$7)+SUMIF('SPACELOG 8 BP'!$F$2:$EE$2,AF$4,'SPACELOG 8 BP'!$F$7:$EE$7)+SUMIF('SPACELOG 9 BP'!$F$2:$EE$2,AF$4,'SPACELOG 9 BP'!$F$7:$EE$7)+SUMIF('SPACELOG 10 BP'!$F$2:$EE$2,AF$4,'SPACELOG 10 BP'!$F$7:$EE$7)+SUMIF('SPACELOG 11 BP'!$F$2:$EE$2,AF$4,'SPACELOG 11 BP'!$F$7:$EE$7)+SUMIF('SPACELOG 12 BP'!$F$2:$EE$2,AF$4,'SPACELOG 12 BP'!$F$7:$EE$7) -> 116935 | AG7: =SUMIF('reporting montigny'!$F$2:$EE$2,AG$4,'reporting montigny'!$F$7:$EE$7)+SUMIF('reporting boissy'!$F$2:$EE$2,AG$4,'reporting boissy'!$F$7:$EE$7)+SUMIF('reporting moussy'!$F$2:$EE$2,AG$4,'reporting moussy'!$F$7:$EE$7)+SUMIF('reporting trappes'!$F$2:$EE$2,AG$4,'reporting trappes'!$F$7:$EE$7)+SUMIF('SPACELOG 5 BP'!$F$2:$EE$2,AG$4,'SPACELOG 5 BP'!$F$7:$EE$7)+SUMIF('SPACELOG 6 BP'!$F$2:$EE$2,AG$4,'SPACELOG 6 BP'!$F$7:$EE$7)+SUMIF('SPACELOG 7 BP'!$F$2:$EE$2,AG$4,'SPACELOG 7 BP'!$F$7:$EE$7)+SUMIF('SPACELOG 8 BP'!$F$2:$EE$2,AG$4,'SPACELOG 8 BP'!$F$7:$EE$7)+SUMIF('SPACELOG 9 BP'!$F$2:$EE$2,AG$4,'SPACELOG 9 BP'!$F$7:$EE$7)+SUMIF('SPACELOG 10 BP'!$F$2:$EE$2,AG$4,'SPACELOG 10 BP'!$F$7:$EE$7)+SUMIF('SPACELOG 11 BP'!$F$2:$EE$2,AG$4,'SPACELOG 11 BP'!$F$7:$EE$7)+SUMIF('SPACELOG 12 BP'!$F$2:$EE$2,AG$4,'SPACELOG 12 BP'!$F$7:$EE$7) -> 119485 | AH7: =SUMIF('reporting montigny'!$F$2:$EE$2,AH$4,'reporting montigny'!$F$7:$EE$7)+SUMIF('reporting boissy'!$F$2:$EE$2,AH$4,'reporting boissy'!$F$7:$EE$7)+SUMIF('reporting moussy'!$F$2:$EE$2,AH$4,'reporting moussy'!$F$7:$EE$7)+SUMIF('reporting trappes'!$F$2:$EE$2,AH$4,'reporting trappes'!$F$7:$EE$7)+SUMIF('SPACELOG 5 BP'!$F$2:$EE$2,AH$4,'SPACELOG 5 BP'!$F$7:$EE$7)+SUMIF('SPACELOG 6 BP'!$F$2:$EE$2,AH$4,'SPACELOG 6 BP'!$F$7:$EE$7)+SUMIF('SPACELOG 7 BP'!$F$2:$EE$2,AH$4,'SPACELOG 7 BP'!$F$7:$EE$7)+SUMIF('SPACELOG 8 BP'!$F$2:$EE$2,AH$4,'SPACELOG 8 BP'!$F$7:$EE$7)+SUMIF('SPACELOG 9 BP'!$F$2:$EE$2,AH$4,'SPACELOG 9 BP'!$F$7:$EE$7)+SUMIF('SPACELOG 10 BP'!$F$2:$EE$2,AH$4,'SPACELOG 10 BP'!$F$7:$EE$7)+SUMIF('SPACELOG 11 BP'!$F$2:$EE$2,AH$4,'SPACELOG 11 BP'!$F$7:$EE$7)+SUMIF('SPACELOG 12 BP'!$F$2:$EE$2,AH$4,'SPACELOG 12 BP'!$F$7:$EE$7) -> 122035 | AI7: =SUMIF('reporting montigny'!$F$2:$EE$2,AI$4,'reporting montigny'!$F$7:$EE$7)+SUMIF('reporting boissy'!$F$2:$EE$2,AI$4,'reporting boissy'!$F$7:$EE$7)+SUMIF('reporting moussy'!$F$2:$EE$2,AI$4,'reporting moussy'!$F$7:$EE$7)+SUMIF('reporting trappes'!$F$2:$EE$2,AI$4,'reporting trappes'!$F$7:$EE$7)+SUMIF('SPACELOG 5 BP'!$F$2:$EE$2,AI$4,'SPACELOG 5 BP'!$F$7:$EE$7)+SUMIF('SPACELOG 6 BP'!$F$2:$EE$2,AI$4,'SPACELOG 6 BP'!$F$7:$EE$7)+SUMIF('SPACELOG 7 BP'!$F$2:$EE$2,AI$4,'SPACELOG 7 BP'!$F$7:$EE$7)+SUMIF('SPACELOG 8 BP'!$F$2:$EE$2,AI$4,'SPACELOG 8 BP'!$F$7:$EE$7)+SUMIF('SPACELOG 9 BP'!$F$2:$EE$2,AI$4,'SPACELOG 9 BP'!$F$7:$EE$7)+SUMIF('SPACELOG 10 BP'!$F$2:$EE$2,AI$4,'SPACELOG 10 BP'!$F$7:$EE$7)+SUMIF('SPACELOG 11 BP'!$F$2:$EE$2,AI$4,'SPACELOG 11 BP'!$F$7:$EE$7)+SUMIF('SPACELOG 12 BP'!$F$2:$EE$2,AI$4,'SPACELOG 12 BP'!$F$7:$EE$7) -> 124585 | AJ7: =SUMIF('reporting montigny'!$F$2:$EE$2,AJ$4,'reporting montigny'!$F$7:$EE$7)+SUMIF('reporting boissy'!$F$2:$EE$2,AJ$4,'reporting boissy'!$F$7:$EE$7)+SUMIF('reporting moussy'!$F$2:$EE$2,AJ$4,'reporting moussy'!$F$7:$EE$7)+SUMIF('reporting trappes'!$F$2:$EE$2,AJ$4,'reporting trappes'!$F$7:$EE$7)+SUMIF('SPACELOG 5 BP'!$F$2:$EE$2,AJ$4,'SPACELOG 5 BP'!$F$7:$EE$7)+SUMIF('SPACELOG 6 BP'!$F$2:$EE$2,AJ$4,'SPACELOG 6 BP'!$F$7:$EE$7)+SUMIF('SPACELOG 7 BP'!$F$2:$EE$2,AJ$4,'SPACELOG 7 BP'!$F$7:$EE$7)+SUMIF('SPACELOG 8 BP'!$F$2:$EE$2,AJ$4,'SPACELOG 8 BP'!$F$7:$EE$7)+SUMIF('SPACELOG 9 BP'!$F$2:$EE$2,AJ$4,'SPACELOG 9 BP'!$F$7:$EE$7)+SUMIF('SPACELOG 10 BP'!$F$2:$EE$2,AJ$4,'SPACELOG 10 BP'!$F$7:$EE$7)+SUMIF('SPACELOG 11 BP'!$F$2:$EE$2,AJ$4,'SPACELOG 11 BP'!$F$7:$EE$7)+SUMIF('SPACELOG 12 BP'!$F$2:$EE$2,AJ$4,'SPACELOG 12 BP'!$F$7:$EE$7) -> 126385 | AK7: =SUMIF('reporting montigny'!$F$2:$EE$2,AK$4,'reporting montigny'!$F$7:$EE$7)+SUMIF('reporting boissy'!$F$2:$EE$2,AK$4,'reporting boissy'!$F$7:$EE$7)+SUMIF('reporting moussy'!$F$2:$EE$2,AK$4,'reporting moussy'!$F$7:$EE$7)+SUMIF('reporting trappes'!$F$2:$EE$2,AK$4,'reporting trappes'!$F$7:$EE$7)+SUMIF('SPACELOG 5 BP'!$F$2:$EE$2,AK$4,'SPACELOG 5 BP'!$F$7:$EE$7)+SUMIF('SPACELOG 6 BP'!$F$2:$EE$2,AK$4,'SPACELOG 6 BP'!$F$7:$EE$7)+SUMIF('SPACELOG 7 BP'!$F$2:$EE$2,AK$4,'SPACELOG 7 BP'!$F$7:$EE$7)+SUMIF('SPACELOG 8 BP'!$F$2:$EE$2,AK$4,'SPACELOG 8 BP'!$F$7:$EE$7)+SUMIF('SPACELOG 9 BP'!$F$2:$EE$2,AK$4,'SPACELOG 9 BP'!$F$7:$EE$7)+SUMIF('SPACELOG 10 BP'!$F$2:$EE$2,AK$4,'SPACELOG 10 BP'!$F$7:$EE$7)+SUMIF('SPACELOG 11 BP'!$F$2:$EE$2,AK$4,'SPACELOG 11 BP'!$F$7:$EE$7)+SUMIF('SPACELOG 12 BP'!$F$2:$EE$2,AK$4,'SPACELOG 12 BP'!$F$7:$EE$7) -> 128185 | AL7: =SUMIF('reporting montigny'!$F$2:$EE$2,AL$4,'reporting montigny'!$F$7:$EE$7)+SUMIF('reporting boissy'!$F$2:$EE$2,AL$4,'reporting boissy'!$F$7:$EE$7)+SUMIF('reporting moussy'!$F$2:$EE$2,AL$4,'reporting moussy'!$F$7:$EE$7)+SUMIF('reporting trappes'!$F$2:$EE$2,AL$4,'reporting trappes'!$F$7:$EE$7)+SUMIF('SPACELOG 5 BP'!$F$2:$EE$2,AL$4,'SPACELOG 5 BP'!$F$7:$EE$7)+SUMIF('SPACELOG 6 BP'!$F$2:$EE$2,AL$4,'SPACELOG 6 BP'!$F$7:$EE$7)+SUMIF('SPACELOG 7 BP'!$F$2:$EE$2,AL$4,'SPACELOG 7 BP'!$F$7:$EE$7)+SUMIF('SPACELOG 8 BP'!$F$2:$EE$2,AL$4,'SPACELOG 8 BP'!$F$7:$EE$7)+SUMIF('SPACELOG 9 BP'!$F$2:$EE$2,AL$4,'SPACELOG 9 BP'!$F$7:$EE$7)+SUMIF('SPACELOG 10 BP'!$F$2:$EE$2,AL$4,'SPACELOG 10 BP'!$F$7:$EE$7)+SUMIF('SPACELOG 11 BP'!$F$2:$EE$2,AL$4,'SPACELOG 11 BP'!$F$7:$EE$7)+SUMIF('SPACELOG 12 BP'!$F$2:$EE$2,AL$4,'SPACELOG 12 BP'!$F$7:$EE$7) -> 128185 | AM7: =SUMIF('reporting montigny'!$F$2:$EE$2,AM$4,'reporting montigny'!$F$7:$EE$7)+SUMIF('reporting boissy'!$F$2:$EE$2,AM$4,'reporting boissy'!$F$7:$EE$7)+SUMIF('reporting moussy'!$F$2:$EE$2,AM$4,'reporting moussy'!$F$7:$EE$7)+SUMIF('reporting trappes'!$F$2:$EE$2,AM$4,'reporting trappes'!$F$7:$EE$7)+SUMIF('SPACELOG 5 BP'!$F$2:$EE$2,AM$4,'SPACELOG 5 BP'!$F$7:$EE$7)+SUMIF('SPACELOG 6 BP'!$F$2:$EE$2,AM$4,'SPACELOG 6 BP'!$F$7:$EE$7)+SUMIF('SPACELOG 7 BP'!$F$2:$EE$2,AM$4,'SPACELOG 7 BP'!$F$7:$EE$7)+SUMIF('SPACELOG 8 BP'!$F$2:$EE$2,AM$4,'SPACELOG 8 BP'!$F$7:$EE$7)+SUMIF('SPACELOG 9 BP'!$F$2:$EE$2,AM$4,'SPACELOG 9 BP'!$F$7:$EE$7)+SUMIF('SPACELOG 10 BP'!$F$2:$EE$2,AM$4,'SPACELOG 10 BP'!$F$7:$EE$7)+SUMIF('SPACELOG 11 BP'!$F$2:$EE$2,AM$4,'SPACELOG 11 BP'!$F$7:$EE$7)+SUMIF('SPACELOG 12 BP'!$F$2:$EE$2,AM$4,'SPACELOG 12 BP'!$F$7:$EE$7) -> 128185 | ... AQ7: =SUMIF('reporting montigny'!$F$2:$EE$2,AQ$4,'reporting montigny'!$F$7:$EE$7)+SUMIF('reporting boissy'!$F$2:$EE$2,AQ$4,'reporting boissy'!$F$7:$EE$7)+SUMIF('reporting moussy'!$F$2:$EE$2,AQ$4,'reporting moussy'!$F$7:$EE$7)+SUMIF('reporting trappes'!$F$2:$EE$2,AQ$4,'reporting trappes'!$F$7:$EE$7)+SUMIF('SPACELOG 5 BP'!$F$2:$EE$2,AQ$4,'SPACELOG 5 BP'!$F$7:$EE$7)+SUMIF('SPACELOG 6 BP'!$F$2:$EE$2,AQ$4,'SPACELOG 6 BP'!$F$7:$EE$7)+SUMIF('SPACELOG 7 BP'!$F$2:$EE$2,AQ$4,'SPACELOG 7 BP'!$F$7:$EE$7)+SUMIF('SPACELOG 8 BP'!$F$2:$EE$2,AQ$4,'SPACELOG 8 BP'!$F$7:$EE$7)+SUMIF('SPACELOG 9 BP'!$F$2:$EE$2,AQ$4,'SPACELOG 9 BP'!$F$7:$EE$7)+SUMIF('SPACELOG 10 BP'!$F$2:$EE$2,AQ$4,'SPACELOG 10 BP'!$F$7:$EE$7)+SUMIF('SPACELOG 11 BP'!$F$2:$EE$2,AQ$4,'SPACELOG 11 BP'!$F$7:$EE$7)+SUMIF('SPACELOG 12 BP'!$F$2:$EE$2,AQ$4,'SPACELOG 12 BP'!$F$7:$EE$7) -> 128185 | AR7: =SUM(AF7:AQ7) -> 1506720 | AS7: =SUMIF('reporting montigny'!$F$2:$EE$2,AS$4,'reporting montigny'!$F$7:$EE$7)+SUMIF('reporting boissy'!$F$2:$EE$2,AS$4,'reporting boissy'!$F$7:$EE$7)+SUMIF('reporting moussy'!$F$2:$EE$2,AS$4,'reporting moussy'!$F$7:$EE$7)+SUMIF('reporting trappes'!$F$2:$EE$2,AS$4,'reporting trappes'!$F$7:$EE$7)+SUMIF('SPACELOG 5 BP'!$F$2:$EE$2,AS$4,'SPACELOG 5 BP'!$F$7:$EE$7)+SUMIF('SPACELOG 6 BP'!$F$2:$EE$2,AS$4,'SPACELOG 6 BP'!$F$7:$EE$7)+SUMIF('SPACELOG 7 BP'!$F$2:$EE$2,AS$4,'SPACELOG 7 BP'!$F$7:$EE$7)+SUMIF('SPACELOG 8 BP'!$F$2:$EE$2,AS$4,'SPACELOG 8 BP'!$F$7:$EE$7)+SUMIF('SPACELOG 9 BP'!$F$2:$EE$2,AS$4,'SPACELOG 9 BP'!$F$7:$EE$7)+SUMIF('SPACELOG 10 BP'!$F$2:$EE$2,AS$4,'SPACELOG 10 BP'!$F$7:$EE$7)+SUMIF('SPACELOG 11 BP'!$F$2:$EE$2,AS$4,'SPACELOG 11 BP'!$F$7:$EE$7)+SUMIF('SPACELOG 12 BP'!$F$2:$EE$2,AS$4,'SPACELOG 12 BP'!$F$7:$EE$7) -> 128185 | AT7: =SUMIF('reporting montigny'!$F$2:$EE$2,AT$4,'reporting montigny'!$F$7:$EE$7)+SUMIF('reporting boissy'!$F$2:$EE$2,AT$4,'reporting boissy'!$F$7:$EE$7)+SUMIF('reporting moussy'!$F$2:$EE$2,AT$4,'reporting moussy'!$F$7:$EE$7)+SUMIF('reporting trappes'!$F$2:$EE$2,AT$4,'reporting trappes'!$F$7:$EE$7)+SUMIF('SPACELOG 5 BP'!$F$2:$EE$2,AT$4,'SPACELOG 5 BP'!$F$7:$EE$7)+SUMIF('SPACELOG 6 BP'!$F$2:$EE$2,AT$4,'SPACELOG 6 BP'!$F$7:$EE$7)+SUMIF('SPACELOG 7 BP'!$F$2:$EE$2,AT$4,'SPACELOG 7 BP'!$F$7:$EE$7)+SUMIF('SPACELOG 8 BP'!$F$2:$EE$2,AT$4,'SPACELOG 8 BP'!$F$7:$EE$7)+SUMIF('SPACELOG 9 BP'!$F$2:$EE$2,AT$4,'SPACELOG 9 BP'!$F$7:$EE$7)+SUMIF('SPACELOG 10 BP'!$F$2:$EE$2,AT$4,'SPACELOG 10 BP'!$F$7:$EE$7)+SUMIF('SPACELOG 11 BP'!$F$2:$EE$2,AT$4,'SPACELOG 11 BP'!$F$7:$EE$7)+SUMIF('SPACELOG 12 BP'!$F$2:$EE$2,AT$4,'SPACELOG 12 BP'!$F$7:$EE$7) -> 128185 | AU7: =SUMIF('reporting montigny'!$F$2:$EE$2,AU$4,'reporting montigny'!$F$7:$EE$7)+SUMIF('reporting boissy'!$F$2:$EE$2,AU$4,'reporting boissy'!$F$7:$EE$7)+SUMIF('reporting moussy'!$F$2:$EE$2,AU$4,'reporting moussy'!$F$7:$EE$7)+SUMIF('reporting trappes'!$F$2:$EE$2,AU$4,'reporting trappes'!$F$7:$EE$7)+SUMIF('SPACELOG 5 BP'!$F$2:$EE$2,AU$4,'SPACELOG 5 BP'!$F$7:$EE$7)+SUMIF('SPACELOG 6 BP'!$F$2:$EE$2,AU$4,'SPACELOG 6 BP'!$F$7:$EE$7)+SUMIF('SPACELOG 7 BP'!$F$2:$EE$2,AU$4,'SPACELOG 7 BP'!$F$7:$EE$7)+SUMIF('SPACELOG 8 BP'!$F$2:$EE$2,AU$4,'SPACELOG 8 BP'!$F$7:$EE$7)+SUMIF('SPACELOG 9 BP'!$F$2:$EE$2,AU$4,'SPACELOG 9 BP'!$F$7:$EE$7)+SUMIF('SPACELOG 10 BP'!$F$2:$EE$2,AU$4,'SPACELOG 10 BP'!$F$7:$EE$7)+SUMIF('SPACELOG 11 BP'!$F$2:$EE$2,AU$4,'SPACELOG 11 BP'!$F$7:$EE$7)+SUMIF('SPACELOG 12 BP'!$F$2:$EE$2,AU$4,'SPACELOG 12 BP'!$F$7:$EE$7) -> 128185 | AV7: =SUMIF('reporting montigny'!$F$2:$EE$2,AV$4,'reporting montigny'!$F$7:$EE$7)+SUMIF('reporting boissy'!$F$2:$EE$2,AV$4,'reporting boissy'!$F$7:$EE$7)+SUMIF('reporting moussy'!$F$2:$EE$2,AV$4,'reporting moussy'!$F$7:$EE$7)+SUMIF('reporting trappes'!$F$2:$EE$2,AV$4,'reporting trappes'!$F$7:$EE$7)+SUMIF('SPACELOG 5 BP'!$F$2:$EE$2,AV$4,'SPACELOG 5 BP'!$F$7:$EE$7)+SUMIF('SPACELOG 6 BP'!$F$2:$EE$2,AV$4,'SPACELOG 6 BP'!$F$7:$EE$7)+SUMIF('SPACELOG 7 BP'!$F$2:$EE$2,AV$4,'SPACELOG 7 BP'!$F$7:$EE$7)+SUMIF('SPACELOG 8 BP'!$F$2:$EE$2,AV$4,'SPACELOG 8 BP'!$F$7:$EE$7)+SUMIF('SPACELOG 9 BP'!$F$2:$EE$2,AV$4,'SPACELOG 9 BP'!$F$7:$EE$7)+SUMIF('SPACELOG 10 BP'!$F$2:$EE$2,AV$4,'SPACELOG 10 BP'!$F$7:$EE$7)+SUMIF('SPACELOG 11 BP'!$F$2:$EE$2,AV$4,'SPACELOG 11 BP'!$F$7:$EE$7)+SUMIF('SPACELOG 12 BP'!$F$2:$EE$2,AV$4,'SPACELOG 12 BP'!$F$7:$EE$7) -> 128185 | AW7: =SUMIF('reporting montigny'!$F$2:$EE$2,AW$4,'reporting montigny'!$F$7:$EE$7)+SUMIF('reporting boissy'!$F$2:$EE$2,AW$4,'reporting boissy'!$F$7:$EE$7)+SUMIF('reporting moussy'!$F$2:$EE$2,AW$4,'reporting moussy'!$F$7:$EE$7)+SUMIF('reporting trappes'!$F$2:$EE$2,AW$4,'reporting trappes'!$F$7:$EE$7)+SUMIF('SPACELOG 5 BP'!$F$2:$EE$2,AW$4,'SPACELOG 5 BP'!$F$7:$EE$7)+SUMIF('SPACELOG 6 BP'!$F$2:$EE$2,AW$4,'SPACELOG 6 BP'!$F$7:$EE$7)+SUMIF('SPACELOG 7 BP'!$F$2:$EE$2,AW$4,'SPACELOG 7 BP'!$F$7:$EE$7)+SUMIF('SPACELOG 8 BP'!$F$2:$EE$2,AW$4,'SPACELOG 8 BP'!$F$7:$EE$7)+SUMIF('SPACELOG 9 BP'!$F$2:$EE$2,AW$4,'SPACELOG 9 BP'!$F$7:$EE$7)+SUMIF('SPACELOG 10 BP'!$F$2:$EE$2,AW$4,'SPACELOG 10 BP'!$F$7:$EE$7)+SUMIF('SPACELOG 11 BP'!$F$2:$EE$2,AW$4,'SPACELOG 11 BP'!$F$7:$EE$7)+SUMIF('SPACELOG 12 BP'!$F$2:$EE$2,AW$4,'SPACELOG 12 BP'!$F$7:$EE$7) -> 128185 | AX7: =SUMIF('reporting montigny'!$F$2:$EE$2,AX$4,'reporting montigny'!$F$7:$EE$7)+SUMIF('reporting boissy'!$F$2:$EE$2,AX$4,'reporting boissy'!$F$7:$EE$7)+SUMIF('reporting moussy'!$F$2:$EE$2,AX$4,'reporting moussy'!$F$7:$EE$7)+SUMIF('reporting trappes'!$F$2:$EE$2,AX$4,'reporting trappes'!$F$7:$EE$7)+SUMIF('SPACELOG 5 BP'!$F$2:$EE$2,AX$4,'SPACELOG 5 BP'!$F$7:$EE$7)+SUMIF('SPACELOG 6 BP'!$F$2:$EE$2,AX$4,'SPACELOG 6 BP'!$F$7:$EE$7)+SUMIF('SPACELOG 7 BP'!$F$2:$EE$2,AX$4,'SPACELOG 7 BP'!$F$7:$EE$7)+SUMIF('SPACELOG 8 BP'!$F$2:$EE$2,AX$4,'SPACELOG 8 BP'!$F$7:$EE$7)+SUMIF('SPACELOG 9 BP'!$F$2:$EE$2,AX$4,'SPACELOG 9 BP'!$F$7:$EE$7)+SUMIF('SPACELOG 10 BP'!$F$2:$EE$2,AX$4,'SPACELOG 10 BP'!$F$7:$EE$7)+SUMIF('SPACELOG 11 BP'!$F$2:$EE$2,AX$4,'SPACELOG 11 BP'!$F$7:$EE$7)+SUMIF('SPACELOG 12 BP'!$F$2:$EE$2,AX$4,'SPACELOG 12 BP'!$F$7:$EE$7) -> 128185 | AY7: =SUMIF('reporting montigny'!$F$2:$EE$2,AY$4,'reporting montigny'!$F$7:$EE$7)+SUMIF('reporting boissy'!$F$2:$EE$2,AY$4,'reporting boissy'!$F$7:$EE$7)+SUMIF('reporting moussy'!$F$2:$EE$2,AY$4,'reporting moussy'!$F$7:$EE$7)+SUMIF('reporting trappes'!$F$2:$EE$2,AY$4,'reporting trappes'!$F$7:$EE$7)+SUMIF('SPACELOG 5 BP'!$F$2:$EE$2,AY$4,'SPACELOG 5 BP'!$F$7:$EE$7)+SUMIF('SPACELOG 6 BP'!$F$2:$EE$2,AY$4,'SPACELOG 6 BP'!$F$7:$EE$7)+SUMIF('SPACELOG 7 BP'!$F$2:$EE$2,AY$4,'SPACELOG 7 BP'!$F$7:$EE$7)+SUMIF('SPACELOG 8 BP'!$F$2:$EE$2,AY$4,'SPACELOG 8 BP'!$F$7:$EE$7)+SUMIF('SPACELOG 9 BP'!$F$2:$EE$2,AY$4,'SPACELOG 9 BP'!$F$7:$EE$7)+SUMIF('SPACELOG 10 BP'!$F$2:$EE$2,AY$4,'SPACELOG 10 BP'!$F$7:$EE$7)+SUMIF('SPACELOG 11 BP'!$F$2:$EE$2,AY$4,'SPACELOG 11 BP'!$F$7:$EE$7)+SUMIF('SPACELOG 12 BP'!$F$2:$EE$2,AY$4,'SPACELOG 12 BP'!$F$7:$EE$7) -> 128185 | AZ7: =SUMIF('reporting montigny'!$F$2:$EE$2,AZ$4,'reporting montigny'!$F$7:$EE$7)+SUMIF('reporting boissy'!$F$2:$EE$2,AZ$4,'reporting boissy'!$F$7:$EE$7)+SUMIF('reporting moussy'!$F$2:$EE$2,AZ$4,'reporting moussy'!$F$7:$EE$7)+SUMIF('reporting trappes'!$F$2:$EE$2,AZ$4,'reporting trappes'!$F$7:$EE$7)+SUMIF('SPACELOG 5 BP'!$F$2:$EE$2,AZ$4,'SPACELOG 5 BP'!$F$7:$EE$7)+SUMIF('SPACELOG 6 BP'!$F$2:$EE$2,AZ$4,'SPACELOG 6 BP'!$F$7:$EE$7)+SUMIF('SPACELOG 7 BP'!$F$2:$EE$2,AZ$4,'SPACELOG 7 BP'!$F$7:$EE$7)+SUMIF('SPACELOG 8 BP'!$F$2:$EE$2,AZ$4,'SPACELOG 8 BP'!$F$7:$EE$7)+SUMIF('SPACELOG 9 BP'!$F$2:$EE$2,AZ$4,'SPACELOG 9 BP'!$F$7:$EE$7)+SUMIF('SPACELOG 10 BP'!$F$2:$EE$2,AZ$4,'SPACELOG 10 BP'!$F$7:$EE$7)+SUMIF('SPACELOG 11 BP'!$F$2:$EE$2,AZ$4,'SPACELOG 11 BP'!$F$7:$EE$7)+SUMIF('SPACELOG 12 BP'!$F$2:$EE$2,AZ$4,'SPACELOG 12 BP'!$F$7:$EE$7) -> 128185 | ... BD7: =SUMIF('reporting montigny'!$F$2:$EE$2,BD$4,'reporting montigny'!$F$7:$EE$7)+SUMIF('reporting boissy'!$F$2:$EE$2,BD$4,'reporting boissy'!$F$7:$EE$7)+SUMIF('reporting moussy'!$F$2:$EE$2,BD$4,'reporting moussy'!$F$7:$EE$7)+SUMIF('reporting trappes'!$F$2:$EE$2,BD$4,'reporting trappes'!$F$7:$EE$7)+SUMIF('SPACELOG 5 BP'!$F$2:$EE$2,BD$4,'SPACELOG 5 BP'!$F$7:$EE$7)+SUMIF('SPACELOG 6 BP'!$F$2:$EE$2,BD$4,'SPACELOG 6 BP'!$F$7:$EE$7)+SUMIF('SPACELOG 7 BP'!$F$2:$EE$2,BD$4,'SPACELOG 7 BP'!$F$7:$EE$7)+SUMIF('SPACELOG 8 BP'!$F$2:$EE$2,BD$4,'SPACELOG 8 BP'!$F$7:$EE$7)+SUMIF('SPACELOG 9 BP'!$F$2:$EE$2,BD$4,'SPACELOG 9 BP'!$F$7:$EE$7)+SUMIF('SPACELOG 10 BP'!$F$2:$EE$2,BD$4,'SPACELOG 10 BP'!$F$7:$EE$7)+SUMIF('SPACELOG 11 BP'!$F$2:$EE$2,BD$4,'SPACELOG 11 BP'!$F$7:$EE$7)+SUMIF('SPACELOG 12 BP'!$F$2:$EE$2,BD$4,'SPACELOG 12 BP'!$F$7:$EE$7) -> 128185 | BE7: =SUM(AS7:BD7) -> 1538220 | BF7: =SUMIF('reporting montigny'!$F$2:$EE$2,BF$4,'reporting montigny'!$F$7:$EE$7)+SUMIF('reporting boissy'!$F$2:$EE$2,BF$4,'reporting boissy'!$F$7:$EE$7)+SUMIF('reporting moussy'!$F$2:$EE$2,BF$4,'reporting moussy'!$F$7:$EE$7)+SUMIF('reporting trappes'!$F$2:$EE$2,BF$4,'reporting trappes'!$F$7:$EE$7)+SUMIF('SPACELOG 5 BP'!$F$2:$EE$2,BF$4,'SPACELOG 5 BP'!$F$7:$EE$7)+SUMIF('SPACELOG 6 BP'!$F$2:$EE$2,BF$4,'SPACELOG 6 BP'!$F$7:$EE$7)+SUMIF('SPACELOG 7 BP'!$F$2:$EE$2,BF$4,'SPACELOG 7 BP'!$F$7:$EE$7)+SUMIF('SPACELOG 8 BP'!$F$2:$EE$2,BF$4,'SPACELOG 8 BP'!$F$7:$EE$7)+SUMIF('SPACELOG 9 BP'!$F$2:$EE$2,BF$4,'SPACELOG 9 BP'!$F$7:$EE$7)+SUMIF('SPACELOG 10 BP'!$F$2:$EE$2,BF$4,'SPACELOG 10 BP'!$F$7:$EE$7)+SUMIF('SPACELOG 11 BP'!$F$2:$EE$2,BF$4,'SPACELOG 11 BP'!$F$7:$EE$7)+SUMIF('SPACELOG 12 BP'!$F$2:$EE$2,BF$4,'SPACELOG 12 BP'!$F$7:$EE$7) -> 128185 | BG7: =SUMIF('reporting montigny'!$F$2:$EE$2,BG$4,'reporting montigny'!$F$7:$EE$7)+SUMIF('reporting boissy'!$F$2:$EE$2,BG$4,'reporting boissy'!$F$7:$EE$7)+SUMIF('reporting moussy'!$F$2:$EE$2,BG$4,'reporting moussy'!$F$7:$EE$7)+SUMIF('reporting trappes'!$F$2:$EE$2,BG$4,'reporting trappes'!$F$7:$EE$7)+SUMIF('SPACELOG 5 BP'!$F$2:$EE$2,BG$4,'SPACELOG 5 BP'!$F$7:$EE$7)+SUMIF('SPACELOG 6 BP'!$F$2:$EE$2,BG$4,'SPACELOG 6 BP'!$F$7:$EE$7)+SUMIF('SPACELOG 7 BP'!$F$2:$EE$2,BG$4,'SPACELOG 7 BP'!$F$7:$EE$7)+SUMIF('SPACELOG 8 BP'!$F$2:$EE$2,BG$4,'SPACELOG 8 BP'!$F$7:$EE$7)+SUMIF('SPACELOG 9 BP'!$F$2:$EE$2,BG$4,'SPACELOG 9 BP'!$F$7:$EE$7)+SUMIF('SPACELOG 10 BP'!$F$2:$EE$2,BG$4,'SPACELOG 10 BP'!$F$7:$EE$7)+SUMIF('SPACELOG 11 BP'!$F$2:$EE$2,BG$4,'SPACELOG 11 BP'!$F$7:$EE$7)+SUMIF('SPACELOG 12 BP'!$F$2:$EE$2,BG$4,'SPACELOG 12 BP'!$F$7:$EE$7) -> 128185 | BH7: =SUMIF('reporting montigny'!$F$2:$EE$2,BH$4,'reporting montigny'!$F$7:$EE$7)+SUMIF('reporting boissy'!$F$2:$EE$2,BH$4,'reporting boissy'!$F$7:$EE$7)+SUMIF('reporting moussy'!$F$2:$EE$2,BH$4,'reporting moussy'!$F$7:$EE$7)+SUMIF('reporting trappes'!$F$2:$EE$2,BH$4,'reporting trappes'!$F$7:$EE$7)+SUMIF('SPACELOG 5 BP'!$F$2:$EE$2,BH$4,'SPACELOG 5 BP'!$F$7:$EE$7)+SUMIF('SPACELOG 6 BP'!$F$2:$EE$2,BH$4,'SPACELOG 6 BP'!$F$7:$EE$7)+SUMIF('SPACELOG 7 BP'!$F$2:$EE$2,BH$4,'SPACELOG 7 BP'!$F$7:$EE$7)+SUMIF('SPACELOG 8 BP'!$F$2:$EE$2,BH$4,'SPACELOG 8 BP'!$F$7:$EE$7)+SUMIF('SPACELOG 9 BP'!$F$2:$EE$2,BH$4,'SPACELOG 9 BP'!$F$7:$EE$7)+SUMIF('SPACELOG 10 BP'!$F$2:$EE$2,BH$4,'SPACELOG 10 BP'!$F$7:$EE$7)+SUMIF('SPACELOG 11 BP'!$F$2:$EE$2,BH$4,'SPACELOG 11 BP'!$F$7:$EE$7)+SUMIF('SPACELOG 12 BP'!$F$2:$EE$2,BH$4,'SPACELOG 12 BP'!$F$7:$EE$7) -> 128185 | BI7: =SUMIF('reporting montigny'!$F$2:$EE$2,BI$4,'reporting montigny'!$F$7:$EE$7)+SUMIF('reporting boissy'!$F$2:$EE$2,BI$4,'reporting boissy'!$F$7:$EE$7)+SUMIF('reporting moussy'!$F$2:$EE$2,BI$4,'reporting moussy'!$F$7:$EE$7)+SUMIF('reporting trappes'!$F$2:$EE$2,BI$4,'reporting trappes'!$F$7:$EE$7)+SUMIF('SPACELOG 5 BP'!$F$2:$EE$2,BI$4,'SPACELOG 5 BP'!$F$7:$EE$7)+SUMIF('SPACELOG 6 BP'!$F$2:$EE$2,BI$4,'SPACELOG 6 BP'!$F$7:$EE$7)+SUMIF('SPACELOG 7 BP'!$F$2:$EE$2,BI$4,'SPACELOG 7 BP'!$F$7:$EE$7)+SUMIF('SPACELOG 8 BP'!$F$2:$EE$2,BI$4,'SPACELOG 8 BP'!$F$7:$EE$7)+SUMIF('SPACELOG 9 BP'!$F$2:$EE$2,BI$4,'SPACELOG 9 BP'!$F$7:$EE$7)+SUMIF('SPACELOG 10 BP'!$F$2:$EE$2,BI$4,'SPACELOG 10 BP'!$F$7:$EE$7)+SUMIF('SPACELOG 11 BP'!$F$2:$EE$2,BI$4,'SPACELOG 11 BP'!$F$7:$EE$7)+SUMIF('SPACELOG 12 BP'!$F$2:$EE$2,BI$4,'SPACELOG 12 BP'!$F$7:$EE$7) -> 128185 | BJ7: =SUMIF('reporting montigny'!$F$2:$EE$2,BJ$4,'reporting montigny'!$F$7:$EE$7)+SUMIF('reporting boissy'!$F$2:$EE$2,BJ$4,'reporting boissy'!$F$7:$EE$7)+SUMIF('reporting moussy'!$F$2:$EE$2,BJ$4,'reporting moussy'!$F$7:$EE$7)+SUMIF('reporting trappes'!$F$2:$EE$2,BJ$4,'reporting trappes'!$F$7:$EE$7)+SUMIF('SPACELOG 5 BP'!$F$2:$EE$2,BJ$4,'SPACELOG 5 BP'!$F$7:$EE$7)+SUMIF('SPACELOG 6 BP'!$F$2:$EE$2,BJ$4,'SPACELOG 6 BP'!$F$7:$EE$7)+SUMIF('SPACELOG 7 BP'!$F$2:$EE$2,BJ$4,'SPACELOG 7 BP'!$F$7:$EE$7)+SUMIF('SPACELOG 8 BP'!$F$2:$EE$2,BJ$4,'SPACELOG 8 BP'!$F$7:$EE$7)+SUMIF('SPACELOG 9 BP'!$F$2:$EE$2,BJ$4,'SPACELOG 9 BP'!$F$7:$EE$7)+SUMIF('SPACELOG 10 BP'!$F$2:$EE$2,BJ$4,'SPACELOG 10 BP'!$F$7:$EE$7)+SUMIF('SPACELOG 11 BP'!$F$2:$EE$2,BJ$4,'SPACELOG 11 BP'!$F$7:$EE$7)+SUMIF('SPACELOG 12 BP'!$F$2:$EE$2,BJ$4,'SPACELOG 12 BP'!$F$7:$EE$7) -> 128185 | BK7: =SUMIF('reporting montigny'!$F$2:$EE$2,BK$4,'reporting montigny'!$F$7:$EE$7)+SUMIF('reporting boissy'!$F$2:$EE$2,BK$4,'reporting boissy'!$F$7:$EE$7)+SUMIF('reporting moussy'!$F$2:$EE$2,BK$4,'reporting moussy'!$F$7:$EE$7)+SUMIF('reporting trappes'!$F$2:$EE$2,BK$4,'reporting trappes'!$F$7:$EE$7)+SUMIF('SPACELOG 5 BP'!$F$2:$EE$2,BK$4,'SPACELOG 5 BP'!$F$7:$EE$7)+SUMIF('SPACELOG 6 BP'!$F$2:$EE$2,BK$4,'SPACELOG 6 BP'!$F$7:$EE$7)+SUMIF('SPACELOG 7 BP'!$F$2:$EE$2,BK$4,'SPACELOG 7 BP'!$F$7:$EE$7)+SUMIF('SPACELOG 8 BP'!$F$2:$EE$2,BK$4,'SPACELOG 8 BP'!$F$7:$EE$7)+SUMIF('SPACELOG 9 BP'!$F$2:$EE$2,BK$4,'SPACELOG 9 BP'!$F$7:$EE$7)+SUMIF('SPACELOG 10 BP'!$F$2:$EE$2,BK$4,'SPACELOG 10 BP'!$F$7:$EE$7)+SUMIF('SPACELOG 11 BP'!$F$2:$EE$2,BK$4,'SPACELOG 11 BP'!$F$7:$EE$7)+SUMIF('SPACELOG 12 BP'!$F$2:$EE$2,BK$4,'SPACELOG 12 BP'!$F$7:$EE$7) -> 128185 | BL7: =SUMIF('reporting montigny'!$F$2:$EE$2,BL$4,'reporting montigny'!$F$7:$EE$7)+SUMIF('reporting boissy'!$F$2:$EE$2,BL$4,'reporting boissy'!$F$7:$EE$7)+SUMIF('reporting moussy'!$F$2:$EE$2,BL$4,'reporting moussy'!$F$7:$EE$7)+SUMIF('reporting trappes'!$F$2:$EE$2,BL$4,'reporting trappes'!$F$7:$EE$7)+SUMIF('SPACELOG 5 BP'!$F$2:$EE$2,BL$4,'SPACELOG 5 BP'!$F$7:$EE$7)+SUMIF('SPACELOG 6 BP'!$F$2:$EE$2,BL$4,'SPACELOG 6 BP'!$F$7:$EE$7)+SUMIF('SPACELOG 7 BP'!$F$2:$EE$2,BL$4,'SPACELOG 7 BP'!$F$7:$EE$7)+SUMIF('SPACELOG 8 BP'!$F$2:$EE$2,BL$4,'SPACELOG 8 BP'!$F$7:$EE$7)+SUMIF('SPACELOG 9 BP'!$F$2:$EE$2,BL$4,'SPACELOG 9 BP'!$F$7:$EE$7)+SUMIF('SPACELOG 10 BP'!$F$2:$EE$2,BL$4,'SPACELOG 10 BP'!$F$7:$EE$7)+SUMIF('SPACELOG 11 BP'!$F$2:$EE$2,BL$4,'SPACELOG 11 BP'!$F$7:$EE$7)+SUMIF('SPACELOG 12 BP'!$F$2:$EE$2,BL$4,'SPACELOG 12 BP'!$F$7:$EE$7) -> 128185 | BM7: =SUMIF('reporting montigny'!$F$2:$EE$2,BM$4,'reporting montigny'!$F$7:$EE$7)+SUMIF('reporting boissy'!$F$2:$EE$2,BM$4,'reporting boissy'!$F$7:$EE$7)+SUMIF('reporting moussy'!$F$2:$EE$2,BM$4,'reporting moussy'!$F$7:$EE$7)+SUMIF('reporting trappes'!$F$2:$EE$2,BM$4,'reporting trappes'!$F$7:$EE$7)+SUMIF('SPACELOG 5 BP'!$F$2:$EE$2,BM$4,'SPACELOG 5 BP'!$F$7:$EE$7)+SUMIF('SPACELOG 6 BP'!$F$2:$EE$2,BM$4,'SPACELOG 6 BP'!$F$7:$EE$7)+SUMIF('SPACELOG 7 BP'!$F$2:$EE$2,BM$4,'SPACELOG 7 BP'!$F$7:$EE$7)+SUMIF('SPACELOG 8 BP'!$F$2:$EE$2,BM$4,'SPACELOG 8 BP'!$F$7:$EE$7)+SUMIF('SPACELOG 9 BP'!$F$2:$EE$2,BM$4,'SPACELOG 9 BP'!$F$7:$EE$7)+SUMIF('SPACELOG 10 BP'!$F$2:$EE$2,BM$4,'SPACELOG 10 BP'!$F$7:$EE$7)+SUMIF('SPACELOG 11 BP'!$F$2:$EE$2,BM$4,'SPACELOG 11 BP'!$F$7:$EE$7)+SUMIF('SPACELOG 12 BP'!$F$2:$EE$2,BM$4,'SPACELOG 12 BP'!$F$7:$EE$7) -> 128185 | ... BQ7: =SUMIF('reporting montigny'!$F$2:$EE$2,BQ$4,'reporting montigny'!$F$7:$EE$7)+SUMIF('reporting boissy'!$F$2:$EE$2,BQ$4,'reporting boissy'!$F$7:$EE$7)+SUMIF('reporting moussy'!$F$2:$EE$2,BQ$4,'reporting moussy'!$F$7:$EE$7)+SUMIF('reporting trappes'!$F$2:$EE$2,BQ$4,'reporting trappes'!$F$7:$EE$7)+SUMIF('SPACELOG 5 BP'!$F$2:$EE$2,BQ$4,'SPACELOG 5 BP'!$F$7:$EE$7)+SUMIF('SPACELOG 6 BP'!$F$2:$EE$2,BQ$4,'SPACELOG 6 BP'!$F$7:$EE$7)+SUMIF('SPACELOG 7 BP'!$F$2:$EE$2,BQ$4,'SPACELOG 7 BP'!$F$7:$EE$7)+SUMIF('SPACELOG 8 BP'!$F$2:$EE$2,BQ$4,'SPACELOG 8 BP'!$F$7:$EE$7)+SUMIF('SPACELOG 9 BP'!$F$2:$EE$2,BQ$4,'SPACELOG 9 BP'!$F$7:$EE$7)+SUMIF('SPACELOG 10 BP'!$F$2:$EE$2,BQ$4,'SPACELOG 10 BP'!$F$7:$EE$7)+SUMIF('SPACELOG 11 BP'!$F$2:$EE$2,BQ$4,'SPACELOG 11 BP'!$F$7:$EE$7)+SUMIF('SPACELOG 12 BP'!$F$2:$EE$2,BQ$4,'SPACELOG 12 BP'!$F$7:$EE$7) -> 128185 | BR7: =SUM(BF7:BQ7) -> 1538220 | BS7: =SUMIF('reporting montigny'!$F$2:$EE$2,BS$4,'reporting montigny'!$F$7:$EE$7)+SUMIF('reporting boissy'!$F$2:$EE$2,BS$4,'reporting boissy'!$F$7:$EE$7)+SUMIF('reporting moussy'!$F$2:$EE$2,BS$4,'reporting moussy'!$F$7:$EE$7)+SUMIF('reporting trappes'!$F$2:$EE$2,BS$4,'reporting trappes'!$F$7:$EE$7)+SUMIF('SPACELOG 5 BP'!$F$2:$EE$2,BS$4,'SPACELOG 5 BP'!$F$7:$EE$7)+SUMIF('SPACELOG 6 BP'!$F$2:$EE$2,BS$4,'SPACELOG 6 BP'!$F$7:$EE$7)+SUMIF('SPACELOG 7 BP'!$F$2:$EE$2,BS$4,'SPACELOG 7 BP'!$F$7:$EE$7)+SUMIF('SPACELOG 8 BP'!$F$2:$EE$2,BS$4,'SPACELOG 8 BP'!$F$7:$EE$7)+SUMIF('SPACELOG 9 BP'!$F$2:$EE$2,BS$4,'SPACELOG 9 BP'!$F$7:$EE$7)+SUMIF('SPACELOG 10 BP'!$F$2:$EE$2,BS$4,'SPACELOG 10 BP'!$F$7:$EE$7)+SUMIF('SPACELOG 11 BP'!$F$2:$EE$2,BS$4,'SPACELOG 11 BP'!$F$7:$EE$7)+SUMIF('SPACELOG 12 BP'!$F$2:$EE$2,BS$4,'SPACELOG 12 BP'!$F$7:$EE$7) -> 128185 | BT7: =SUMIF('reporting montigny'!$F$2:$EE$2,BT$4,'reporting montigny'!$F$7:$EE$7)+SUMIF('reporting boissy'!$F$2:$EE$2,BT$4,'reporting boissy'!$F$7:$EE$7)+SUMIF('reporting moussy'!$F$2:$EE$2,BT$4,'reporting moussy'!$F$7:$EE$7)+SUMIF('reporting trappes'!$F$2:$EE$2,BT$4,'reporting trappes'!$F$7:$EE$7)+SUMIF('SPACELOG 5 BP'!$F$2:$EE$2,BT$4,'SPACELOG 5 BP'!$F$7:$EE$7)+SUMIF('SPACELOG 6 BP'!$F$2:$EE$2,BT$4,'SPACELOG 6 BP'!$F$7:$EE$7)+SUMIF('SPACELOG 7 BP'!$F$2:$EE$2,BT$4,'SPACELOG 7 BP'!$F$7:$EE$7)+SUMIF('SPACELOG 8 BP'!$F$2:$EE$2,BT$4,'SPACELOG 8 BP'!$F$7:$EE$7)+SUMIF('SPACELOG 9 BP'!$F$2:$EE$2,BT$4,'SPACELOG 9 BP'!$F$7:$EE$7)+SUMIF('SPACELOG 10 BP'!$F$2:$EE$2,BT$4,'SPACELOG 10 BP'!$F$7:$EE$7)+SUMIF('SPACELOG 11 BP'!$F$2:$EE$2,BT$4,'SPACELOG 11 BP'!$F$7:$EE$7)+SUMIF('SPACELOG 12 BP'!$F$2:$EE$2,BT$4,'SPACELOG 12 BP'!$F$7:$EE$7) -> 128185 | BU7: =SUMIF('reporting montigny'!$F$2:$EE$2,BU$4,'reporting montigny'!$F$7:$EE$7)+SUMIF('reporting boissy'!$F$2:$EE$2,BU$4,'reporting boissy'!$F$7:$EE$7)+SUMIF('reporting moussy'!$F$2:$EE$2,BU$4,'reporting moussy'!$F$7:$EE$7)+SUMIF('reporting trappes'!$F$2:$EE$2,BU$4,'reporting trappes'!$F$7:$EE$7)+SUMIF('SPACELOG 5 BP'!$F$2:$EE$2,BU$4,'SPACELOG 5 BP'!$F$7:$EE$7)+SUMIF('SPACELOG 6 BP'!$F$2:$EE$2,BU$4,'SPACELOG 6 BP'!$F$7:$EE$7)+SUMIF('SPACELOG 7 BP'!$F$2:$EE$2,BU$4,'SPACELOG 7 BP'!$F$7:$EE$7)+SUMIF('SPACELOG 8 BP'!$F$2:$EE$2,BU$4,'SPACELOG 8 BP'!$F$7:$EE$7)+SUMIF('SPACELOG 9 BP'!$F$2:$EE$2,BU$4,'SPACELOG 9 BP'!$F$7:$EE$7)+SUMIF('SPACELOG 10 BP'!$F$2:$EE$2,BU$4,'SPACELOG 10 BP'!$F$7:$EE$7)+SUMIF('SPACELOG 11 BP'!$F$2:$EE$2,BU$4,'SPACELOG 11 BP'!$F$7:$EE$7)+SUMIF('SPACELOG 12 BP'!$F$2:$EE$2,BU$4,'SPACELOG 12 BP'!$F$7:$EE$7) -> 128185 | BV7: =SUMIF('reporting montigny'!$F$2:$EE$2,BV$4,'reporting montigny'!$F$7:$EE$7)+SUMIF('reporting boissy'!$F$2:$EE$2,BV$4,'reporting boissy'!$F$7:$EE$7)+SUMIF('reporting moussy'!$F$2:$EE$2,BV$4,'reporting moussy'!$F$7:$EE$7)+SUMIF('reporting trappes'!$F$2:$EE$2,BV$4,'reporting trappes'!$F$7:$EE$7)+SUMIF('SPACELOG 5 BP'!$F$2:$EE$2,BV$4,'SPACELOG 5 BP'!$F$7:$EE$7)+SUMIF('SPACELOG 6 BP'!$F$2:$EE$2,BV$4,'SPACELOG 6 BP'!$F$7:$EE$7)+SUMIF('SPACELOG 7 BP'!$F$2:$EE$2,BV$4,'SPACELOG 7 BP'!$F$7:$EE$7)+SUMIF('SPACELOG 8 BP'!$F$2:$EE$2,BV$4,'SPACELOG 8 BP'!$F$7:$EE$7)+SUMIF('SPACELOG 9 BP'!$F$2:$EE$2,BV$4,'SPACELOG 9 BP'!$F$7:$EE$7)+SUMIF('SPACELOG 10 BP'!$F$2:$EE$2,BV$4,'SPACELOG 10 BP'!$F$7:$EE$7)+SUMIF('SPACELOG 11 BP'!$F$2:$EE$2,BV$4,'SPACELOG 11 BP'!$F$7:$EE$7)+SUMIF('SPACELOG 12 BP'!$F$2:$EE$2,BV$4,'SPACELOG 12 BP'!$F$7:$EE$7) -> 128185 | BW7: =SUMIF('reporting montigny'!$F$2:$EE$2,BW$4,'reporting montigny'!$F$7:$EE$7)+SUMIF('reporting boissy'!$F$2:$EE$2,BW$4,'reporting boissy'!$F$7:$EE$7)+SUMIF('reporting moussy'!$F$2:$EE$2,BW$4,'reporting moussy'!$F$7:$EE$7)+SUMIF('reporting trappes'!$F$2:$EE$2,BW$4,'reporting trappes'!$F$7:$EE$7)+SUMIF('SPACELOG 5 BP'!$F$2:$EE$2,BW$4,'SPACELOG 5 BP'!$F$7:$EE$7)+SUMIF('SPACELOG 6 BP'!$F$2:$EE$2,BW$4,'SPACELOG 6 BP'!$F$7:$EE$7)+SUMIF('SPACELOG 7 BP'!$F$2:$EE$2,BW$4,'SPACELOG 7 BP'!$F$7:$EE$7)+SUMIF('SPACELOG 8 BP'!$F$2:$EE$2,BW$4,'SPACELOG 8 BP'!$F$7:$EE$7)+SUMIF('SPACELOG 9 BP'!$F$2:$EE$2,BW$4,'SPACELOG 9 BP'!$F$7:$EE$7)+SUMIF('SPACELOG 10 BP'!$F$2:$EE$2,BW$4,'SPACELOG 10 BP'!$F$7:$EE$7)+SUMIF('SPACELOG 11 BP'!$F$2:$EE$2,BW$4,'SPACELOG 11 BP'!$F$7:$EE$7)+SUMIF('SPACELOG 12 BP'!$F$2:$EE$2,BW$4,'SPACELOG 12 BP'!$F$7:$EE$7) -> 128185 | BX7: =SUMIF('reporting montigny'!$F$2:$EE$2,BX$4,'reporting montigny'!$F$7:$EE$7)+SUMIF('reporting boissy'!$F$2:$EE$2,BX$4,'reporting boissy'!$F$7:$EE$7)+SUMIF('reporting moussy'!$F$2:$EE$2,BX$4,'reporting moussy'!$F$7:$EE$7)+SUMIF('reporting trappes'!$F$2:$EE$2,BX$4,'reporting trappes'!$F$7:$EE$7)+SUMIF('SPACELOG 5 BP'!$F$2:$EE$2,BX$4,'SPACELOG 5 BP'!$F$7:$EE$7)+SUMIF('SPACELOG 6 BP'!$F$2:$EE$2,BX$4,'SPACELOG 6 BP'!$F$7:$EE$7)+SUMIF('SPACELOG 7 BP'!$F$2:$EE$2,BX$4,'SPACELOG 7 BP'!$F$7:$EE$7)+SUMIF('SPACELOG 8 BP'!$F$2:$EE$2,BX$4,'SPACELOG 8 BP'!$F$7:$EE$7)+SUMIF('SPACELOG 9 BP'!$F$2:$EE$2,BX$4,'SPACELOG 9 BP'!$F$7:$EE$7)+SUMIF('SPACELOG 10 BP'!$F$2:$EE$2,BX$4,'SPACELOG 10 BP'!$F$7:$EE$7)+SUMIF('SPACELOG 11 BP'!$F$2:$EE$2,BX$4,'SPACELOG 11 BP'!$F$7:$EE$7)+SUMIF('SPACELOG 12 BP'!$F$2:$EE$2,BX$4,'SPACELOG 12 BP'!$F$7:$EE$7) -> 128185 | BY7: =SUMIF('reporting montigny'!$F$2:$EE$2,BY$4,'reporting montigny'!$F$7:$EE$7)+SUMIF('reporting boissy'!$F$2:$EE$2,BY$4,'reporting boissy'!$F$7:$EE$7)+SUMIF('reporting moussy'!$F$2:$EE$2,BY$4,'reporting moussy'!$F$7:$EE$7)+SUMIF('reporting trappes'!$F$2:$EE$2,BY$4,'reporting trappes'!$F$7:$EE$7)+SUMIF('SPACELOG 5 BP'!$F$2:$EE$2,BY$4,'SPACELOG 5 BP'!$F$7:$EE$7)+SUMIF('SPACELOG 6 BP'!$F$2:$EE$2,BY$4,'SPACELOG 6 BP'!$F$7:$EE$7)+SUMIF('SPACELOG 7 BP'!$F$2:$EE$2,BY$4,'SPACELOG 7 BP'!$F$7:$EE$7)+SUMIF('SPACELOG 8 BP'!$F$2:$EE$2,BY$4,'SPACELOG 8 BP'!$F$7:$EE$7)+SUMIF('SPACELOG 9 BP'!$F$2:$EE$2,BY$4,'SPACELOG 9 BP'!$F$7:$EE$7)+SUMIF('SPACELOG 10 BP'!$F$2:$EE$2,BY$4,'SPACELOG 10 BP'!$F$7:$EE$7)+SUMIF('SPACELOG 11 BP'!$F$2:$EE$2,BY$4,'SPACELOG 11 BP'!$F$7:$EE$7)+SUMIF('SPACELOG 12 BP'!$F$2:$EE$2,BY$4,'SPACELOG 12 BP'!$F$7:$EE$7) -> 128185 | BZ7: =SUMIF('reporting montigny'!$F$2:$EE$2,BZ$4,'reporting montigny'!$F$7:$EE$7)+SUMIF('reporting boissy'!$F$2:$EE$2,BZ$4,'reporting boissy'!$F$7:$EE$7)+SUMIF('reporting moussy'!$F$2:$EE$2,BZ$4,'reporting moussy'!$F$7:$EE$7)+SUMIF('reporting trappes'!$F$2:$EE$2,BZ$4,'reporting trappes'!$F$7:$EE$7)+SUMIF('SPACELOG 5 BP'!$F$2:$EE$2,BZ$4,'SPACELOG 5 BP'!$F$7:$EE$7)+SUMIF('SPACELOG 6 BP'!$F$2:$EE$2,BZ$4,'SPACELOG 6 BP'!$F$7:$EE$7)+SUMIF('SPACELOG 7 BP'!$F$2:$EE$2,BZ$4,'SPACELOG 7 BP'!$F$7:$EE$7)+SUMIF('SPACELOG 8 BP'!$F$2:$EE$2,BZ$4,'SPACELOG 8 BP'!$F$7:$EE$7)+SUMIF('SPACELOG 9 BP'!$F$2:$EE$2,BZ$4,'SPACELOG 9 BP'!$F$7:$EE$7)+SUMIF('SPACELOG 10 BP'!$F$2:$EE$2,BZ$4,'SPACELOG 10 BP'!$F$7:$EE$7)+SUMIF('SPACELOG 11 BP'!$F$2:$EE$2,BZ$4,'SPACELOG 11 BP'!$F$7:$EE$7)+SUMIF('SPACELOG 12 BP'!$F$2:$EE$2,BZ$4,'SPACELOG 12 BP'!$F$7:$EE$7) -> 128185 | ... CD7: =SUMIF('reporting montigny'!$F$2:$EE$2,CD$4,'reporting montigny'!$F$7:$EE$7)+SUMIF('reporting boissy'!$F$2:$EE$2,CD$4,'reporting boissy'!$F$7:$EE$7)+SUMIF('reporting moussy'!$F$2:$EE$2,CD$4,'reporting moussy'!$F$7:$EE$7)+SUMIF('reporting trappes'!$F$2:$EE$2,CD$4,'reporting trappes'!$F$7:$EE$7)+SUMIF('SPACELOG 5 BP'!$F$2:$EE$2,CD$4,'SPACELOG 5 BP'!$F$7:$EE$7)+SUMIF('SPACELOG 6 BP'!$F$2:$EE$2,CD$4,'SPACELOG 6 BP'!$F$7:$EE$7)+SUMIF('SPACELOG 7 BP'!$F$2:$EE$2,CD$4,'SPACELOG 7 BP'!$F$7:$EE$7)+SUMIF('SPACELOG 8 BP'!$F$2:$EE$2,CD$4,'SPACELOG 8 BP'!$F$7:$EE$7)+SUMIF('SPACELOG 9 BP'!$F$2:$EE$2,CD$4,'SPACELOG 9 BP'!$F$7:$EE$7)+SUMIF('SPACELOG 10 BP'!$F$2:$EE$2,CD$4,'SPACELOG 10 BP'!$F$7:$EE$7)+SUMIF('SPACELOG 11 BP'!$F$2:$EE$2,CD$4,'SPACELOG 11 BP'!$F$7:$EE$7)+SUMIF('SPACELOG 12 BP'!$F$2:$EE$2,CD$4,'SPACELOG 12 BP'!$F$7:$EE$7) -> 128185 | CE7: =SUM(BS7:CD7) -> 1538220 | CF7: =SUMIF('reporting montigny'!$F$2:$EE$2,CF$4,'reporting montigny'!$F$7:$EE$7)+SUMIF('reporting boissy'!$F$2:$EE$2,CF$4,'reporting boissy'!$F$7:$EE$7)+SUMIF('reporting moussy'!$F$2:$EE$2,CF$4,'reporting moussy'!$F$7:$EE$7)+SUMIF('reporting trappes'!$F$2:$EE$2,CF$4,'reporting trappes'!$F$7:$EE$7)+SUMIF('SPACELOG 5 BP'!$F$2:$EE$2,CF$4,'SPACELOG 5 BP'!$F$7:$EE$7)+SUMIF('SPACELOG 6 BP'!$F$2:$EE$2,CF$4,'SPACELOG 6 BP'!$F$7:$EE$7)+SUMIF('SPACELOG 7 BP'!$F$2:$EE$2,CF$4,'SPACELOG 7 BP'!$F$7:$EE$7)+SUMIF('SPACELOG 8 BP'!$F$2:$EE$2,CF$4,'SPACELOG 8 BP'!$F$7:$EE$7)+SUMIF('SPACELOG 9 BP'!$F$2:$EE$2,CF$4,'SPACELOG 9 BP'!$F$7:$EE$7)+SUMIF('SPACELOG 10 BP'!$F$2:$EE$2,CF$4,'SPACELOG 10 BP'!$F$7:$EE$7)+SUMIF('SPACELOG 11 BP'!$F$2:$EE$2,CF$4,'SPACELOG 11 BP'!$F$7:$EE$7)+SUMIF('SPACELOG 12 BP'!$F$2:$EE$2,CF$4,'SPACELOG 12 BP'!$F$7:$EE$7) -> 128185 | CG7: =SUMIF('reporting montigny'!$F$2:$EE$2,CG$4,'reporting montigny'!$F$7:$EE$7)+SUMIF('reporting boissy'!$F$2:$EE$2,CG$4,'reporting boissy'!$F$7:$EE$7)+SUMIF('reporting moussy'!$F$2:$EE$2,CG$4,'reporting moussy'!$F$7:$EE$7)+SUMIF('reporting trappes'!$F$2:$EE$2,CG$4,'reporting trappes'!$F$7:$EE$7)+SUMIF('SPACELOG 5 BP'!$F$2:$EE$2,CG$4,'SPACELOG 5 BP'!$F$7:$EE$7)+SUMIF('SPACELOG 6 BP'!$F$2:$EE$2,CG$4,'SPACELOG 6 BP'!$F$7:$EE$7)+SUMIF('SPACELOG 7 BP'!$F$2:$EE$2,CG$4,'SPACELOG 7 BP'!$F$7:$EE$7)+SUMIF('SPACELOG 8 BP'!$F$2:$EE$2,CG$4,'SPACELOG 8 BP'!$F$7:$EE$7)+SUMIF('SPACELOG 9 BP'!$F$2:$EE$2,CG$4,'SPACELOG 9 BP'!$F$7:$EE$7)+SUMIF('SPACELOG 10 BP'!$F$2:$EE$2,CG$4,'SPACELOG 10 BP'!$F$7:$EE$7)+SUMIF('SPACELOG 11 BP'!$F$2:$EE$2,CG$4,'SPACELOG 11 BP'!$F$7:$EE$7)+SUMIF('SPACELOG 12 BP'!$F$2:$EE$2,CG$4,'SPACELOG 12 BP'!$F$7:$EE$7) -> 128185 | CH7: =SUMIF('reporting montigny'!$F$2:$EE$2,CH$4,'reporting montigny'!$F$7:$EE$7)+SUMIF('reporting boissy'!$F$2:$EE$2,CH$4,'reporting boissy'!$F$7:$EE$7)+SUMIF('reporting moussy'!$F$2:$EE$2,CH$4,'reporting moussy'!$F$7:$EE$7)+SUMIF('reporting trappes'!$F$2:$EE$2,CH$4,'reporting trappes'!$F$7:$EE$7)+SUMIF('SPACELOG 5 BP'!$F$2:$EE$2,CH$4,'SPACELOG 5 BP'!$F$7:$EE$7)+SUMIF('SPACELOG 6 BP'!$F$2:$EE$2,CH$4,'SPACELOG 6 BP'!$F$7:$EE$7)+SUMIF('SPACELOG 7 BP'!$F$2:$EE$2,CH$4,'SPACELOG 7 BP'!$F$7:$EE$7)+SUMIF('SPACELOG 8 BP'!$F$2:$EE$2,CH$4,'SPACELOG 8 BP'!$F$7:$EE$7)+SUMIF('SPACELOG 9 BP'!$F$2:$EE$2,CH$4,'SPACELOG 9 BP'!$F$7:$EE$7)+SUMIF('SPACELOG 10 BP'!$F$2:$EE$2,CH$4,'SPACELOG 10 BP'!$F$7:$EE$7)+SUMIF('SPACELOG 11 BP'!$F$2:$EE$2,CH$4,'SPACELOG 11 BP'!$F$7:$EE$7)+SUMIF('SPACELOG 12 BP'!$F$2:$EE$2,CH$4,'SPACELOG 12 BP'!$F$7:$EE$7) -> 128185 | CI7: =SUMIF('reporting montigny'!$F$2:$EE$2,CI$4,'reporting montigny'!$F$7:$EE$7)+SUMIF('reporting boissy'!$F$2:$EE$2,CI$4,'reporting boissy'!$F$7:$EE$7)+SUMIF('reporting moussy'!$F$2:$EE$2,CI$4,'reporting moussy'!$F$7:$EE$7)+SUMIF('reporting trappes'!$F$2:$EE$2,CI$4,'reporting trappes'!$F$7:$EE$7)+SUMIF('SPACELOG 5 BP'!$F$2:$EE$2,CI$4,'SPACELOG 5 BP'!$F$7:$EE$7)+SUMIF('SPACELOG 6 BP'!$F$2:$EE$2,CI$4,'SPACELOG 6 BP'!$F$7:$EE$7)+SUMIF('SPACELOG 7 BP'!$F$2:$EE$2,CI$4,'SPACELOG 7 BP'!$F$7:$EE$7)+SUMIF('SPACELOG 8 BP'!$F$2:$EE$2,CI$4,'SPACELOG 8 BP'!$F$7:$EE$7)+SUMIF('SPACELOG 9 BP'!$F$2:$EE$2,CI$4,'SPACELOG 9 BP'!$F$7:$EE$7)+SUMIF('SPACELOG 10 BP'!$F$2:$EE$2,CI$4,'SPACELOG 10 BP'!$F$7:$EE$7)+SUMIF('SPACELOG 11 BP'!$F$2:$EE$2,CI$4,'SPACELOG 11 BP'!$F$7:$EE$7)+SUMIF('SPACELOG 12 BP'!$F$2:$EE$2,CI$4,'SPACELOG 12 BP'!$F$7:$EE$7) -> 128185 | CJ7: =SUMIF('reporting montigny'!$F$2:$EE$2,CJ$4,'reporting montigny'!$F$7:$EE$7)+SUMIF('reporting boissy'!$F$2:$EE$2,CJ$4,'reporting boissy'!$F$7:$EE$7)+SUMIF('reporting moussy'!$F$2:$EE$2,CJ$4,'reporting moussy'!$F$7:$EE$7)+SUMIF('reporting trappes'!$F$2:$EE$2,CJ$4,'reporting trappes'!$F$7:$EE$7)+SUMIF('SPACELOG 5 BP'!$F$2:$EE$2,CJ$4,'SPACELOG 5 BP'!$F$7:$EE$7)+SUMIF('SPACELOG 6 BP'!$F$2:$EE$2,CJ$4,'SPACELOG 6 BP'!$F$7:$EE$7)+SUMIF('SPACELOG 7 BP'!$F$2:$EE$2,CJ$4,'SPACELOG 7 BP'!$F$7:$EE$7)+SUMIF('SPACELOG 8 BP'!$F$2:$EE$2,CJ$4,'SPACELOG 8 BP'!$F$7:$EE$7)+SUMIF('SPACELOG 9 BP'!$F$2:$EE$2,CJ$4,'SPACELOG 9 BP'!$F$7:$EE$7)+SUMIF('SPACELOG 10 BP'!$F$2:$EE$2,CJ$4,'SPACELOG 10 BP'!$F$7:$EE$7)+SUMIF('SPACELOG 11 BP'!$F$2:$EE$2,CJ$4,'SPACELOG 11 BP'!$F$7:$EE$7)+SUMIF('SPACELOG 12 BP'!$F$2:$EE$2,CJ$4,'SPACELOG 12 BP'!$F$7:$EE$7) -> 128185 | CK7: =SUMIF('reporting montigny'!$F$2:$EE$2,CK$4,'reporting montigny'!$F$7:$EE$7)+SUMIF('reporting boissy'!$F$2:$EE$2,CK$4,'reporting boissy'!$F$7:$EE$7)+SUMIF('reporting moussy'!$F$2:$EE$2,CK$4,'reporting moussy'!$F$7:$EE$7)+SUMIF('reporting trappes'!$F$2:$EE$2,CK$4,'reporting trappes'!$F$7:$EE$7)+SUMIF('SPACELOG 5 BP'!$F$2:$EE$2,CK$4,'SPACELOG 5 BP'!$F$7:$EE$7)+SUMIF('SPACELOG 6 BP'!$F$2:$EE$2,CK$4,'SPACELOG 6 BP'!$F$7:$EE$7)+SUMIF('SPACELOG 7 BP'!$F$2:$EE$2,CK$4,'SPACELOG 7 BP'!$F$7:$EE$7)+SUMIF('SPACELOG 8 BP'!$F$2:$EE$2,CK$4,'SPACELOG 8 BP'!$F$7:$EE$7)+SUMIF('SPACELOG 9 BP'!$F$2:$EE$2,CK$4,'SPACELOG 9 BP'!$F$7:$EE$7)+SUMIF('SPACELOG 10 BP'!$F$2:$EE$2,CK$4,'SPACELOG 10 BP'!$F$7:$EE$7)+SUMIF('SPACELOG 11 BP'!$F$2:$EE$2,CK$4,'SPACELOG 11 BP'!$F$7:$EE$7)+SUMIF('SPACELOG 12 BP'!$F$2:$EE$2,CK$4,'SPACELOG 12 BP'!$F$7:$EE$7) -> 128185 | CL7: =SUMIF('reporting montigny'!$F$2:$EE$2,CL$4,'reporting montigny'!$F$7:$EE$7)+SUMIF('reporting boissy'!$F$2:$EE$2,CL$4,'reporting boissy'!$F$7:$EE$7)+SUMIF('reporting moussy'!$F$2:$EE$2,CL$4,'reporting moussy'!$F$7:$EE$7)+SUMIF('reporting trappes'!$F$2:$EE$2,CL$4,'reporting trappes'!$F$7:$EE$7)+SUMIF('SPACELOG 5 BP'!$F$2:$EE$2,CL$4,'SPACELOG 5 BP'!$F$7:$EE$7)+SUMIF('SPACELOG 6 BP'!$F$2:$EE$2,CL$4,'SPACELOG 6 BP'!$F$7:$EE$7)+SUMIF('SPACELOG 7 BP'!$F$2:$EE$2,CL$4,'SPACELOG 7 BP'!$F$7:$EE$7)+SUMIF('SPACELOG 8 BP'!$F$2:$EE$2,CL$4,'SPACELOG 8 BP'!$F$7:$EE$7)+SUMIF('SPACELOG 9 BP'!$F$2:$EE$2,CL$4,'SPACELOG 9 BP'!$F$7:$EE$7)+SUMIF('SPACELOG 10 BP'!$F$2:$EE$2,CL$4,'SPACELOG 10 BP'!$F$7:$EE$7)+SUMIF('SPACELOG 11 BP'!$F$2:$EE$2,CL$4,'SPACELOG 11 BP'!$F$7:$EE$7)+SUMIF('SPACELOG 12 BP'!$F$2:$EE$2,CL$4,'SPACELOG 12 BP'!$F$7:$EE$7) -> 128185 | CM7: =SUMIF('reporting montigny'!$F$2:$EE$2,CM$4,'reporting montigny'!$F$7:$EE$7)+SUMIF('reporting boissy'!$F$2:$EE$2,CM$4,'reporting boissy'!$F$7:$EE$7)+SUMIF('reporting moussy'!$F$2:$EE$2,CM$4,'reporting moussy'!$F$7:$EE$7)+SUMIF('reporting trappes'!$F$2:$EE$2,CM$4,'reporting trappes'!$F$7:$EE$7)+SUMIF('SPACELOG 5 BP'!$F$2:$EE$2,CM$4,'SPACELOG 5 BP'!$F$7:$EE$7)+SUMIF('SPACELOG 6 BP'!$F$2:$EE$2,CM$4,'SPACELOG 6 BP'!$F$7:$EE$7)+SUMIF('SPACELOG 7 BP'!$F$2:$EE$2,CM$4,'SPACELOG 7 BP'!$F$7:$EE$7)+SUMIF('SPACELOG 8 BP'!$F$2:$EE$2,CM$4,'SPACELOG 8 BP'!$F$7:$EE$7)+SUMIF('SPACELOG 9 BP'!$F$2:$EE$2,CM$4,'SPACELOG 9 BP'!$F$7:$EE$7)+SUMIF('SPACELOG 10 BP'!$F$2:$EE$2,CM$4,'SPACELOG 10 BP'!$F$7:$EE$7)+SUMIF('SPACELOG 11 BP'!$F$2:$EE$2,CM$4,'SPACELOG 11 BP'!$F$7:$EE$7)+SUMIF('SPACELOG 12 BP'!$F$2:$EE$2,CM$4,'SPACELOG 12 BP'!$F$7:$EE$7) -> 128185 | ... CQ7: =SUMIF('reporting montigny'!$F$2:$EE$2,CQ$4,'reporting montigny'!$F$7:$EE$7)+SUMIF('reporting boissy'!$F$2:$EE$2,CQ$4,'reporting boissy'!$F$7:$EE$7)+SUMIF('reporting moussy'!$F$2:$EE$2,CQ$4,'reporting moussy'!$F$7:$EE$7)+SUMIF('reporting trappes'!$F$2:$EE$2,CQ$4,'reporting trappes'!$F$7:$EE$7)+SUMIF('SPACELOG 5 BP'!$F$2:$EE$2,CQ$4,'SPACELOG 5 BP'!$F$7:$EE$7)+SUMIF('SPACELOG 6 BP'!$F$2:$EE$2,CQ$4,'SPACELOG 6 BP'!$F$7:$EE$7)+SUMIF('SPACELOG 7 BP'!$F$2:$EE$2,CQ$4,'SPACELOG 7 BP'!$F$7:$EE$7)+SUMIF('SPACELOG 8 BP'!$F$2:$EE$2,CQ$4,'SPACELOG 8 BP'!$F$7:$EE$7)+SUMIF('SPACELOG 9 BP'!$F$2:$EE$2,CQ$4,'SPACELOG 9 BP'!$F$7:$EE$7)+SUMIF('SPACELOG 10 BP'!$F$2:$EE$2,CQ$4,'SPACELOG 10 BP'!$F$7:$EE$7)+SUMIF('SPACELOG 11 BP'!$F$2:$EE$2,CQ$4,'SPACELOG 11 BP'!$F$7:$EE$7)+SUMIF('SPACELOG 12 BP'!$F$2:$EE$2,CQ$4,'SPACELOG 12 BP'!$F$7:$EE$7) -> 128185 | CR7: =SUM(CF7:CQ7) -> 1538220 | CS7: =SUMIF('reporting montigny'!$F$2:$EE$2,CS$4,'reporting montigny'!$F$7:$EE$7)+SUMIF('reporting boissy'!$F$2:$EE$2,CS$4,'reporting boissy'!$F$7:$EE$7)+SUMIF('reporting moussy'!$F$2:$EE$2,CS$4,'reporting moussy'!$F$7:$EE$7)+SUMIF('reporting trappes'!$F$2:$EE$2,CS$4,'reporting trappes'!$F$7:$EE$7)+SUMIF('SPACELOG 5 BP'!$F$2:$EE$2,CS$4,'SPACELOG 5 BP'!$F$7:$EE$7)+SUMIF('SPACELOG 6 BP'!$F$2:$EE$2,CS$4,'SPACELOG 6 BP'!$F$7:$EE$7)+SUMIF('SPACELOG 7 BP'!$F$2:$EE$2,CS$4,'SPACELOG 7 BP'!$F$7:$EE$7)+SUMIF('SPACELOG 8 BP'!$F$2:$EE$2,CS$4,'SPACELOG 8 BP'!$F$7:$EE$7)+SUMIF('SPACELOG 9 BP'!$F$2:$EE$2,CS$4,'SPACELOG 9 BP'!$F$7:$EE$7)+SUMIF('SPACELOG 10 BP'!$F$2:$EE$2,CS$4,'SPACELOG 10 BP'!$F$7:$EE$7)+SUMIF('SPACELOG 11 BP'!$F$2:$EE$2,CS$4,'SPACELOG 11 BP'!$F$7:$EE$7)+SUMIF('SPACELOG 12 BP'!$F$2:$EE$2,CS$4,'SPACELOG 12 BP'!$F$7:$EE$7) -> 128185 | CT7: =SUMIF('reporting montigny'!$F$2:$EE$2,CT$4,'reporting montigny'!$F$7:$EE$7)+SUMIF('reporting boissy'!$F$2:$EE$2,CT$4,'reporting boissy'!$F$7:$EE$7)+SUMIF('reporting moussy'!$F$2:$EE$2,CT$4,'reporting moussy'!$F$7:$EE$7)+SUMIF('reporting trappes'!$F$2:$EE$2,CT$4,'reporting trappes'!$F$7:$EE$7)+SUMIF('SPACELOG 5 BP'!$F$2:$EE$2,CT$4,'SPACELOG 5 BP'!$F$7:$EE$7)+SUMIF('SPACELOG 6 BP'!$F$2:$EE$2,CT$4,'SPACELOG 6 BP'!$F$7:$EE$7)+SUMIF('SPACELOG 7 BP'!$F$2:$EE$2,CT$4,'SPACELOG 7 BP'!$F$7:$EE$7)+SUMIF('SPACELOG 8 BP'!$F$2:$EE$2,CT$4,'SPACELOG 8 BP'!$F$7:$EE$7)+SUMIF('SPACELOG 9 BP'!$F$2:$EE$2,CT$4,'SPACELOG 9 BP'!$F$7:$EE$7)+SUMIF('SPACELOG 10 BP'!$F$2:$EE$2,CT$4,'SPACELOG 10 BP'!$F$7:$EE$7)+SUMIF('SPACELOG 11 BP'!$F$2:$EE$2,CT$4,'SPACELOG 11 BP'!$F$7:$EE$7)+SUMIF('SPACELOG 12 BP'!$F$2:$EE$2,CT$4,'SPACELOG 12 BP'!$F$7:$EE$7) -> 128185 | CU7: =SUMIF('reporting montigny'!$F$2:$EE$2,CU$4,'reporting montigny'!$F$7:$EE$7)+SUMIF('reporting boissy'!$F$2:$EE$2,CU$4,'reporting boissy'!$F$7:$EE$7)+SUMIF('reporting moussy'!$F$2:$EE$2,CU$4,'reporting moussy'!$F$7:$EE$7)+SUMIF('reporting trappes'!$F$2:$EE$2,CU$4,'reporting trappes'!$F$7:$EE$7)+SUMIF('SPACELOG 5 BP'!$F$2:$EE$2,CU$4,'SPACELOG 5 BP'!$F$7:$EE$7)+SUMIF('SPACELOG 6 BP'!$F$2:$EE$2,CU$4,'SPACELOG 6 BP'!$F$7:$EE$7)+SUMIF('SPACELOG 7 BP'!$F$2:$EE$2,CU$4,'SPACELOG 7 BP'!$F$7:$EE$7)+SUMIF('SPACELOG 8 BP'!$F$2:$EE$2,CU$4,'SPACELOG 8 BP'!$F$7:$EE$7)+SUMIF('SPACELOG 9 BP'!$F$2:$EE$2,CU$4,'SPACELOG 9 BP'!$F$7:$EE$7)+SUMIF('SPACELOG 10 BP'!$F$2:$EE$2,CU$4,'SPACELOG 10 BP'!$F$7:$EE$7)+SUMIF('SPACELOG 11 BP'!$F$2:$EE$2,CU$4,'SPACELOG 11 BP'!$F$7:$EE$7)+SUMIF('SPACELOG 12 BP'!$F$2:$EE$2,CU$4,'SPACELOG 12 BP'!$F$7:$EE$7) -> 128185 | CV7: =SUMIF('reporting montigny'!$F$2:$EE$2,CV$4,'reporting montigny'!$F$7:$EE$7)+SUMIF('reporting boissy'!$F$2:$EE$2,CV$4,'reporting boissy'!$F$7:$EE$7)+SUMIF('reporting moussy'!$F$2:$EE$2,CV$4,'reporting moussy'!$F$7:$EE$7)+SUMIF('reporting trappes'!$F$2:$EE$2,CV$4,'reporting trappes'!$F$7:$EE$7)+SUMIF('SPACELOG 5 BP'!$F$2:$EE$2,CV$4,'SPACELOG 5 BP'!$F$7:$EE$7)+SUMIF('SPACELOG 6 BP'!$F$2:$EE$2,CV$4,'SPACELOG 6 BP'!$F$7:$EE$7)+SUMIF('SPACELOG 7 BP'!$F$2:$EE$2,CV$4,'SPACELOG 7 BP'!$F$7:$EE$7)+SUMIF('SPACELOG 8 BP'!$F$2:$EE$2,CV$4,'SPACELOG 8 BP'!$F$7:$EE$7)+SUMIF('SPACELOG 9 BP'!$F$2:$EE$2,CV$4,'SPACELOG 9 BP'!$F$7:$EE$7)+SUMIF('SPACELOG 10 BP'!$F$2:$EE$2,CV$4,'SPACELOG 10 BP'!$F$7:$EE$7)+SUMIF('SPACELOG 11 BP'!$F$2:$EE$2,CV$4,'SPACELOG 11 BP'!$F$7:$EE$7)+SUMIF('SPACELOG 12 BP'!$F$2:$EE$2,CV$4,'SPACELOG 12 BP'!$F$7:$EE$7) -> 128185 | CW7: =SUMIF('reporting montigny'!$F$2:$EE$2,CW$4,'reporting montigny'!$F$7:$EE$7)+SUMIF('reporting boissy'!$F$2:$EE$2,CW$4,'reporting boissy'!$F$7:$EE$7)+SUMIF('reporting moussy'!$F$2:$EE$2,CW$4,'reporting moussy'!$F$7:$EE$7)+SUMIF('reporting trappes'!$F$2:$EE$2,CW$4,'reporting trappes'!$F$7:$EE$7)+SUMIF('SPACELOG 5 BP'!$F$2:$EE$2,CW$4,'SPACELOG 5 BP'!$F$7:$EE$7)+SUMIF('SPACELOG 6 BP'!$F$2:$EE$2,CW$4,'SPACELOG 6 BP'!$F$7:$EE$7)+SUMIF('SPACELOG 7 BP'!$F$2:$EE$2,CW$4,'SPACELOG 7 BP'!$F$7:$EE$7)+SUMIF('SPACELOG 8 BP'!$F$2:$EE$2,CW$4,'SPACELOG 8 BP'!$F$7:$EE$7)+SUMIF('SPACELOG 9 BP'!$F$2:$EE$2,CW$4,'SPACELOG 9 BP'!$F$7:$EE$7)+SUMIF('SPACELOG 10 BP'!$F$2:$EE$2,CW$4,'SPACELOG 10 BP'!$F$7:$EE$7)+SUMIF('SPACELOG 11 BP'!$F$2:$EE$2,CW$4,'SPACELOG 11 BP'!$F$7:$EE$7)+SUMIF('SPACELOG 12 BP'!$F$2:$EE$2,CW$4,'SPACELOG 12 BP'!$F$7:$EE$7) -> 128185 | CX7: =SUMIF('reporting montigny'!$F$2:$EE$2,CX$4,'reporting montigny'!$F$7:$EE$7)+SUMIF('reporting boissy'!$F$2:$EE$2,CX$4,'reporting boissy'!$F$7:$EE$7)+SUMIF('reporting moussy'!$F$2:$EE$2,CX$4,'reporting moussy'!$F$7:$EE$7)+SUMIF('reporting trappes'!$F$2:$EE$2,CX$4,'reporting trappes'!$F$7:$EE$7)+SUMIF('SPACELOG 5 BP'!$F$2:$EE$2,CX$4,'SPACELOG 5 BP'!$F$7:$EE$7)+SUMIF('SPACELOG 6 BP'!$F$2:$EE$2,CX$4,'SPACELOG 6 BP'!$F$7:$EE$7)+SUMIF('SPACELOG 7 BP'!$F$2:$EE$2,CX$4,'SPACELOG 7 BP'!$F$7:$EE$7)+SUMIF('SPACELOG 8 BP'!$F$2:$EE$2,CX$4,'SPACELOG 8 BP'!$F$7:$EE$7)+SUMIF('SPACELOG 9 BP'!$F$2:$EE$2,CX$4,'SPACELOG 9 BP'!$F$7:$EE$7)+SUMIF('SPACELOG 10 BP'!$F$2:$EE$2,CX$4,'SPACELOG 10 BP'!$F$7:$EE$7)+SUMIF('SPACELOG 11 BP'!$F$2:$EE$2,CX$4,'SPACELOG 11 BP'!$F$7:$EE$7)+SUMIF('SPACELOG 12 BP'!$F$2:$EE$2,CX$4,'SPACELOG 12 BP'!$F$7:$EE$7) -> 128185 | CY7: =SUMIF('reporting montigny'!$F$2:$EE$2,CY$4,'reporting montigny'!$F$7:$EE$7)+SUMIF('reporting boissy'!$F$2:$EE$2,CY$4,'reporting boissy'!$F$7:$EE$7)+SUMIF('reporting moussy'!$F$2:$EE$2,CY$4,'reporting moussy'!$F$7:$EE$7)+SUMIF('reporting trappes'!$F$2:$EE$2,CY$4,'reporting trappes'!$F$7:$EE$7)+SUMIF('SPACELOG 5 BP'!$F$2:$EE$2,CY$4,'SPACELOG 5 BP'!$F$7:$EE$7)+SUMIF('SPACELOG 6 BP'!$F$2:$EE$2,CY$4,'SPACELOG 6 BP'!$F$7:$EE$7)+SUMIF('SPACELOG 7 BP'!$F$2:$EE$2,CY$4,'SPACELOG 7 BP'!$F$7:$EE$7)+SUMIF('SPACELOG 8 BP'!$F$2:$EE$2,CY$4,'SPACELOG 8 BP'!$F$7:$EE$7)+SUMIF('SPACELOG 9 BP'!$F$2:$EE$2,CY$4,'SPACELOG 9 BP'!$F$7:$EE$7)+SUMIF('SPACELOG 10 BP'!$F$2:$EE$2,CY$4,'SPACELOG 10 BP'!$F$7:$EE$7)+SUMIF('SPACELOG 11 BP'!$F$2:$EE$2,CY$4,'SPACELOG 11 BP'!$F$7:$EE$7)+SUMIF('SPACELOG 12 BP'!$F$2:$EE$2,CY$4,'SPACELOG 12 BP'!$F$7:$EE$7) -> 128185 | CZ7: =SUMIF('reporting montigny'!$F$2:$EE$2,CZ$4,'reporting montigny'!$F$7:$EE$7)+SUMIF('reporting boissy'!$F$2:$EE$2,CZ$4,'reporting boissy'!$F$7:$EE$7)+SUMIF('reporting moussy'!$F$2:$EE$2,CZ$4,'reporting moussy'!$F$7:$EE$7)+SUMIF('reporting trappes'!$F$2:$EE$2,CZ$4,'reporting trappes'!$F$7:$EE$7)+SUMIF('SPACELOG 5 BP'!$F$2:$EE$2,CZ$4,'SPACELOG 5 BP'!$F$7:$EE$7)+SUMIF('SPACELOG 6 BP'!$F$2:$EE$2,CZ$4,'SPACELOG 6 BP'!$F$7:$EE$7)+SUMIF('SPACELOG 7 BP'!$F$2:$EE$2,CZ$4,'SPACELOG 7 BP'!$F$7:$EE$7)+SUMIF('SPACELOG 8 BP'!$F$2:$EE$2,CZ$4,'SPACELOG 8 BP'!$F$7:$EE$7)+SUMIF('SPACELOG 9 BP'!$F$2:$EE$2,CZ$4,'SPACELOG 9 BP'!$F$7:$EE$7)+SUMIF('SPACELOG 10 BP'!$F$2:$EE$2,CZ$4,'SPACELOG 10 BP'!$F$7:$EE$7)+SUMIF('SPACELOG 11 BP'!$F$2:$EE$2,CZ$4,'SPACELOG 11 BP'!$F$7:$EE$7)+SUMIF('SPACELOG 12 BP'!$F$2:$EE$2,CZ$4,'SPACELOG 12 BP'!$F$7:$EE$7) -> 128185 | ... DD7: =SUMIF('reporting montigny'!$F$2:$EE$2,DD$4,'reporting montigny'!$F$7:$EE$7)+SUMIF('reporting boissy'!$F$2:$EE$2,DD$4,'reporting boissy'!$F$7:$EE$7)+SUMIF('reporting moussy'!$F$2:$EE$2,DD$4,'reporting moussy'!$F$7:$EE$7)+SUMIF('reporting trappes'!$F$2:$EE$2,DD$4,'reporting trappes'!$F$7:$EE$7)+SUMIF('SPACELOG 5 BP'!$F$2:$EE$2,DD$4,'SPACELOG 5 BP'!$F$7:$EE$7)+SUMIF('SPACELOG 6 BP'!$F$2:$EE$2,DD$4,'SPACELOG 6 BP'!$F$7:$EE$7)+SUMIF('SPACELOG 7 BP'!$F$2:$EE$2,DD$4,'SPACELOG 7 BP'!$F$7:$EE$7)+SUMIF('SPACELOG 8 BP'!$F$2:$EE$2,DD$4,'SPACELOG 8 BP'!$F$7:$EE$7)+SUMIF('SPACELOG 9 BP'!$F$2:$EE$2,DD$4,'SPACELOG 9 BP'!$F$7:$EE$7)+SUMIF('SPACELOG 10 BP'!$F$2:$EE$2,DD$4,'SPACELOG 10 BP'!$F$7:$EE$7)+SUMIF('SPACELOG 11 BP'!$F$2:$EE$2,DD$4,'SPACELOG 11 BP'!$F$7:$EE$7)+SUMIF('SPACELOG 12 BP'!$F$2:$EE$2,DD$4,'SPACELOG 12 BP'!$F$7:$EE$7) -> 128185 | DE7: =SUM(CS7:DD7) -> 1538220 | DF7: =SUMIF('reporting montigny'!$F$2:$EE$2,DF$4,'reporting montigny'!$F$7:$EE$7)+SUMIF('reporting boissy'!$F$2:$EE$2,DF$4,'reporting boissy'!$F$7:$EE$7)+SUMIF('reporting moussy'!$F$2:$EE$2,DF$4,'reporting moussy'!$F$7:$EE$7)+SUMIF('reporting trappes'!$F$2:$EE$2,DF$4,'reporting trappes'!$F$7:$EE$7)+SUMIF('SPACELOG 5 BP'!$F$2:$EE$2,DF$4,'SPACELOG 5 BP'!$F$7:$EE$7)+SUMIF('SPACELOG 6 BP'!$F$2:$EE$2,DF$4,'SPACELOG 6 BP'!$F$7:$EE$7)+SUMIF('SPACELOG 7 BP'!$F$2:$EE$2,DF$4,'SPACELOG 7 BP'!$F$7:$EE$7)+SUMIF('SPACELOG 8 BP'!$F$2:$EE$2,DF$4,'SPACELOG 8 BP'!$F$7:$EE$7)+SUMIF('SPACELOG 9 BP'!$F$2:$EE$2,DF$4,'SPACELOG 9 BP'!$F$7:$EE$7)+SUMIF('SPACELOG 10 BP'!$F$2:$EE$2,DF$4,'SPACELOG 10 BP'!$F$7:$EE$7)+SUMIF('SPACELOG 11 BP'!$F$2:$EE$2,DF$4,'SPACELOG 11 BP'!$F$7:$EE$7)+SUMIF('SPACELOG 12 BP'!$F$2:$EE$2,DF$4,'SPACELOG 12 BP'!$F$7:$EE$7) -> 128185 | DG7: =SUMIF('reporting montigny'!$F$2:$EE$2,DG$4,'reporting montigny'!$F$7:$EE$7)+SUMIF('reporting boissy'!$F$2:$EE$2,DG$4,'reporting boissy'!$F$7:$EE$7)+SUMIF('reporting moussy'!$F$2:$EE$2,DG$4,'reporting moussy'!$F$7:$EE$7)+SUMIF('reporting trappes'!$F$2:$EE$2,DG$4,'reporting trappes'!$F$7:$EE$7)+SUMIF('SPACELOG 5 BP'!$F$2:$EE$2,DG$4,'SPACELOG 5 BP'!$F$7:$EE$7)+SUMIF('SPACELOG 6 BP'!$F$2:$EE$2,DG$4,'SPACELOG 6 BP'!$F$7:$EE$7)+SUMIF('SPACELOG 7 BP'!$F$2:$EE$2,DG$4,'SPACELOG 7 BP'!$F$7:$EE$7)+SUMIF('SPACELOG 8 BP'!$F$2:$EE$2,DG$4,'SPACELOG 8 BP'!$F$7:$EE$7)+SUMIF('SPACELOG 9 BP'!$F$2:$EE$2,DG$4,'SPACELOG 9 BP'!$F$7:$EE$7)+SUMIF('SPACELOG 10 BP'!$F$2:$EE$2,DG$4,'SPACELOG 10 BP'!$F$7:$EE$7)+SUMIF('SPACELOG 11 BP'!$F$2:$EE$2,DG$4,'SPACELOG 11 BP'!$F$7:$EE$7)+SUMIF('SPACELOG 12 BP'!$F$2:$EE$2,DG$4,'SPACELOG 12 BP'!$F$7:$EE$7) -> 128185 | DH7: =SUMIF('reporting montigny'!$F$2:$EE$2,DH$4,'reporting montigny'!$F$7:$EE$7)+SUMIF('reporting boissy'!$F$2:$EE$2,DH$4,'reporting boissy'!$F$7:$EE$7)+SUMIF('reporting moussy'!$F$2:$EE$2,DH$4,'reporting moussy'!$F$7:$EE$7)+SUMIF('reporting trappes'!$F$2:$EE$2,DH$4,'reporting trappes'!$F$7:$EE$7)+SUMIF('SPACELOG 5 BP'!$F$2:$EE$2,DH$4,'SPACELOG 5 BP'!$F$7:$EE$7)+SUMIF('SPACELOG 6 BP'!$F$2:$EE$2,DH$4,'SPACELOG 6 BP'!$F$7:$EE$7)+SUMIF('SPACELOG 7 BP'!$F$2:$EE$2,DH$4,'SPACELOG 7 BP'!$F$7:$EE$7)+SUMIF('SPACELOG 8 BP'!$F$2:$EE$2,DH$4,'SPACELOG 8 BP'!$F$7:$EE$7)+SUMIF('SPACELOG 9 BP'!$F$2:$EE$2,DH$4,'SPACELOG 9 BP'!$F$7:$EE$7)+SUMIF('SPACELOG 10 BP'!$F$2:$EE$2,DH$4,'SPACELOG 10 BP'!$F$7:$EE$7)+SUMIF('SPACELOG 11 BP'!$F$2:$EE$2,DH$4,'SPACELOG 11 BP'!$F$7:$EE$7)+SUMIF('SPACELOG 12 BP'!$F$2:$EE$2,DH$4,'SPACELOG 12 BP'!$F$7:$EE$7) -> 128185 | DI7: =SUMIF('reporting montigny'!$F$2:$EE$2,DI$4,'reporting montigny'!$F$7:$EE$7)+SUMIF('reporting boissy'!$F$2:$EE$2,DI$4,'reporting boissy'!$F$7:$EE$7)+SUMIF('reporting moussy'!$F$2:$EE$2,DI$4,'reporting moussy'!$F$7:$EE$7)+SUMIF('reporting trappes'!$F$2:$EE$2,DI$4,'reporting trappes'!$F$7:$EE$7)+SUMIF('SPACELOG 5 BP'!$F$2:$EE$2,DI$4,'SPACELOG 5 BP'!$F$7:$EE$7)+SUMIF('SPACELOG 6 BP'!$F$2:$EE$2,DI$4,'SPACELOG 6 BP'!$F$7:$EE$7)+SUMIF('SPACELOG 7 BP'!$F$2:$EE$2,DI$4,'SPACELOG 7 BP'!$F$7:$EE$7)+SUMIF('SPACELOG 8 BP'!$F$2:$EE$2,DI$4,'SPACELOG 8 BP'!$F$7:$EE$7)+SUMIF('SPACELOG 9 BP'!$F$2:$EE$2,DI$4,'SPACELOG 9 BP'!$F$7:$EE$7)+SUMIF('SPACELOG 10 BP'!$F$2:$EE$2,DI$4,'SPACELOG 10 BP'!$F$7:$EE$7)+SUMIF('SPACELOG 11 BP'!$F$2:$EE$2,DI$4,'SPACELOG 11 BP'!$F$7:$EE$7)+SUMIF('SPACELOG 12 BP'!$F$2:$EE$2,DI$4,'SPACELOG 12 BP'!$F$7:$EE$7) -> 128185 | DJ7: =SUMIF('reporting montigny'!$F$2:$EE$2,DJ$4,'reporting montigny'!$F$7:$EE$7)+SUMIF('reporting boissy'!$F$2:$EE$2,DJ$4,'reporting boissy'!$F$7:$EE$7)+SUMIF('reporting moussy'!$F$2:$EE$2,DJ$4,'reporting moussy'!$F$7:$EE$7)+SUMIF('reporting trappes'!$F$2:$EE$2,DJ$4,'reporting trappes'!$F$7:$EE$7)+SUMIF('SPACELOG 5 BP'!$F$2:$EE$2,DJ$4,'SPACELOG 5 BP'!$F$7:$EE$7)+SUMIF('SPACELOG 6 BP'!$F$2:$EE$2,DJ$4,'SPACELOG 6 BP'!$F$7:$EE$7)+SUMIF('SPACELOG 7 BP'!$F$2:$EE$2,DJ$4,'SPACELOG 7 BP'!$F$7:$EE$7)+SUMIF('SPACELOG 8 BP'!$F$2:$EE$2,DJ$4,'SPACELOG 8 BP'!$F$7:$EE$7)+SUMIF('SPACELOG 9 BP'!$F$2:$EE$2,DJ$4,'SPACELOG 9 BP'!$F$7:$EE$7)+SUMIF('SPACELOG 10 BP'!$F$2:$EE$2,DJ$4,'SPACELOG 10 BP'!$F$7:$EE$7)+SUMIF('SPACELOG 11 BP'!$F$2:$EE$2,DJ$4,'SPACELOG 11 BP'!$F$7:$EE$7)+SUMIF('SPACELOG 12 BP'!$F$2:$EE$2,DJ$4,'SPACELOG 12 BP'!$F$7:$EE$7) -> 128185 | DK7: =SUMIF('reporting montigny'!$F$2:$EE$2,DK$4,'reporting montigny'!$F$7:$EE$7)+SUMIF('reporting boissy'!$F$2:$EE$2,DK$4,'reporting boissy'!$F$7:$EE$7)+SUMIF('reporting moussy'!$F$2:$EE$2,DK$4,'reporting moussy'!$F$7:$EE$7)+SUMIF('reporting trappes'!$F$2:$EE$2,DK$4,'reporting trappes'!$F$7:$EE$7)+SUMIF('SPACELOG 5 BP'!$F$2:$EE$2,DK$4,'SPACELOG 5 BP'!$F$7:$EE$7)+SUMIF('SPACELOG 6 BP'!$F$2:$EE$2,DK$4,'SPACELOG 6 BP'!$F$7:$EE$7)+SUMIF('SPACELOG 7 BP'!$F$2:$EE$2,DK$4,'SPACELOG 7 BP'!$F$7:$EE$7)+SUMIF('SPACELOG 8 BP'!$F$2:$EE$2,DK$4,'SPACELOG 8 BP'!$F$7:$EE$7)+SUMIF('SPACELOG 9 BP'!$F$2:$EE$2,DK$4,'SPACELOG 9 BP'!$F$7:$EE$7)+SUMIF('SPACELOG 10 BP'!$F$2:$EE$2,DK$4,'SPACELOG 10 BP'!$F$7:$EE$7)+SUMIF('SPACELOG 11 BP'!$F$2:$EE$2,DK$4,'SPACELOG 11 BP'!$F$7:$EE$7)+SUMIF('SPACELOG 12 BP'!$F$2:$EE$2,DK$4,'SPACELOG 12 BP'!$F$7:$EE$7) -> 128185 | DL7: =SUMIF('reporting montigny'!$F$2:$EE$2,DL$4,'reporting montigny'!$F$7:$EE$7)+SUMIF('reporting boissy'!$F$2:$EE$2,DL$4,'reporting boissy'!$F$7:$EE$7)+SUMIF('reporting moussy'!$F$2:$EE$2,DL$4,'reporting moussy'!$F$7:$EE$7)+SUMIF('reporting trappes'!$F$2:$EE$2,DL$4,'reporting trappes'!$F$7:$EE$7)+SUMIF('SPACELOG 5 BP'!$F$2:$EE$2,DL$4,'SPACELOG 5 BP'!$F$7:$EE$7)+SUMIF('SPACELOG 6 BP'!$F$2:$EE$2,DL$4,'SPACELOG 6 BP'!$F$7:$EE$7)+SUMIF('SPACELOG 7 BP'!$F$2:$EE$2,DL$4,'SPACELOG 7 BP'!$F$7:$EE$7)+SUMIF('SPACELOG 8 BP'!$F$2:$EE$2,DL$4,'SPACELOG 8 BP'!$F$7:$EE$7)+SUMIF('SPACELOG 9 BP'!$F$2:$EE$2,DL$4,'SPACELOG 9 BP'!$F$7:$EE$7)+SUMIF('SPACELOG 10 BP'!$F$2:$EE$2,DL$4,'SPACELOG 10 BP'!$F$7:$EE$7)+SUMIF('SPACELOG 11 BP'!$F$2:$EE$2,DL$4,'SPACELOG 11 BP'!$F$7:$EE$7)+SUMIF('SPACELOG 12 BP'!$F$2:$EE$2,DL$4,'SPACELOG 12 BP'!$F$7:$EE$7) -> 128185 | DM7: =SUMIF('reporting montigny'!$F$2:$EE$2,DM$4,'reporting montigny'!$F$7:$EE$7)+SUMIF('reporting boissy'!$F$2:$EE$2,DM$4,'reporting boissy'!$F$7:$EE$7)+SUMIF('reporting moussy'!$F$2:$EE$2,DM$4,'reporting moussy'!$F$7:$EE$7)+SUMIF('reporting trappes'!$F$2:$EE$2,DM$4,'reporting trappes'!$F$7:$EE$7)+SUMIF('SPACELOG 5 BP'!$F$2:$EE$2,DM$4,'SPACELOG 5 BP'!$F$7:$EE$7)+SUMIF('SPACELOG 6 BP'!$F$2:$EE$2,DM$4,'SPACELOG 6 BP'!$F$7:$EE$7)+SUMIF('SPACELOG 7 BP'!$F$2:$EE$2,DM$4,'SPACELOG 7 BP'!$F$7:$EE$7)+SUMIF('SPACELOG 8 BP'!$F$2:$EE$2,DM$4,'SPACELOG 8 BP'!$F$7:$EE$7)+SUMIF('SPACELOG 9 BP'!$F$2:$EE$2,DM$4,'SPACELOG 9 BP'!$F$7:$EE$7)+SUMIF('SPACELOG 10 BP'!$F$2:$EE$2,DM$4,'SPACELOG 10 BP'!$F$7:$EE$7)+SUMIF('SPACELOG 11 BP'!$F$2:$EE$2,DM$4,'SPACELOG 11 BP'!$F$7:$EE$7)+SUMIF('SPACELOG 12 BP'!$F$2:$EE$2,DM$4,'SPACELOG 12 BP'!$F$7:$EE$7) -> 128185 | ... DQ7: =SUMIF('reporting montigny'!$F$2:$EE$2,DQ$4,'reporting montigny'!$F$7:$EE$7)+SUMIF('reporting boissy'!$F$2:$EE$2,DQ$4,'reporting boissy'!$F$7:$EE$7)+SUMIF('reporting moussy'!$F$2:$EE$2,DQ$4,'reporting moussy'!$F$7:$EE$7)+SUMIF('reporting trappes'!$F$2:$EE$2,DQ$4,'reporting trappes'!$F$7:$EE$7)+SUMIF('SPACELOG 5 BP'!$F$2:$EE$2,DQ$4,'SPACELOG 5 BP'!$F$7:$EE$7)+SUMIF('SPACELOG 6 BP'!$F$2:$EE$2,DQ$4,'SPACELOG 6 BP'!$F$7:$EE$7)+SUMIF('SPACELOG 7 BP'!$F$2:$EE$2,DQ$4,'SPACELOG 7 BP'!$F$7:$EE$7)+SUMIF('SPACELOG 8 BP'!$F$2:$EE$2,DQ$4,'SPACELOG 8 BP'!$F$7:$EE$7)+SUMIF('SPACELOG 9 BP'!$F$2:$EE$2,DQ$4,'SPACELOG 9 BP'!$F$7:$EE$7)+SUMIF('SPACELOG 10 BP'!$F$2:$EE$2,DQ$4,'SPACELOG 10 BP'!$F$7:$EE$7)+SUMIF('SPACELOG 11 BP'!$F$2:$EE$2,DQ$4,'SPACELOG 11 BP'!$F$7:$EE$7)+SUMIF('SPACELOG 12 BP'!$F$2:$EE$2,DQ$4,'SPACELOG 12 BP'!$F$7:$EE$7) -> 128185 | DR7: =SUM(DF7:DQ7) -> 1538220
